Workbook

Sheet private_equity
B2: Income yield | C2: {=AVERAGE(IF(ISNUMBER(ma_deal_list!K2:K799),ma_deal_list!K2:K799))/2} -> 0.035948177 | D2: US M&A deal private equity LBO small cap median LTM EBIT/EV multiple / 2
B3: Real growth rate | C3: 0.03
B4: Real unlevered return | C4: =SUM(C2:C3) -> 0.065948177
B5: Debt to Equity | C5: 0.52 | D5: Taken from AQR 2025 CMA. For the post-2008 period, we interpolate annual D/E ratios from Pitchbook/Bain. Pre-2008, we assume an aggregate D/E ratio that tapers from 300% in the 1990s to the 150% D/E reported in 2008. Although historical simulations often assume a constant D/E ratio of, say, 200% over time, PE leverage levels have been trending lower despite lower funding costs.30 In principle, higher leverage (D/E) should boost equity returns if operating income is greater than the interest expense on the debt. In reality, however, Axelson et al. (2013) showed that low funding costs and high leverage tend to coincide with hot, overpriced vintages that have lower future returns. Our usage of PE yield and multiple expansion partly captures this effect.
B6: Real cost of debt | C6: =cost_of_debt!B280 -> 0.031379267
B7: Real levered return | C7: =C4+C5*(C4-C6) -> 0.083924011
B8: Multiple expansion | C8: 0.03 | D8: Taken from AQR 2025 CMA. Multiple Expansion: The principle of meanreversion suggests that PE multiple expansion is more likely if it has an initial discount versus the market. Hence, we estimate the return from multiple expansion as the annualized return if PE multiples converged partly, say 20% of the way, toward the initial public market multiple, over the lifetime of the deal, assumed to be six years. We f loor this return at zero; that is, we do not allow for multiple compression, as there is evidence that PE GPs delay exits so as to sell at higher multiples. We assume no multiple expansion in our yieldbased frameworks for passively managed public equities and fixed income. However, we make an exception for PE due to its active ownership and some evidence that PE GPs can time deal entries and exits.33 Given the arbitrary nature of our estimate, our general skepticism around multiple expansion for any asset class, and the noise in data on PE purchase multiples, we choose to apply only a conservative, partial convergence towards the market multiple.34
B9: Gross real expected return | C9: =C7+C8 -> 0.11392401
B10: Fees | C10: 0.04
B11: Net expected real return | C11: =C9-C10 -> 0.073924011
B12: Expected inflation | C12: =cost_of_debt!D224/100 -> 0.022839
B13: Net expected return | C13: =C11+C12 -> 0.096763011
F16: yu | G16: gu | H16: ru = yu + gu | I16: D/E | J16: kd | K16: rl = ru + (D/E)*(ru - kd) | L16: m | M16: rg = rl + m | N16: f | O16: rr = rg - f | P16: i | Q16: r = rr + i
F17: Income Yield | G17: Real Growth Rate | H17: Real Unlevered Return | I17: Debt to Equity | J17: Real Cost of Debt | K17: Real levered Return | L17: Multiple Expansion | M17: Gross Real Expected Return | N17: Fees | O17: Net Expected Real Return | P17: Expected Inflation | Q17: Net Expected Return
F18: =VLOOKUP(F17,$B$2:$C$13,2,0) -> 0.035948177 | G18: =VLOOKUP(G17,$B$2:$C$13,2,0) -> 0.03 | H18: =VLOOKUP(H17,$B$2:$C$13,2,0) -> 0.065948177 | I18: =VLOOKUP(I17,$B$2:$C$13,2,0) -> 0.52 | J18: =VLOOKUP(J17,$B$2:$C$13,2,0) -> 0.031379267 | K18: =VLOOKUP(K17,$B$2:$C$13,2,0) -> 0.083924011 | L18: =VLOOKUP(L17,$B$2:$C$13,2,0) -> 0.03 | M18: =VLOOKUP(M17,$B$2:$C$13,2,0) -> 0.11392401 | ... Q18: =VLOOKUP(Q17,$B$2:$C$13,2,0) -> 0.096763011

Sheet ma_deal_list
A1: Deal Type | B1: Announce Date | C1: Target Name | D1: Acquirer Name | E1: Seller Name | F1: Announced Total Value (mil.) | G1: Payment Type | H1: Deal Status | I1: TV/EBITDA | J1: TV/EBIT | K1: EBIT/TV | L1: add D/E
A2: M&A | B2: 45723 | C2: Walgreens Boots Alliance Inc | D2: Sycamore Partners LLC | F2: 39411.56 | G2: Cash | H2: Completed | J2: 16.86 | K2: =1/J2 -> 0.059311981
A3: M&A | B3: 45845 | C3: Altice France SA/France | D3: Blackstone Inc | F3: 36360.73 | G3: Undisclosed | H3: Proposed | I3: 6.19 | J3: 15.67 | K3: =1/J3 -> 0.063816209
A4: M&A | B4: 45804 | C4: Hologic Inc | D4: Blackstone Inc,TPG Inc | F4: 16910 | G4: Cash | H4: Proposed | I4: 13.72 | J4: 19.16 | K4: =1/J4 -> 0.052192067
A5: M&A | B5: 45796 | C5: TXNM Energy Inc | D5: Blackstone Inc | F5: 11811.08 | G5: Cash | H5: Pending | I5: 13.16 | J5: 26.05 | K5: =1/J5 -> 0.038387716
A6: M&A | B6: 45890 | C6: Dayforce Inc | D6: Thoma Bravo LLC | F6: 11237.21 | G6: Cash | H6: Pending | I6: 35.07 | J6: 107.95 | K6: =1/J6 -> 0.0092635479
A7: M&A | B7: 45782 | C7: Skechers USA Inc | D7: 3G Capital Partners LP | F7: 10479.16 | G7: Cash or Stock | H7: Pending | I7: 6.87 | J7: 11.59 | K7: =1/J7 -> 0.086281277
A8: M&A | B8: 45630 | C8: ESR Group Ltd | D8: Starwood Capital Group LLC,Warburg Pincus LLC,Qatar Holding LLC,Sixth Street Partners LLC,SSW Partners LP | F8: 9381.14 | G8: Cash or Stock | H8: Completed | I8: 18.48 | J8: 20.01 | K8: =1/J8 -> 0.049975012
A9: M&A | B9: 45637 | C9: Resolution Life Group Holdings LP | D9: Nippon Life Insurance Co | E9: Blackstone Inc | F9: 8200 | G9: Cash | H9: Pending | J9: 16.17 | K9: =1/J9 -> 0.061842919
A10: M&A | B10: 45559 | C10: Smartsheet Inc | D10: Blackstone Inc,Vista Equity Partners LLC | F10: 7298.54 | G10: Cash | H10: Completed | J10: 98.53 | K10: =1/J10 -> 0.010149193
A11: M&A | B11: 45902 | C11: Air Lease Corp | D11: Sumitomo Corp,Sumitomo Mitsui Finance & Leasing Co Ltd,Brookfield Corp,Apollo Global Management Inc | F11: 7264.73 | G11: Cash | H11: Pending | I11: 2.89 | J11: 5.3 | K11: =1/J11 -> 0.18867925
A12: M&A | B12: 45840 | C12: Spectris PLC | D12: KKR & Co Inc | F12: 6466.7 | G12: Cash | H12: Pending | I12: 29.91 | J12: 48.61 | K12: =1/J12 -> 0.020571899
A13: M&A | B13: 45831 | C13: Spectris PLC | D13: Advent International Corp | F13: 6298 | G13: Cash | H13: Terminated | I13: 29.43 | J13: 47.83 | K13: =1/J13 -> 0.02090738
A14: M&A | B14: 45875 | C14: Enverus Inc | D14: Blackstone Inc | E14: Genstar Capital LLC (Fund: Genstar Capital Partners VIII LP),Hellman & Friedman LLC (Fund: Hellman & Friedman Capital Partners X LP) | F14: 6000 | G14: Cash | H14: Pending | J14: 63.6 | K14: =1/J14 -> 0.01572327
A15: M&A | B15: 45593 | C15: Yondr Group Ltd | D15: Caisse de Depot et Placement du Quebec,DigitalBridge Group Inc | E15: Cathexis Holdings LP | F15: 5800 | G15: Cash | H15: Completed | J15: 18.26 | K15: =1/J15 -> 0.054764513
A16: M&A | B16: 45722 | C16: YORK Holdings Co Ltd | D16: Bain Capital Private Equity LP | E16: Seven & i Holdings Co Ltd | F16: 5507.37 | G16: Cash | H16: Completed | J16: 27.35 | K16: =1/J16 -> 0.036563071
A17: M&A | B17: 45685 | C17: Surgery Partners Inc | D17: Bain Capital Private Equity LP | F17: 5156.99 | G17: Cash | H17: Proposed | I17: 13.2 | J17: 20.94 | K17: =1/J17 -> 0.047755492
A18: M&A | B18: 45600 | C18: Northwest Fiber LLC | D18: BCE Inc | E18: Canada Pension Plan Investment Board,British Columbia Investment Management Corp,Public Sector Pension Investment Board,Searchlight Capital Partners UK LLP (Fund: Searchlight Capital III LP),WaveDivision Capital LLC | F18: 5039.3 | G18: Cash | H18: Completed | J18: 12.87 | K18: =1/J18 -> 0.077700078
A19: M&A | B19: 45798 | C19: IO Products Inc | D19: OpenAI LLC | E19: Emerson Collective Investments LLC,Maverick Ventures Inc (Fund: Maverick Ventures Evergreen Fund),Sutter Hill Ventures LP (Fund: Bluebird Ventures I LP),SV Angel Management LLC (Fund: SV Angel Growth I LP),Thrive Capital Management LLC (Fund: Thrive Capital Partners XI) | F19: 5000 | G19: Stock | H19: Completed | J19: 12.89 | K19: =1/J19 -> 0.077579519
A20: M&A | B20: 45577 | C20: Fuji Soft Inc | D20: Bain Capital Private Equity LP | F20: 4422.44 | G20: Cash | H20: Terminated | I20: 26.5 | J20: 31.86 | K20: =1/J20 -> 0.03138732
A21: M&A | B21: 45695 | C21: SolarWinds Corp | D21: Turn/River Capital | F21: 4217.81 | G21: Cash | H21: Completed | J21: 41.85 | K21: =1/J21 -> 0.023894863
A22: M&A | B22: 45740 | C22: Dun & Bradstreet Holdings Inc | D22: Clearlake Capital Group LP | F22: 4039.87 | G22: Cash | H22: Completed | I22: 5.16 | J22: 20.74 | K22: =1/J22 -> 0.048216008
A23: M&A | B23: 45572 | C23: Barnes Group Inc | D23: Apollo Global Management Inc | F23: 3511.94 | G23: Cash | H23: Completed | I23: 17.15 | J23: 39.46 | K23: =1/J23 -> 0.025342119
A24: M&A | B24: 45637 | C24: Patterson Cos Inc | D24: Patient Square Capital LP | F24: 3423.33 | G24: Cash | H24: Completed | I24: 9.02 | J24: 13.54 | K24: =1/J24 -> 0.073855244
A25: M&A | B25: 45728 | C25: Gerresheimer AG | D25: Warburg Pincus LLC | F25: 3390.55 | G25: Cash | H25: Withdrawn | I25: 7.85 | J25: 15.74 | K25: =1/J25 -> 0.063532402
A26: M&A | B26: 45695 | C26: Mitsubishi Tanabe Pharma Corp | D26: Bain Capital Private Equity LP | E26: Mitsubishi Chemical Group Corp | F26: 3362.43 | G26: Cash | H26: Pending | J26: 11.33 | K26: =1/J26 -> 0.088261253
A27: M&A | B27: 45875 | C27: TechnoPro Holdings Inc | D27: Blackstone Inc | F27: 3319.8 | G27: Cash | H27: Pending | I27: 19.42 | J27: 22.32 | K27: =1/J27 -> 0.044802867
A28: M&A | B28: 45599 | C28: Air Transport Services Group Inc | D28: Stonepeak Partners LP | F28: 3167.19 | G28: Cash | H28: Completed | I28: 5.62 | J28: 15.85 | K28: =1/J28 -> 0.063091483
A29: M&A | B29: 45761 | C29: OSTTRA | D29: KKR & Co Inc | E29: S&P Global Inc,CME Group Inc | F29: 3100 | G29: Cash | H29: Pending | J29: 12.87 | K29: =1/J29 -> 0.077700078
A30: M&A | B30: 45783 | C30: Exafunction Inc | D30: OpenAI Inc | E30: Kleiner Perkins Caufield & Byers LLC (Fund: Kleiner Perkins Caufield & Byers XX LLC),Founders Fund Management LLC/The (Fund: Founders Fund Growth II LP),Greenoaks Capital Management LLC (Fund: Greenoaks Capital Opportunities Fund V LP),General Catalyst Partners LLC (Fund: General Catalyst Gro... | F30: 3000 | G30: Cash | H30: Pending | J30: 13.75 | K30: =1/J30 -> 0.072727273
A31: M&A | B31: 45691 | C31: Triumph Group Inc | D31: Warburg Pincus LLC (Fund: Warburg Pincus Global Growth II),Berkshire Partners LLC (Fund: Berkshire Fund XI LP) | F31: 2871.96 | G31: Cash | H31: Completed | I31: 22.82 | J31: 33.22 | K31: =1/J31 -> 0.030102348
A32: M&A | B32: 45726 | C32: Moveworks Inc | D32: ServiceNow Inc | E32: Comerica Inc,Kleiner Perkins Caufield & Byers LLC,Lightspeed Management Co LLC,Alkeon Capital Management LLC,Tiger Global Management LLC,Bain Capital Venture Partners LLC,Sapphire Ventures LLC,ICONIQ Capital LLC | F32: 2850 | G32: Cash | H32: Pending | J32: 63.6 | K32: =1/J32 -> 0.01572327
A33: M&A | B33: 45744 | C33: Topcon Corp | D33: KKR & Co Inc | F33: 2844.65 | G33: Cash | H33: Pending | I33: 16.74 | J33: 38.08 | K33: =1/J33 -> 0.026260504
A34: M&A | B34: 45756 | C34: Karo Pharma AB | D34: KKR & Co Inc | E34: EQT AB | F34: 2755 | G34: Cash | H34: Pending | I34: 36.17 | J34: 11.33 | K34: =1/J34 -> 0.088261253
A35: M&A | B35: 45611 | C35: Fuji Soft Inc | D35: KKR & Co Inc | F35: 2736.03 | G35: Cash | H35: Completed | I35: 25.74 | J35: 30.95 | K35: =1/J35 -> 0.032310178
A36: M&A | B36: 45903 | C36: DiMeo Schneider & Associates LLC,Newport Private Wealth Inc,Wealthspire Advisors LP | D36: Madison Dearborn Partners LLC | E36: Aon PLC | F36: 2700 | G36: Cash | H36: Pending | K36: =1/J36 -> #VALUE!
A37: M&A | B37: 45628 | C37: Sunstone Hotel Investors Inc | D37: Trinity Investments LLC | F37: 2611.72 | G37: Cash | H37: Proposed | I37: 10.02 | J37: 22.01 | K37: =1/J37 -> 0.045433894
A38: M&A | B38: 45670 | C38: Scorpion Therapeutics Inc | D38: Eli Lilly & Co | E38: Wellington Management Group LLP,Mass General Brigham Inc,Janus Henderson Group PLC,Willett Advisors LLC,Boxer Capital LLC,Invus Group LLC/The (Fund: IFA PE Fund II LP),Omega Funds Investment Ltd,Logos Capital Partners Sarl (Fund: Logos Global Opportunities I),Woodline Partners LP,EcoR1 Capita... | F38: 2500 | G38: Cash | H38: Pending | J38: 23.39 | K38: =1/J38 -> 0.042753313
A39: M&A | B39: 45882 | C39: Sapiens International Corp NV | D39: Advent International Corp | F39: 2283.82 | G39: Cash | H39: Pending | I39: 20.73 | J39: 26.6 | K39: =1/J39 -> 0.037593985
A40: M&A | B40: 45602 | C40: Retail Opportunity Investments Corp | D40: Blackstone Inc | F40: 2251.36 | G40: Cash | H40: Completed | I40: 10.44 | J40: 20.5 | K40: =1/J40 -> 0.048780488
A41: M&A | B41: 45720 | C41: Sundyne Corp | D41: Honeywell International Inc | E41: Warburg Pincus LLC | F41: 2160 | G41: Cash | H41: Completed | J41: 8.68 | K41: =1/J41 -> 0.11520737
A42: M&A | B42: 45638 | C42: Insignia Financial Ltd | D42: Bain Capital Private Equity LP | F42: 2139.62 | G42: Cash | H42: Withdrawn | J42: 8.79 | K42: =1/J42 -> 0.11376564
A43: M&A | B43: 45771 | C43: New Day | D43: Bain Capital Private Equity LP,Pacific Investment Management Co LLC,KKR & Co Inc | F43: 2132.64 | G43: Cash | H43: Proposed | J43: 12.49 | K43: =1/J43 -> 0.080064051
A44: M&A | B44: 45814 | C44: Yinson Holdings BHD | D44: Stonepeak Partners LP | F44: 2127.6 | G44: Cash | H44: Proposed | I44: 3.07 | J44: 3.48 | K44: =1/J44 -> 0.28735632
A45: M&A | B45: 45860 | C45: Insignia Financial Ltd | D45: One Investment Administration Ltd,CC Capital Management LLC | F45: 2109.73 | G45: Cash | H45: Pending | J45: 8.79 | K45: =1/J45 -> 0.11376564
A46: M&A | B46: 45653 | C46: RED Lobster Hospitality LLC | D46: Golden Gate Capital LP | E46: Darden Restaurants Inc | F46: 2100 | G46: Cash | H46: Completed | J46: 58.57 | K46: =1/J46 -> 0.017073587
A47: M&A | B47: 45866 | C47: First National Financial Corp | D47: Birch Hill Equity Partners Management Inc (Fund: Birch Hill Equity Partners VI LP),Brookfield Corp (Fund: Brookfield Capital Partners VI LP) | F47: 2098.09 | G47: Cash | H47: Pending | I47: 1.58 | J47: 10.4 | K47: =1/J47 -> 0.096153846
A48: M&A | B48: 45572 | C48: Duckhorn Portfolio Inc/The | D48: Butterfly Equity LLC | F48: 1946.52 | G48: Cash | H48: Completed | I48: 14.11 | J48: 18.37 | K48: =1/J48 -> 0.054436581
A49: M&A | B49: 45880 | C49: MeridianLink Inc | D49: Centerbridge Partners LP | F49: 1905.89 | G49: Cash | H49: Pending | I49: 30.31 | J49: 411.11 | K49: =1/J49 -> 0.002432439
A50: M&A | B50: 45694 | C50: Encore Holdings LLC | D50: Permira Holdings LLP | F50: 1800 | G50: Cash | H50: Proposed | J50: 53.97 | K50: =1/J50 -> 0.018528812
A51: M&A | B51: 45629 | C51: INEOS AG | D51: KPS Capital Partners LP | E51: INEOS Ltd | F51: 1789.93 | G51: Cash | H51: Completed | J51: 8.06 | K51: =1/J51 -> 0.12406948
A52: M&A | B52: 45783 | C52: AvidXchange Holdings Inc | D52: Corpay Inc,TPG Capital LP/US (Fund: TPG LSI Equity LP) | F52: 1754.75 | G52: Cash | H52: Pending | I52: 49.72 | J52: 29.76 | K52: =1/J52 -> 0.033602151
A53: M&A | B53: 45797 | C53: Global Sea Containers Ltd | D53: Stonepeak Partners LP | E53: Bohai Leasing Co Ltd | F53: 1750 | G53: Cash | H53: Pending | J53: 9.65 | K53: =1/J53 -> 0.10362694
A54: M&A | B54: 45761 | C54: esure Group PLC | D54: Ageas SA/NV | E54: Bain Capital Private Equity LP | F54: 1705.13 | G54: Cash | H54: Pending | J54: 23.64 | K54: =1/J54 -> 0.042301184
A55: M&A | B55: 45710 | C55: VaxCare Corp | D55: Blackstone Inc | E55: Summit Partners LP,HLM Investments LLC,Echo Health Ventures LLC | F55: 1700 | G55: Cash | H55: Proposed | J55: 7.44 | K55: =1/J55 -> 0.1344086
A56: M&A | B56: 45890 | C56: Shermco Industries Inc | D56: Blackstone Inc | E56: Gryphon Investors Inc | F56: 1600 | G56: Cash and Debt | H56: Pending | J56: 9.56 | K56: =1/J56 -> 0.10460251
A57: M&A | B57: 45640 | C57: Forgital Group SpA | D57: Stonepeak Partners LP | E57: Carlyle Group Inc/The | F57: 1574.4 | G57: Cash | H57: Completed | J57: 17.47 | K57: =1/J57 -> 0.057240985
A58: M&A | B58: 45553 | C58: Cala Group Ltd | D58: Patron Capital Advisers LLP,Sixth Street Partners LLC (Fund: Sixth Street Mid-Stage Growth Partners LP) | E58: Legal & General Group PLC | F58: 1532.48 | G58: Cash | H58: Pending | J58: 17.41 | K58: =1/J58 -> 0.057438254
A59: M&A | B59: 45663 | C59: Sauer Brands Inc | D59: Advent International Corp | E59: Falfurrias Capital Partners LP | F59: 1500 | G59: Cash | H59: Completed | J59: 27.35 | K59: =1/J59 -> 0.036563071
A60: M&A | B60: 45890 | C60: International Paper Global Cellulose Fibers Holdings Sarl | D60: American Industrial Partners LP | E60: International Paper Co | F60: 1500 | G60: Cash | H60: Pending | J60: 8.97 | K60: =1/J60 -> 0.11148272
A61: M&A | B61: 45894 | C61: Verint Systems Inc | D61: Thoma Bravo LLC | F61: 1494.05 | G61: Cash | H61: Pending | I61: 9.24 | J61: 14.04 | K61: =1/J61 -> 0.071225071
A62: M&A | B62: 45841 | C62: Olo Inc | D62: Thoma Bravo LLC | F62: 1482.42 | G62: Cash | H62: Pending | J62: 334.45 | K62: =1/J62 -> 0.0029899836
A63: M&A | B63: 45712 | C63: Chemring Group PLC | D63: Bain Capital Private Equity LP | F63: 1412.93 | G63: Cash | H63: Proposed | I63: 13.47 | J63: 19.14 | K63: =1/J63 -> 0.052246604
A64: M&A | B64: 45582 | C64: Zuora Inc | D64: GIC Pte Ltd,Silver Lake Management LLC (Fund: Silver Lake Partners VII LP) | F64: 1390.33 | G64: Cash | H64: Completed | J64: 36.65 | K64: =1/J64 -> 0.02728513
A65: M&A | B65: 45880 | C65: WideOpenWest Inc | D65: Digital Bridge Holdings LLC,Crestview Partners LP/NY (Fund: Crestview Partners IV LP) | F65: 1302.27 | G65: Cash | H65: Pending | I65: 6.59 | J65: 226.33 | K65: =1/J65 -> 0.0044183272
A66: M&A | B66: 45797 | C66: AGS Health | D66: Blackstone Inc | E66: WindRose Health Investors LLC,Altaris Capital Partners LLC,EQT AB | F66: 1300 | G66: Cash | H66: Proposed | J66: 26.46 | K66: =1/J66 -> 0.037792895
A67: M&A | B67: 45839 | C67: Proten Pty Ltd | D67: KKR & Co Inc | E67: Aware Super Pty Ltd | F67: 1300 | G67: Cash | H67: Pending | J67: 50.62 | K67: =1/J67 -> 0.019755038
A68: M&A | B68: 45888 | C68: Jinju Industry Co Ltd,Renewus Co Ltd,DaewonGreenEnergy Co Ltd | D68: KKR & Co Inc | E68: SK ecoplant Co Ltd | F68: 1278.4 | G68: Cash | H68: Pending | K68: =1/J68 -> #VALUE!
A69: M&A | B69: 45601 | C69: Nexus AG | D69: TA Associates Management LP | F69: 1254.67 | G69: Cash | H69: Pending | I69: 22.55 | J69: 35.43 | K69: =1/J69 -> 0.028224668
A70: M&A | B70: 45828 | C70: Couchbase Inc | D70: Haveli Investment LP | F70: 1186.99 | G70: Cash | H70: Pending | J70: 24.15 | K70: =1/J70 -> 0.041407867
A71: M&A | B71: 45886 | C71: u-blox Holding AG | D71: Advent International Corp | F71: 1178.05 | G71: Cash | H71: Pending | J71: 20.94 | K71: =1/J71 -> 0.047755492
A72: M&A | B72: 45569 | C72: Vista Outdoor Products SpinCo | D72: Strategic Value Partners LLC | F72: 1175.56 | G72: Cash | H72: Completed | J72: 13.06 | K72: =1/J72 -> 0.076569678
A73: M&A | B73: 45860 | C73: Vicebio Ltd | D73: Sanofi | E73: Avoro Ventures LLC,UniQuest Ltd,Medicxi Ventures UK LLP (Fund: Medicxi IV LP),Goldman Sachs Group Inc/The (Fund: West Street Life Sciences I LP),TCG Crossover Management LLC (Fund: TCG Crossover Fund II LP),venBio Partners LLC (Fund: venBio Global Strategic Fund V LP) | F73: 1150 | G73: Cash | H73: Pending | J73: 23.39 | K73: =1/J73 -> 0.042753313
A74: M&A | B74: 45595 | C74: ADP AdvancedMD Inc | D74: Francisco Partners Management LLC | E74: Global Payments Inc | F74: 1125 | G74: Cash | H74: Completed | J74: 27.93 | K74: =1/J74 -> 0.035803795
A75: M&A | B75: 45775 | C75: SynXis Corp | D75: TPG Inc | E75: Sabre Corp | F75: 1100 | G75: Cash | H75: Completed | K75: =1/J75 -> #VALUE!
A76: M&A | B76: 45876 | C76: Meade Pipeline Co LLC | D76: Ares Management LLC | E76: XPLR Infrastructure LP,Meade Pipeline Investment LLC,Redwood Meade Midstream MPC LLC | F76: 1100 | G76: Cash | H76: Completed | J76: 18.84 | K76: =1/J76 -> 0.053078556
A77: M&A | B77: 45630 | C77: Learning Technologies Group PLC | D77: General Atlantic LP | F77: 1091.67 | G77: Cash | H77: Completed | I77: 8.17 | J77: 14.73 | K77: =1/J77 -> 0.067888663
A78: M&A | B78: 45628 | C78: HKBN Ltd | D78: I Squared Capital Advisors US LLC | F78: 1011.24 | G78: Cash | H78: Withdrawn | I78: 3.68 | J78: 8.87 | K78: =1/J78 -> 0.11273957
A79: M&A | B79: 45742 | C79: Family Dollar Stores Inc | D79: Brigade Capital Management LP,Macellum Capital Management LLC | E79: Dollar Tree Inc | F79: 1007.5 | G79: Cash | H79: Completed | J79: 11.22 | K79: =1/J79 -> 0.08912656
A80: M&A | B80: 45769 | C80: Biotage AB | D80: KKR & Co Inc | F80: 1005.99 | G80: Cash | H80: Completed | I80: 20.93 | J80: 31.45 | K80: =1/J80 -> 0.031796502
A81: M&A | B81: 45670 | C81: IDRx Inc | D81: GSK PLC | E81: Rock Springs Capital Management LP,Blackstone Multi-Asset Advisors LLC,Commodore Capital LP,Nextech Invest AG (Fund: Nextech VII Oncology Scsp),Andreessen Horowitz (Fund: AH Bio Fund IV LP),Casdin Capital LLC (Fund: Casdin Private Growth Equity Fund II LP),Forge Life Science Partners,RA Capit... | F81: 1000 | G81: Cash | H81: Completed | J81: 23.39 | K81: =1/J81 -> 0.042753313
A82: M&A | B82: 45678 | C82: Kantar Media UK Ltd | D82: HIG Capital LLC | E82: Kantar Global Holdings SARL | F82: 1000 | G82: Cash | H82: Completed | J82: 13.06 | K82: =1/J82 -> 0.076569678
A83: M&A | B83: 45840 | C83: Sizzling Platter LLC | D83: Bain Capital Private Equity LP | E83: Yukon Partners Management LLC,CapitalSpring LLC,Valor Equity Management LLC (Fund: Valor Equity Partners LP) | F83: 1000 | G83: Cash and Debt | H83: Pending | J83: 9.85 | K83: =1/J83 -> 0.10152284
A84: M&A | B84: 45700 | C84: Vermont Information Processing Inc | D84: Warburg Pincus LLC | F84: 1000 | G84: Cash | H84: Pending | J84: 58.57 | K84: =1/J84 -> 0.017073587
A85: M&A | B85: 45904 | C85: UST Healthproof Inc | D85: Bain Capital LP | E85: UST Holdings Ltd | F85: 1000 | G85: Cash | H85: Pending | J85: 17.33 | K85: =1/J85 -> 0.057703405
A86: M&A | B86: 45551 | C86: Sunrise Medical AG | D86: Platinum Equity LLC | E86: Nordic Capital Svenska AB | F86: 984.92 | G86: Cash | H86: Completed | J86: 15.6 | K86: =1/J86 -> 0.064102564
A87: M&A | B87: 45602 | C87: Avid Bioservices Inc | D87: Ampersand Management LLC (Fund: Ampersand 2022 LP),GHO Capital Partners LLP (Fund: GHO Capital IV LP) | F87: 982.93 | G87: Cash | H87: Completed | J87: 13.54 | K87: =1/J87 -> 0.073855244
A88: M&A | B88: 45888 | C88: Plymouth Industrial REIT Inc | D88: Sixth Street Partners LLC | F88: 966.48 | G88: Cash | H88: Proposed | I88: 8.9 | J88: 29.71 | K88: =1/J88 -> 0.033658701
A89: M&A | B89: 45695 | C89: Converge Technology Solutions Corp | D89: HIG Capital LLC | F89: 881.16 | G89: Cash | H89: Completed | I89: 9.11 | J89: 68.83 | K89: =1/J89 -> 0.014528549
A90: M&A | B90: 45642 | C90: DCP GCX Pipeline LLC | D90: ArcLight Capital Partners LLC | E90: Phillips 66 | F90: 865 | G90: Cash | H90: Pending | J90: 17.33 | K90: =1/J90 -> 0.057703405
A91: M&A | B91: 45789 | C91: Nissin Corp | D91: Bain Capital LP | F91: 825.69 | G91: Cash | H91: Pending | I91: 7.65 | J91: 13.47 | K91: =1/J91 -> 0.07423905
A92: M&A | B92: 45694 | C92: Altus Power Inc | D92: TPG Growth LLC | F92: 803.98 | G92: Cash | H92: Completed | I92: 11.37 | J92: 47.02 | K92: =1/J92 -> 0.021267546
A93: M&A | B93: 45883 | C93: Greenyard NV | D93: Solum Partners LP | F93: 784.41 | G93: Cash | H93: Completed | I93: 4.8 | J93: 13.73 | K93: =1/J93 -> 0.072833212
A94: M&A | B94: 45637 | C94: Figs Inc | D94: STORY3 Capital Partners LLC | F94: 769.58 | G94: Cash | H94: Proposed | I94: 20.81 | J94: 22.6 | K94: =1/J94 -> 0.044247788
A95: M&A | B95: 45785 | C95: FD Technologies PLC | D95: TA Associates Management LP | F95: 758.01 | G95: Cash | H95: Completed | I95: 29.76 | J95: 25.79 | K95: =1/J95 -> 0.038774719
A96: M&A | B96: 45729 | C96: GreenSquareDC Pty Ltd | D96: Partners Group Holding AG | F96: 753.24 | G96: Cash | H96: Completed | J96: 51.57 | K96: =1/J96 -> 0.019391119
A97: M&A | B97: 45762 | C97: Datagroup SE | D97: KKR & Co Inc | F97: 741.84 | G97: Cash | H97: Pending | I97: 8.18 | J97: 14.37 | K97: =1/J97 -> 0.069589422
A98: M&A | B98: 45874 | C98: Tinexta Spa | D98: Advent International Corp (Fund: Advent International GPE X LP),Nextalia Sgr SpA | F98: 697.39 | G98: Cash | H98: Pending | I98: 10.83 | J98: 25.77 | K98: =1/J98 -> 0.038804812
A99: M&A | B99: 45797 | C99: Estacionamientos y Servicios SA | D99: Tikehau Capital SCA | E99: HIG Capital LLC | F99: 675.42 | G99: Cash | H99: Completed | J99: 63.6 | K99: =1/J99 -> 0.01572327
A100: M&A | B100: 45693 | C100: FICT Ltd | D100: FormFactor Inc,MBK Partners Ltd (Fund: MBK Partners Fund VI LP) | E100: Advantage Partners LLP | F100: 656.6 | G100: Cash | H100: Completed | J100: 27.19 | K100: =1/J100 -> 0.036778227
...

Sheet cost_of_debt
A1: Date | B1: Index OAS to Treasury Curve Basis Points | C1: Nominal SOFR | D1: Expected inflation (US 10Y breakeven) | E1: Real SOFR
A2: 45525 | B2: 316.7254 | C2: 5.31 | D2: 2.0808 | E2: =C2-D2 -> 3.2292
A3: 45526 | B3: 310.83441 | C3: 5.31 | D3: 2.102 | E3: =C3-D3 -> 3.208
A4: 45527 | B4: 309.6752 | C4: 5.33 | D4: 2.123 | E4: =C4-D4 -> 3.207
A5: 45530 | B5: 305.44131 | C5: 5.34 | D5: 2.1439 | E5: =C5-D5 -> 3.1961
A6: 45531 | B6: 307.75989 | C6: 5.35 | D6: 2.1522 | E6: =C6-D6 -> 3.1978
A7: 45532 | B7: 307.65741 | C7: 5.35 | D7: 2.1535 | E7: =C7-D7 -> 3.1965
A8: 45533 | B8: 304.3891 | C8: 5.33 | D8: 2.1597 | E8: =C8-D8 -> 3.1703
A9: 45534 | B9: 301.6766 | C9: 5.32 | D9: 2.152 | E9: =C9-D9 -> 3.168
A10: 45537 | B10: 304.86359 | C10: 5.32 | D10: #N/A | E10: =C10-D10 -> #N/A
A11: 45538 | B11: 320.1131 | C11: 5.34 | D11: 2.1131 | E11: =C11-D11 -> 3.2269
A12: 45539 | B12: 324.2836 | C12: 5.35 | D12: 2.0614 | E12: =C12-D12 -> 3.2886
A13: 45540 | B13: 319.0123 | C13: 5.35 | D13: 2.0485 | E13: =C13-D13 -> 3.3015
A14: 45541 | B14: 326.7529 | C14: 5.34 | D14: 2.0354 | E14: =C14-D14 -> 3.3046
A15: 45544 | B15: 324.80969 | C15: 5.34 | D15: 2.044 | E15: =C15-D15 -> 3.296
A16: 45545 | B16: 334.8508 | C16: 5.33 | D16: 2.0308 | E16: =C16-D16 -> 3.2992
A17: 45546 | B17: 334.19479 | C17: 5.32 | D17: 2.0436 | E17: =C17-D17 -> 3.2764
A18: 45547 | B18: 329.88611 | C18: 5.33 | D18: 2.0642 | E18: =C18-D18 -> 3.2658
A19: 45548 | B19: 326.6824 | C19: 5.33 | D19: 2.0818 | E19: =C19-D19 -> 3.2482
A20: 45551 | B20: 324.8692 | C20: 5.38 | D20: 2.0895 | E20: =C20-D20 -> 3.2905
A21: 45552 | B21: 316.95999 | C21: 5.38 | D21: 2.1084 | E21: =C21-D21 -> 3.2716
A22: 45553 | B22: 311.98969 | C22: 5.33 | D22: 2.1114 | E22: =C22-D22 -> 3.2186
... A39: 45576 | B39: 293.93631 | C39: 4.81 | D39: 2.3324 | E39: =C39-D39 -> 2.4776
A40: 45579 | B40: 293.93631 | C40: 4.81 | D40: #N/A | E40: =C40-D40 -> #N/A
A41: 45580 | B41: 288.8512 | C41: 4.86 | D41: 2.2778 | E41: =C41-D41 -> 2.5822
A42: 45581 | B42: 286.4241 | C42: 4.86 | D42: 2.2709 | E42: =C42-D42 -> 2.5891
A43: 45582 | B43: 284.185 | C43: 4.85 | D43: 2.3105 | E43: =C43-D43 -> 2.5395
A44: 45583 | B44: 285.35751 | C44: 4.84 | D44: 2.3064 | E44: =C44-D44 -> 2.5336
A45: 45586 | B45: 282.92151 | C45: 4.82 | D45: 2.3178 | E45: =C45-D45 -> 2.5022
A46: 45587 | B46: 287.6691 | C46: 4.83 | D46: 2.3368 | E46: =C46-D46 -> 2.4932
A47: 45588 | B47: 289.6879 | C47: 4.83 | D47: 2.3209 | E47: =C47-D47 -> 2.5091
A48: 45589 | B48: 288.8981 | C48: 4.83 | D48: 2.2985 | E48: =C48-D48 -> 2.5315
A49: 45590 | B49: 285.79321 | C49: 4.83 | D49: 2.2938 | E49: =C49-D49 -> 2.5362
A50: 45593 | B50: 279.58758 | C50: 4.82 | D50: 2.294 | E50: =C50-D50 -> 2.526
A51: 45594 | B51: 281.71579 | C51: 4.82 | D51: 2.3137 | E51: =C51-D51 -> 2.5063
A52: 45595 | B52: 276.27759 | C52: 4.81 | D52: 2.3469 | E52: =C52-D52 -> 2.4631
... A59: 45604 | B59: 256.27801 | C59: 4.6 | D59: 2.3631 | E59: =C59-D59 -> 2.2369
A60: 45607 | B60: 256.27801 | C60: 4.6 | D60: #N/A | E60: =C60-D60 -> #N/A
A61: 45608 | B61: 252.6678 | C61: 4.6 | D61: 2.3676 | E61: =C61-D61 -> 2.2324
A62: 45609 | B62: 255.22031 | C62: 4.59 | D62: 2.3658 | E62: =C62-D62 -> 2.2242
A63: 45610 | B63: 254.1705 | C63: 4.58 | D63: 2.3454 | E63: =C63-D63 -> 2.2346
A64: 45611 | B64: 264.82681 | C64: 4.57 | D64: 2.3408 | E64: =C64-D64 -> 2.2292
A65: 45614 | B65: 267.5751 | C65: 4.57 | D65: 2.3526 | E65: =C65-D65 -> 2.2174
A66: 45615 | B66: 264.94659 | C66: 4.57 | D66: 2.3509 | E66: =C66-D66 -> 2.2191
A67: 45616 | B67: 262.48599 | C67: 4.56 | D67: 2.3618 | E67: =C67-D67 -> 2.1982
A68: 45617 | B68: 256.76959 | C68: 4.57 | D68: 2.3522 | E68: =C68-D68 -> 2.2178
A69: 45618 | B69: 257.56381 | C69: 4.57 | D69: 2.3545 | E69: =C69-D69 -> 2.2155
A70: 45621 | B70: 261.13171 | C70: 4.58 | D70: 2.2986 | E70: =C70-D70 -> 2.2814
A71: 45622 | B71: 263.43091 | C71: 4.58 | D71: 2.2895 | E71: =C71-D71 -> 2.2905
A72: 45623 | B72: 265.04541 | C72: 4.57 | D72: 2.2783 | E72: =C72-D72 -> 2.2917
A73: 45624 | B73: 265.04541 | C73: 4.57 | D73: #N/A | E73: =C73-D73 -> #N/A
A74: 45625 | B74: 264.76502 | C74: 4.59 | D74: 2.2679 | E74: =C74-D74 -> 2.3221
A75: 45628 | B75: 263.61569 | C75: 4.64 | D75: 2.2649 | E75: =C75-D75 -> 2.3751
A76: 45629 | B76: 261.90369 | C76: 4.64 | D76: 2.3086 | E76: =C76-D76 -> 2.3314
A77: 45630 | B77: 262.24759 | C77: 4.59 | D77: 2.288 | E77: =C77-D77 -> 2.302
A78: 45631 | B78: 262.05539 | C78: 4.59 | D78: 2.2729 | E78: =C78-D78 -> 2.3171
A79: 45632 | B79: 263.60519 | C79: 4.6 | D79: 2.2526 | E79: =C79-D79 -> 2.3474
A80: 45635 | B80: 262.21231 | C80: 4.63 | D80: 2.2668 | E80: =C80-D80 -> 2.3632
A81: 45636 | B81: 262.7746 | C81: 4.64 | D81: 2.2971 | E81: =C81-D81 -> 2.3429
A82: 45637 | B82: 259.33591 | C82: 4.62 | D82: 2.3188 | E82: =C82-D82 -> 2.3012
A83: 45638 | B83: 258.32919 | C83: 4.62 | D83: 2.3275 | E83: =C83-D83 -> 2.2925
A84: 45639 | B84: 261.29669 | C84: 4.6 | D84: 2.3455 | E84: =C84-D84 -> 2.2545
A85: 45642 | B85: 263.949 | C85: 4.65 | D85: 2.327 | E85: =C85-D85 -> 2.323
... A91: 45650 | B91: 281.40439 | C91: 4.4 | D91: 2.3534 | E91: =C91-D91 -> 2.0466
A92: 45651 | B92: 281.40439 | C92: 4.4 | D92: #N/A | E92: =C92-D92 -> #N/A
A93: 45652 | B93: 278.4267 | C93: 4.53 | D93: 2.3491 | E93: =C93-D93 -> 2.1809
A94: 45653 | B94: 280.6629 | C94: 4.46 | D94: 2.3534 | E94: =C94-D94 -> 2.1066
A95: 45656 | B95: 287.21381 | C95: 4.37 | D95: 2.3262 | E95: =C95-D95 -> 2.0438
A96: 45657 | B96: 287.3775 | C96: 4.49 | D96: 2.3388 | E96: =C96-D96 -> 2.1512
A97: 45659 | B97: 281.79059 | C97: 4.4 | D97: 2.3402 | E97: =C97-D97 -> 2.0598
A98: 45660 | B98: 274.4054 | C98: 4.31 | D98: 2.3399 | E98: =C98-D98 -> 1.9701
A99: 45663 | B99: 269.9704 | C99: 4.27 | D99: 2.3596 | E99: =C99-D99 -> 1.9104
A100: 45664 | B100: 271.35709 | C100: 4.27 | D100: 2.4025 | E100: =C100-D100 -> 1.8675
A101: 45665 | B101: 276.84369 | C101: 4.29 | D101: 2.4196 | E101: =C101-D101 -> 1.8704
A102: 45666 | B102: 275.34699 | C102: 4.3 | D102: 2.4104 | E102: =C102-D102 -> 1.8896
A103: 45667 | B103: 273.80371 | C103: 4.3 | D103: 2.4444 | E103: =C103-D103 -> 1.8556
A104: 45670 | B104: 278.47119 | C104: 4.29 | D104: 2.4657 | E104: =C104-D104 -> 1.8243
... A108: 45674 | B108: 262.52801 | C108: 4.29 | D108: 2.43 | E108: =C108-D108 -> 1.86
A109: 45677 | B109: 262.52801 | C109: 4.29 | D109: #N/A | E109: =C109-D109 -> #N/A
A110: 45678 | B110: 258.18539 | C110: 4.29 | D110: 2.4023 | E110: =C110-D110 -> 1.8877
A111: 45679 | B111: 255.64391 | C111: 4.3 | D111: 2.4184 | E111: =C111-D111 -> 1.8816
A112: 45680 | B112: 256.5907 | C112: 4.35 | D112: 2.4614 | E112: =C112-D112 -> 1.8886
A113: 45681 | B113: 256.11829 | C113: 4.34 | D113: 2.4183 | E113: =C113-D113 -> 1.9217
A114: 45684 | B114: 262.65631 | C114: 4.34 | D114: 2.4012 | E114: =C114-D114 -> 1.9388
A115: 45685 | B115: 263.75729 | C115: 4.35 | D115: 2.4115 | E115: =C115-D115 -> 1.9385
A116: 45686 | B116: 262.35751 | C116: 4.35 | D116: 2.4094 | E116: =C116-D116 -> 1.9406
A117: 45687 | B117: 260.62109 | C117: 4.36 | D117: 2.3884 | E117: =C117-D117 -> 1.9716
A118: 45688 | B118: 260.95581 | C118: 4.38 | D118: 2.4302 | E118: =C118-D118 -> 1.9498
A119: 45691 | B119: 266.8902 | C119: 4.35 | D119: 2.4273 | E119: =C119-D119 -> 1.9227
A120: 45692 | B120: 266.422 | C120: 4.33 | D120: 2.4387 | E120: =C120-D120 -> 1.8913
A121: 45693 | B121: 263.00909 | C121: 4.33 | D121: 2.4195 | E121: =C121-D121 -> 1.9105
... A128: 45702 | B128: 260.8519 | C128: 4.33 | D128: 2.4407 | E128: =C128-D128 -> 1.8893
A129: 45705 | B129: 260.8519 | C129: 4.33 | D129: #N/A | E129: =C129-D129 -> #N/A
A130: 45706 | B130: 257.0701 | C130: 4.37 | D130: 2.4564 | E130: =C130-D130 -> 1.9136
A131: 45707 | B131: 263.04129 | C131: 4.35 | D131: 2.4644 | E131: =C131-D131 -> 1.8856
A132: 45708 | B132: 261.9559 | C132: 4.33 | D132: 2.4681 | E132: =C132-D132 -> 1.8619
A133: 45709 | B133: 272.35818 | C133: 4.34 | D133: 2.422 | E133: =C133-D133 -> 1.918
A134: 45712 | B134: 273.7742 | C134: 4.34 | D134: 2.4331 | E134: =C134-D134 -> 1.9069
A135: 45713 | B135: 278.52359 | C135: 4.33 | D135: 2.3883 | E135: =C135-D135 -> 1.9417
A136: 45714 | B136: 275.74509 | C136: 4.33 | D136: 2.3621 | E136: =C136-D136 -> 1.9679
...

Sheet real_estate
B2: NOI yield | C2: 0.0469
B3: CapEx | C3: =C2/3 -> 0.015633333
B4: Cashflow yield | C4: =C2-C3 -> 0.031266667
B5: Real growth | C5: 0
B6: Unlevered real ER | C6: =C4+C5 -> 0.031266667
B7: Expected inflation | C7: =cost_of_debt!D224/100 -> 0.022839
B8: Unlevered nominal ER | C8: =C6+C7 -> 0.054105667
D13: NOI yield | E13: CapEx (~NOI/3) | F13: Cashflow yield | G13: Real growth | H13: Unlevered real ER | I13: Expected inflation | J13: Unlevered nominal ER
D14: =C2 -> 0.0469 | E14: =C3 -> 0.015633333 | F14: =C4 -> 0.031266667 | G14: =C5 -> 0 | H14: =C6 -> 0.031266667 | I14: =C7 -> 0.022839 | J14: =C8 -> 0.054105667

Sheet private_credit
B2: HY credit expected real return | C2: 0.051761 | D2: from my CMA framework fixed income part, HY intermediate bonds expected return (arithmetic) - expected inflation 2.28%)
B3: Cash real return | C3: =cash!F308 -> 0.016420667
B4: HY credit excess real return | C4: =C2-C3 -> 0.035340333
B5: Leverage multiplier | C5: 1.2 | D5: Taken from Block et al. 2023
B6: Expected PC real return (arithmetic average) | C6: =C3+C4*C5 -> 0.058829067
B7: Variance of levered HY credit return (L^2*Var(HY)) | C7: =D7^2*C5 -> 0.018636447 | D7: 0.12462092 | E7: <--- HY (intermediate) standard deviation over 1987-2025, based on annual returns
B8: Expected PC real return (geometric average) | C8: =C6-C7/2 -> 0.049510843
B9: Expected inflation | C9: =cost_of_debt!D224/100 -> 0.022839
B10: Expected PC nominal return (geometric average) | C10: =(1+C8)*(1+C9)-1 -> 0.073480621
D13: HY credit expected real return | E13: Cash real return | F13: HY credit excess real return | G13: Leverage multiplier | H13: Expected PC real return (arithmetic average) | I13: Variance of levered HY credit return (L^2*Var(HY)) | J13: Expected PC real return (geometric average) | K13: Expected inflation | L13: Expected PC nominal return (geometric average)
D14: 0.051761 | E14: 0.016420667 | F14: 0.035340333 | G14: 1.2 | H14: 0.058829067 | I14: 0.018636447 | J14: 0.049510843 | K14: 0.022839 | L14: 0.073480621
B25: Geometric VS arithmetic
B26: Year | C26: 1 | D26: 2 | E26: 3 | F26: 4 | G26: 5 | H26: 6
B27: Return | C27: 0.015 | D27: 0.1 | E27: -0.12 | F27: 0.2 | G27: 0.012 | H27: 0.06
B29: Arithmetic | C29: =AVERAGE(C27:H27) -> 0.0445
B30: Geometric | C30: {=(PRODUCT(1+C27:H27))^(1/6)-1} -> 0.039923767
B31: Variance/2 | C31: =_xlfn.VAR.P(C27:H27)/2 -> 0.0047072917
B32: A - V/2 ~ G | C32: =C29-C31 -> 0.039792708
B35: Leverage
B36: Rfr | C36: 0.02
B37: HY spread | C37: 0.04
B38: Total yield | C38: =SUM(C36:C37) -> 0.06
B40: Equity | C40: 100
B41: Leverage | C41: 0.2
B42: Total investment | C42: =C40*(1+C41) -> 120
B43: Leverage multiplier | C43: =C42/C40 -> 1.2
B45: Total return | C45: =C42*C38 -> 7.2
B46: Pay cash | C46: =C40*C41*C36 -> 0.4
B47: Return to equity | C47: =C45-C46 -> 6.8
B49: Return % | C49: =C47/C40 -> 0.068
B50: Excess return * leverage multiplier | C50: =C37*C43+C36 -> 0.068
C51: =C50=C49 -> TRUE

Sheet cash
A1: Date | B1: UST, 3M | C1: UST, 10Y
A2: 36525 | B2: 0.05411 | C2: 0.06592
A3: 36556 | B3: 0.05692 | C3: 0.06665
A4: 36585 | B4: 0.05781 | C4: 0.06409
A5: 36616 | B5: 0.05871 | C5: 0.06004
A6: 36646 | B6: 0.05829 | C6: 0.06212
A7: 36677 | B7: 0.05619 | C7: 0.06272
A8: 36707 | B8: 0.05854 | C8: 0.06031
A9: 36738 | B9: 0.06219 | C9: 0.06031
A10: 36769 | B10: 0.06306 | C10: 0.05725
A11: 36799 | B11: 0.06209 | C11: 0.05802
A12: 36830 | B12: 0.06389 | C12: 0.05751
A13: 36860 | B13: 0.06202 | C13: 0.05468
... A306: 45777 | B306: 0.04288 | C306: 0.041619
A307: 45808 | B307: 0.04342 | C307: 0.044004 | D307: Next 10Y Avg. Forecast Short Rate | E307: Expected inflation | F307: Expected real cash return
A308: 45838 | B308: 0.04301 | C308: 0.042769 | D308: 0.032 | E308: =cost_of_debt!D224/100 -> 0.022839 | F308: =AVERAGE(B308:D308)-E308 -> 0.016420667
D309: Taken from AQR which itself uses Consensus Economics forecast estimate
