Workbook

Sheet Timeseries
A1: Date | B1: Stock_1 | C1: Stock_2 | D1: Stock_3 | E1: Stock_4 | F1: Stock_5 | G1: Stock_6 | H1: Stock_7 | I1: Stock_8 | J1: Stock_9 | K1: Stock_10 | L1: Bond_10Y | M1: Stock_Index
A2: 42035 | B2: -0.024185222 | C2: 0.086116494 | D2: 0.20749862 | E2: 0.23616686 | F2: -0.072663996 | G2: 0.079694311 | H2: 0.02148844 | I2: -0.014563967 | J2: 0.36726102 | K2: 0.19249322 | L2: 0.014901425 | M2: 0.12352719 | N2: {=SUMPRODUCT(1+B2:K2,$B$124:$K$124)-1} -> 0.12352719
A3: 42063 | B3: -0.28067557 | C3: 0.034777 | D3: 0.24602997 | E3: 0.046934344 | F3: -0.36535199 | G3: -0.21425038 | H3: 0.082871639 | I3: -0.22069285 | J3: -0.039100388 | K3: 0.010555007 | L3: -0.004147929 | M3: -0.065941036 | N3: {=SUMPRODUCT(1+B3:K3,$B$124:$K$124)-1} -> -0.065941036
A4: 42094 | B4: 0.023830451 | C4: 0.17096898 | D4: -0.35956126 | E4: 0.028738702 | F4: 0.16405904 | G4: 0.010342506 | H4: 0.3919147 | I4: -0.066888532 | J4: 0.10712683 | K4: 0.23042738 | L4: 0.019430656 | M4: 0.076414286 | N4: {=SUMPRODUCT(1+B4:K4,$B$124:$K$124)-1} -> 0.076414286
A5: 42124 | B5: 0.069780484 | C5: -0.36550467 | D5: 0.069709891 | E5: -0.097183049 | F5: -0.25072273 | G5: 0.0016549517 | H5: -0.10887453 | I5: -0.2791566 | J5: -0.11339788 | K5: -0.1884175 | L5: 0.045690896 | M5: -0.13929402 | N5: {=SUMPRODUCT(1+B5:K5,$B$124:$K$124)-1} -> -0.13929402
A6: 42155 | B6: 0.077519962 | C6: 0.17079666 | D6: 0.34484241 | E6: -0.1276944 | F6: 0.40627343 | G6: -0.28154044 | H6: 0.039364195 | I6: 0.16668932 | J6: 0.1034817 | K6: -0.040877661 | L6: -0.0070246012 | M6: 0.094203459 | N6: {=SUMPRODUCT(1+B6:K6,$B$124:$K$124)-1} -> 0.094203459
A7: 42185 | B7: 0.20423396 | C7: 0.1783696 | D7: 0.17558767 | E7: 0.3622999 | F7: 0.31301518 | G7: 0.15058121 | H7: 0.36354643 | I7: 0.3139737 | J7: 0.36523139 | K7: 0.38415038 | L7: -0.0070241087 | M7: 0.28452163 | N7: {=SUMPRODUCT(1+B7:K7,$B$124:$K$124)-1} -> 0.28452163
A8: 42216 | B8: -0.21185717 | C8: -0.17586398 | D8: 0.052878158 | E8: 0.040272235 | F8: -0.041335708 | G8: -0.00083822618 | H8: 0.09112242 | I8: -0.22904085 | J8: 0.006458779 | K8: -0.10108303 | L8: 0.047376384 | M8: -0.062757314 | N8: {=SUMPRODUCT(1+B8:K8,$B$124:$K$124)-1} -> -0.062757314
A9: 42247 | B9: -0.08548363 | C9: 0.12265667 | D9: 0.095049437 | E9: 0.087064071 | F9: 0.18355868 | G9: -0.017909786 | H9: 0.043901655 | I9: -0.12512567 | J9: 0.0023233048 | K9: -0.065671001 | L9: 0.023023042 | M9: 0.024477828 | N9: {=SUMPRODUCT(1+B9:K9,$B$124:$K$124)-1} -> 0.024477828
A10: 42277 | B10: 0.020473565 | C10: 0.097256537 | D10: -0.14486505 | E10: 0.3049078 | F10: -0.17613416 | G10: -0.2323955 | H10: 0.17308299 | I10: 0.14314555 | J10: 0.094754848 | K10: 0.10313046 | L10: -0.014084232 | M10: 0.030530987 | N10: {=SUMPRODUCT(1+B10:K10,$B$124:$K$124)-1} -> 0.030530987
A11: 42308 | B11: -0.051185648 | C11: -0.19210413 | D11: -0.034611735 | E11: -0.1364683 | F11: 0.12567903 | G11: -0.054654929 | H11: -0.16814723 | I11: -0.11712453 | J11: 0.017700926 | K11: -0.14148291 | L11: 0.016276801 | M11: -0.071050493 | N11: {=SUMPRODUCT(1+B11:K11,$B$124:$K$124)-1} -> -0.071050493
A12: 42338 | B12: -0.28968458 | C12: -0.15562072 | D12: -0.1750382 | E12: -0.26631244 | F12: -0.29013037 | G12: -0.19538023 | H12: -0.37969627 | I12: -0.40612522 | J12: -0.29447856 | K12: -0.25664878 | L12: -0.013902531 | M12: -0.26211132 | N12: {=SUMPRODUCT(1+B12:K12,$B$124:$K$124)-1} -> -0.26211132
A13: 42369 | B13: 0.047918663 | C13: 0.23374546 | D13: 0.1428191 | E13: -0.033858952 | F13: -0.019179477 | G13: -0.19907825 | H13: 0.00054141457 | I13: -0.033253051 | J13: 0.045839817 | K13: -0.15275503 | L13: -0.013971893 | M13: 0.0026585589 | N13: {=SUMPRODUCT(1+B13:K13,$B$124:$K$124)-1} -> 0.0026585589
... A121: 45657 | B121: 0.14292624 | C121: 0.24668164 | D121: 0.28579183 | E121: 0.036950347 | F121: 0.11628757 | G121: 0.21370057 | H121: 0.062948317 | I121: 0.35149835 | J121: 0.18770818 | K121: 0.26768585 | L121: 0.022557991 | M121: 0.20335485 | N121: {=SUMPRODUCT(1+B121:K121,$B$124:$K$124)-1} -> 0.20335485
A123: Correl with bond | B123: =CORREL(B2:B121,$L$2:$L$121) -> 0.13339309 | C123: =CORREL(C2:C121,$L$2:$L$121) -> 0.14166519 | D123: =CORREL(D2:D121,$L$2:$L$121) -> 0.24900995 | E123: =CORREL(E2:E121,$L$2:$L$121) -> 0.17006528 | F123: =CORREL(F2:F121,$L$2:$L$121) -> 0.25087745 | G123: =CORREL(G2:G121,$L$2:$L$121) -> 0.32978254 | H123: =CORREL(H2:H121,$L$2:$L$121) -> 0.13837369 | I123: =CORREL(I2:I121,$L$2:$L$121) -> -0.079159385 | ... K123: =CORREL(K2:K121,$L$2:$L$121) -> 0.19779888 | M123: =CORREL(M2:M121,$L$2:$L$121) -> 0.25266587
A124: Weights | B124: 0.08 | C124: 0.12 | D124: 0.1 | E124: 0.07 | F124: 0.11 | G124: 0.09 | H124: 0.06 | I124: 0.08 | J124: 0.13 | K124: 0.16
J125: Average | K125: =AVERAGE(B123:K123) -> 0.16206999 | L125: DR
J126: Weighted average | K126: =SUMPRODUCT(B123:K123,B124:K124) -> 0.1669274 | L126: =Summary!B4 -> 1.4623508 | M126: =K126*Summary!B4 -> 0.2441064
L127: the aggregate (index) correlation with bonds is a weighted average of the individual correlations, multiplied by a diversification factor (the “correlation leverage”).

Sheet PerStock
B1: Weight | C1: Sigma_hat | D1: Phi_i = Sigma_i / Sigma_p | E1: Omega_i | F1: IndivCorr_iB (sample)
A2: Stock_1 | B2: 0.08 | C2: 0.16737885 | D2: 1.183083 | E2: 0.064722257 | F2: 0.13339309
A3: Stock_2 | B3: 0.12 | C3: 0.21667163 | D3: 1.5314989 | E3: 0.12567428 | F3: 0.14166519
A4: Stock_3 | B4: 0.1 | C4: 0.23146253 | D4: 1.6360454 | E4: 0.11187777 | F4: 0.24900995
A5: Stock_4 | B5: 0.07 | C5: 0.18577292 | D5: 1.3130977 | E5: 0.062855536 | F5: 0.17006528
A6: Stock_5 | B6: 0.11 | C6: 0.20343514 | D6: 1.4379395 | E6: 0.10816375 | F6: 0.25087745
A7: Stock_6 | B7: 0.09 | C7: 0.24580919 | D7: 1.7374518 | E7: 0.10693102 | F7: 0.32978254
A8: Stock_7 | B8: 0.06 | C8: 0.19254968 | D8: 1.3609979 | E8: 0.05584151 | F8: 0.13837369
A9: Stock_8 | B9: 0.08 | C9: 0.19695629 | D9: 1.3921451 | E9: 0.076159298 | F9: -0.079159385
A10: Stock_9 | B10: 0.13 | C10: 0.19324931 | D10: 1.3659431 | E10: 0.12142955 | F10: 0.088893247
A11: Stock_10 | B11: 0.16 | C11: 0.21509322 | D11: 1.5203423 | E11: 0.16634502 | F11: 0.19779888

Sheet Summary
B1: Value
A2: Direct aggregate corr (Index vs Bond) | B2: 0.25266587
A3: Formula aggregate corr (DR * sum omega_i * rho_iB) | B3: 0.25266587
A4: Diversification Ratio (DR) | B4: 1.4623508
A5: Index vol (sample) | B5: 0.14147684
A6: Cap-weighted avg indiv corr (sum w_i * rho_iB) | B6: 0.1669274

Sheet JPM Corr
C2: U.S. Inflation | D2: U.S. Cash | E2: U.S. Intermediate Treasuries | F2: U.S. Long Treasuries | G2: TIPS | H2: U.S. Aggregate Bonds | I2: U.S. Securitized | J2: U.S. Short Duration Government/Credit | K2: U.S. Long Duration Government/Credit | L2: U.S. Inv Grade Corporate Bonds | M2: U.S. Long Corporate Bonds | N2: U.S. High Yield Bonds | O2: U.S. Leveraged Loans | P2: World Government Bonds hedged | Q2: World Government Bonds | R2: World ex-U.S. Government Bonds hedged | S2: World ex-U.S. Government Bonds | T2: Emerging Markets Sovereign Debt | U2: Emerging Markets Local Currency Debt | V2: Emerging Markets Corporate Bonds | W2: U.S. Muni 1-15 Yr Blend | X2: U.S. Muni High Yield | Y2: U.S. Large Cap | Z2: U.S. Mid Cap | AA2: U.S. Small Cap | AB2: Euro Area Large Cap | AC2: Japanese Equity | AD2: Hong Kong Equity | AE2: UK Large Cap | AF2: EAFE Equity | AG2: Chinese Domestic Equity | AH2: Emerging Markets Equity | AI2: AC Asia ex-Japan Equity | AJ2: AC World Equity | AK2: U.S. Equity Value Factor | AL2: U.S. Equity Momentum Factor | AM2: U.S. Equity Quality Factor | AN2: U.S. Equity Minimum Volatility Factor | AO2: U.S. Equity Dividend Yield Factor | AP2: Global Convertible Bonds hedged | AQ2: U.S. Core Real Estate | AR2: U.S. Value-Added Real Estate | AS2: European Core Real Estate | AT2: Asia Pacific Core Real Estate | AU2: U.S. REITs | AV2: Commercial Mortgage Loans | AW2: Global Core Infrastructure | AX2: Global Core Transport | AY2: Global Timberland | AZ2: Commodities | BA2: Gold | BB2: Private Equity | BC2: Venture Capital | BD2: Diversified Hedge Funds | BE2: Event Driven Hedge Funds | BF2: Long Bias Hedge Funds | BG2: Relative Value Hedge Funds | BH2: Macro Hedge Funds | BI2: Direct Lending
B3: U.S. Inflation | C3: 1
B4: U.S. Cash | C4: -0.03 | D4: 1
B5: U.S. Intermediate Treasuries | C5: -0.27 | D5: 0.17 | E5: 1
B6: U.S. Long Treasuries | C6: -0.22 | D6: 0.03 | E6: 0.83 | F6: 1
B7: TIPS | C7: -0.02 | D7: 0.02 | E7: 0.62 | F7: 0.6 | G7: 1
B8: U.S. Aggregate Bonds | C8: -0.24 | D8: 0.08 | E8: 0.84 | F8: 0.85 | G8: 0.76 | H8: 1
B9: U.S. Securitized | C9: -0.23 | D9: 0.1 | E9: 0.78 | F9: 0.74 | G9: 0.69 | H9: 0.93 | I9: 1
B10: U.S. Short Duration Government/Credit | C10: -0.3 | D10: 0.28 | E10: 0.84 | F10: 0.59 | G10: 0.63 | H10: 0.82 | I10: 0.76 | J10: 1
B11: U.S. Long Duration Government/Credit | C11: -0.22 | D11: 0.02 | E11: 0.74 | F11: 0.9 | G11: 0.69 | H11: 0.94 | I11: 0.81 | J11: 0.66 | K11: 1
B12: U.S. Inv Grade Corporate Bonds | C12: -0.19 | D12: 0.01 | E12: 0.52 | F12: 0.6 | G12: 0.72 | H12: 0.87 | I12: 0.75 | J12: 0.66 | K12: 0.85 | L12: 1
B13: U.S. Long Corporate Bonds | C13: -0.19 | D13: 0 | E13: 0.51 | F13: 0.67 | G13: 0.67 | H13: 0.87 | I13: 0.74 | J13: 0.6 | K13: 0.91 | L13: 0.97 | M13: 1
B14: U.S. High Yield Bonds | C14: 0 | D14: 0.05 | E14: -0.02 | F14: 0 | G14: 0.48 | H14: 0.38 | I14: 0.38 | J14: 0.28 | K14: 0.33 | L14: 0.66 | M14: 0.6 | N14: 1
B15: U.S. Leveraged Loans | C15: 0.18 | D15: 0.05 | E15: -0.37 | F15: 0.28 | G15: 0.18 | H15: 0.03 | I15: 0.04 | J15: 0.05 | K15: 0.03 | L15: 0.36 | M15: 0.31 | N15: 0.77 | O15: 1
B16: World Government Bonds hedged | C16: -0.29 | D16: 0.1 | E16: 0.86 | F16: 0.87 | G16: 0.62 | H16: 0.87 | I16: 0.78 | J16: 0.72 | K16: 0.84 | L16: 0.66 | M16: 0.68 | N16: 0.12 | O16: 0.2 | P16: 1
B17: World Government Bonds | C17: -0.17 | D17: 0.09 | E17: 0.75 | F17: 0.66 | G17: 0.69 | H17: 0.8 | I17: 0.72 | J17: 0.74 | K17: 0.74 | L17: 0.69 | M17: 0.68 | N17: 0.33 | O17: 0.05 | P17: 0.72 | Q17: 1
B18: World ex-U.S. Government Bonds hedged | C18: -0.28 | D18: 0.1 | E18: 0.72 | F18: 0.74 | G18: 0.58 | H18: 0.79 | I18: 0.7 | J18: 0.63 | K18: 0.77 | L18: 0.64 | M18: 0.66 | N18: 0.19 | O18: -0.1 | P18: 0.96 | Q18: 0.66 | R18: 1
B19: World ex-U.S. Government Bonds | C19: -0.16 | D19: 0.08 | E19: 0.65 | F19: 0.55 | G19: 0.65 | H19: 0.74 | I19: 0.67 | J19: 0.68 | K19: 0.68 | L19: 0.68 | M19: 0.67 | N19: 0.4 | O19: 0.04 | P19: 0.64 | Q19: 0.98 | R19: 0.61 | S19: 1
B20: Emerging Markets Sovereign Debt | C20: -0.14 | D20: 0.03 | E20: 0.31 | F20: 0.34 | G20: 0.62 | H20: 0.66 | I20: 0.6 | J20: 0.49 | K20: 0.62 | L20: 0.82 | M20: 0.78 | N20: 0.75 | O20: 0.45 | P20: 0.44 | Q20: 0.6 | R20: 0.46 | S20: 0.64 | T20: 1
B21: Emerging Markets Local Currency Debt | C21: -0.05 | D21: 0.09 | E21: 0.22 | F21: 0.18 | G21: 0.45 | H21: 0.47 | I21: 0.42 | J21: 0.41 | K21: 0.43 | L21: 0.61 | M21: 0.58 | N21: 0.62 | O21: 0.35 | P21: 0.26 | Q21: 0.61 | R21: 0.28 | S21: 0.67 | T21: 0.81 | U21: 1
B22: Emerging Markets Corporate Bonds | C22: -0.07 | D22: 0.02 | E22: 0.19 | F22: 0.23 | G22: 0.55 | H22: 0.57 | I22: 0.5 | J22: 0.44 | K22: 0.52 | L22: 0.8 | M22: 0.73 | N22: 0.73 | O22: 0.57 | P22: 0.31 | Q22: 0.48 | R22: 0.32 | S22: 0.51 | T22: 0.89 | U22: 0.73 | V22: 1
B23: U.S. Muni 1-15 Yr Blend | C23: -0.17 | D23: 0.06 | E23: 0.52 | F23: 0.51 | G23: 0.58 | H23: 0.72 | I23: 0.69 | J23: 0.55 | K23: 0.64 | L23: 0.69 | M23: 0.66 | N23: 0.42 | O23: 0.18 | P23: 0.6 | Q23: 0.55 | R23: 0.59 | S23: 0.54 | T23: 0.63 | U23: 0.39 | V23: 0.5 | W23: 1
B24: U.S. Muni High Yield | C24: 0.17 | D24: 0.05 | E24: 0.15 | F24: 0.25 | G24: 0.47 | H24: 0.43 | I24: 0.43 | J24: 0.2 | K24: 0.39 | L24: 0.55 | M24: 0.49 | N24: 0.5 | O24: 0.49 | P24: 0.29 | Q24: 0.26 | R24: 0.3 | S24: 0.28 | T24: 0.57 | U24: 0.31 | V24: 0.55 | W24: 0.64 | X24: 1
B25: U.S. Large Cap | C25: 0 | D25: 0 | E25: -0.06 | F25: 0.03 | G25: 0.31 | H25: 0.26 | I25: 0.26 | J25: 0.12 | K25: 0.25 | L25: 0.49 | M25: 0.47 | N25: 0.74 | O25: 0.58 | P25: 0.09 | Q25: 0.29 | R25: 0.16 | S25: 0.37 | T25: 0.62 | U25: 0.6 | V25: 0.57 | W25: 0.23 | X25: 0.33 | Y25: 1
B26: U.S. Mid Cap | C26: 0 | D26: 0.04 | E26: -0.1 | F26: 0.05 | G26: 0.31 | H26: 0.25 | I26: 0.25 | J26: 0.1 | K26: 0.24 | L26: 0.5 | M26: 0.47 | N26: 0.78 | O26: 0.62 | P26: 0.05 | Q26: 0.26 | R26: 0.13 | S26: 0.34 | T26: 0.62 | U26: 0.6 | V26: 0.58 | W26: 0.25 | X26: 0.33 | Y26: 0.96 | Z26: 1
B27: U.S. Small Cap | C27: -0.03 | D27: 0.05 | E27: -0.13 | F27: 0.1 | G27: 0.22 | H27: 0.18 | I27: 0.2 | J27: 0.05 | K27: 0.17 | L27: 0.4 | M27: 0.38 | N27: 0.71 | O27: 0.55 | P27: 0 | Q27: 0.2 | R27: 0.08 | S27: 0.27 | T27: 0.53 | U27: 0.54 | V27: 0.48 | W27: 0.18 | X27: 0.24 | Y27: 0.9 | Z27: 0.95 | AA27: 1
B28: Euro Area Large Cap | C28: -0.02 | D28: 0.05 | E28: -0.02 | F28: 0.04 | G28: 0.29 | H28: 0.29 | I28: 0.29 | J28: 0.22 | K28: 0.26 | L28: 0.5 | M28: 0.48 | N28: 0.73 | O28: 0.52 | P28: 0.06 | Q28: 0.41 | R28: 0.12 | S28: 0.49 | T28: 0.68 | U28: 0.73 | V28: 0.62 | W28: 0.27 | X28: 0.3 | Y28: 0.85 | Z28: 0.84 | AA28: 0.77 | AB28: 1
B29: Japanese Equity | C29: -0.07 | D29: 0 | E29: -0.01 | F29: 0.02 | G29: 0.28 | H29: 0.3 | I29: 0.3 | J29: 0.21 | K29: 0.3 | L29: 0.52 | M29: 0.5 | N29: 0.67 | O29: 0.49 | P29: 0.08 | Q29: 0.33 | R29: 0.13 | S29: 0.4 | T29: 0.6 | U29: 0.62 | V29: 0.58 | W29: 0.25 | X29: 0.29 | Y29: 0.74 | Z29: 0.74 | AA29: 0.68 | AB29: 0.77 | AC29: 1
B30: Hong Kong Equity | C30: -0.04 | D30: 0.05 | E30: -0.06 | F30: 0.03 | G30: 0.23 | H30: 0.26 | I30: 0.24 | J30: 0.18 | K30: 0.24 | L30: 0.48 | M30: 0.44 | N30: 0.59 | O30: 0.49 | P30: -0.02 | Q30: 0.29 | R30: -0.01 | S30: 0.36 | T30: 0.59 | U30: 0.67 | V30: 0.64 | W30: 0.26 | X30: 0.34 | Y30: 0.58 | Z30: 0.6 | AA30: 0.53 | AB30: 0.68 | AC30: 0.59 | AD30: 1
B31: UK Large Cap | C31: 0.04 | D31: 0 | E31: -0.14 | F31: 0.14 | G31: 0.25 | H31: 0.19 | I31: 0.2 | J31: 0.11 | K31: 0.18 | L31: 0.45 | M31: 0.43 | N31: 0.72 | O31: 0.61 | P31: -0.05 | Q31: 0.31 | R31: 0.01 | S31: 0.4 | T31: 0.61 | U31: 0.66 | V31: 0.6 | W31: 0.2 | X31: 0.34 | Y31: 0.82 | Z31: 0.81 | AA31: 0.73 | AB31: 0.91 | AC31: 0.75 | AD31: 0.73 | AE31: 1
B32: EAFE Equity | C32: -0.02 | D32: 0.03 | E32: -0.04 | F32: 0.04 | G32: 0.32 | H32: 0.3 | I32: 0.29 | J32: 0.21 | K32: 0.28 | L32: 0.54 | M32: 0.52 | N32: 0.77 | O32: 0.58 | P32: 0.06 | Q32: 0.41 | R32: 0.11 | S32: 0.49 | T32: 0.7 | U32: 0.75 | V32: 0.66 | W32: 0.26 | X32: 0.33 | Y32: 0.88 | Z32: 0.88 | AA32: 0.8 | AB32: 0.97 | AC32: 0.85 | AD32: 0.73 | AE32: 0.95 | AF32: 1
B33: Chinese Domestic Equity | C33: -0.05 | D33: 0.06 | E33: -0.05 | F33: 0.02 | G33: 0.11 | H33: 0.16 | I33: 0.15 | J33: 0.1 | K33: 0.14 | L33: 0.29 | M33: 0.26 | N33: 0.34 | O33: 0.29 | P33: 0.02 | Q33: 0.15 | R33: 0.02 | S33: 0.18 | T33: 0.34 | U33: 0.36 | V33: 0.4 | W33: 0.11 | X33: 0.18 | Y33: 0.35 | Z33: 0.35 | AA33: 0.32 | AB33: 0.38 | AC33: 0.35 | AD33: 0.59 | AE33: 0.4 | AF33: 0.41 | AG33: 1
B34: Emerging Markets Equity | C34: -0.01 | D34: 0.03 | E34: -0.05 | F34: 0.02 | G34: 0.33 | H34: 0.29 | I34: 0.27 | J34: 0.21 | K34: 0.27 | L34: 0.53 | M34: 0.49 | N34: 0.72 | O34: 0.57 | P34: 0.04 | Q34: 0.39 | R34: 0.08 | S34: 0.47 | T34: 0.7 | U34: 0.8 | V34: 0.7 | W34: 0.24 | X34: 0.37 | Y34: 0.74 | Z34: 0.76 | AA34: 0.68 | AB34: 0.82 | AC34: 0.7 | AD34: 0.84 | AE34: 0.81 | AF34: 0.86 | AG34: 0.56 | AH34: 1
B35: AC Asia ex-Japan Equity | C35: -0.06 | D35: 0.02 | E35: -0.02 | F35: 0.02 | G35: 0.32 | H35: 0.31 | I35: 0.29 | J35: 0.23 | K35: 0.3 | L35: 0.54 | M35: 0.51 | N35: 0.69 | O35: 0.53 | P35: 0.06 | Q35: 0.38 | R35: 0.09 | S35: 0.45 | T35: 0.68 | U35: 0.75 | V35: 0.69 | W35: 0.26 | X35: 0.37 | Y35: 0.71 | Z35: 0.72 | AA35: 0.66 | AB35: 0.78 | AC35: 0.69 | AD35: 0.88 | AE35: 0.77 | AF35: 0.83 | AG35: 0.61 | AH35: 0.98 | AI35: 1
B36: AC World Equity | C36: -0.01 | D36: 0.01 | E36: -0.06 | F36: 0.04 | G36: 0.34 | H36: 0.29 | I36: 0.28 | J36: 0.18 | K36: 0.28 | L36: 0.54 | M36: 0.51 | N36: 0.79 | O36: 0.61 | P36: 0.07 | Q36: 0.37 | R36: 0.14 | S36: 0.45 | T36: 0.69 | U36: 0.71 | V36: 0.65 | W36: 0.25 | X36: 0.34 | Y36: 0.96 | Z36: 0.95 | AA36: 0.87 | AB36: 0.93 | AC36: 0.82 | AD36: 0.7 | AE36: 0.91 | AF36: 0.97 | AG36: 0.42 | AH36: 0.86 | AI36: 0.83 | AJ36: 1
B37: U.S. Equity Value Factor | C37: -0.03 | D37: 0.04 | E37: -0.1 | F37: 0.09 | G37: 0.26 | H37: 0.22 | I37: 0.24 | J37: 0.1 | K37: 0.2 | L37: 0.44 | M37: 0.42 | N37: 0.74 | O37: 0.57 | P37: 0.03 | Q37: 0.25 | R37: 0.12 | S37: 0.33 | T37: 0.58 | U37: 0.6 | V37: 0.54 | W37: 0.2 | X37: 0.27 | Y37: 0.96 | Z37: 0.97 | AA37: 0.93 | AB37: 0.84 | AC37: 0.74 | AD37: 0.57 | AE37: 0.82 | AF37: 0.87 | AG37: 0.33 | AH37: 0.73 | AI37: 0.69 | AJ37: 0.94 | AK37: 1
B38: U.S. Equity Momentum Factor | C38: 0.01 | D38: 0 | E38: -0.07 | F38: 0.02 | G38: 0.35 | H38: 0.27 | I38: 0.26 | J38: 0.11 | K38: 0.27 | L38: 0.5 | M38: 0.48 | N38: 0.76 | O38: 0.61 | P38: 0.08 | Q38: 0.27 | R38: 0.16 | S38: 0.34 | T38: 0.62 | U38: 0.56 | V38: 0.57 | W38: 0.27 | X38: 0.37 | Y38: 0.97 | Z38: 0.96 | AA38: 0.89 | AB38: 0.81 | AC38: 0.72 | AD38: 0.57 | AE38: 0.78 | AF38: 0.85 | AG38: 0.36 | AH38: 0.74 | AI38: 0.71 | AJ38: 0.94 | AK38: 0.91 | AL38: 1
B39: U.S. Equity Quality Factor | C39: -0.02 | D39: 0 | E39: -0.04 | F39: 0.01 | G39: 0.32 | H39: 0.28 | I39: 0.27 | J39: 0.14 | K39: 0.27 | L39: 0.49 | M39: 0.48 | N39: 0.73 | O39: 0.55 | P39: 0.11 | Q39: 0.3 | R39: 0.18 | S39: 0.37 | T39: 0.63 | U39: 0.61 | V39: 0.56 | W39: 0.26 | X39: 0.32 | Y39: 0.99 | Z39: 0.95 | AA39: 0.9 | AB39: 0.84 | AC39: 0.73 | AD39: 0.57 | AE39: 0.81 | AF39: 0.87 | AG39: 0.34 | AH39: 0.72 | AI39: 0.69 | AJ39: 0.95 | AK39: 0.96 | AL39: 0.96 | AM39: 1
B40: U.S. Equity Minimum Volatility Factor | C40: -0.01 | D40: 0.07 | E40: -0.03 | F40: 0.02 | G40: 0.32 | H40: 0.28 | I40: 0.27 | J40: 0.13 | K40: 0.29 | L40: 0.49 | M40: 0.48 | N40: 0.72 | O40: 0.53 | P40: 0.12 | Q40: 0.31 | R40: 0.2 | S40: 0.38 | T40: 0.62 | U40: 0.62 | V40: 0.54 | W40: 0.27 | X40: 0.32 | Y40: 0.93 | Z40: 0.92 | AA40: 0.85 | AB40: 0.8 | AC40: 0.68 | AD40: 0.55 | AE40: 0.78 | AF40: 0.83 | AG40: 0.3 | AH40: 0.69 | AI40: 0.66 | AJ40: 0.9 | AK40: 0.93 | AL40: 0.9 | AM40: 0.95 | AN40: 1
B41: U.S. Equity Dividend Yield Factor | C41: -0.01 | D41: 0.07 | E41: -0.07 | F41: 0.05 | G41: 0.3 | H41: 0.25 | I41: 0.25 | J41: 0.12 | K41: 0.24 | L41: 0.47 | M41: 0.46 | N41: 0.74 | O41: 0.57 | P41: 0.05 | Q41: 0.28 | R41: 0.13 | S41: 0.36 | T41: 0.61 | U41: 0.62 | V41: 0.55 | W41: 0.25 | X41: 0.3 | Y41: 0.93 | Z41: 0.94 | AA41: 0.89 | AB41: 0.82 | AC41: 0.7 | AD41: 0.59 | AE41: 0.83 | AF41: 0.86 | AG41: 0.31 | AH41: 0.73 | AI41: 0.69 | AJ41: 0.91 | AK41: 0.97 | AL41: 0.88 | AM41: 0.93 | AN41: 0.96 | AO41: 1
B42: Global Convertible Bonds hedged | C42: -0.09 | D42: 0.03 | E42: -0.07 | F42: 0.01 | G42: 0.35 | H42: 0.33 | I42: 0.3 | J42: 0.2 | K42: 0.31 | L42: 0.6 | M42: 0.56 | N42: 0.82 | O42: 0.69 | P42: 0.09 | Q42: 0.29 | R42: 0.16 | S42: 0.36 | T42: 0.7 | U42: 0.62 | V42: 0.7 | W42: 0.31 | X42: 0.39 | Y42: 0.86 | Z42: 0.89 | AA42: 0.83 | AB42: 0.82 | AC42: 0.75 | AD42: 0.68 | AE42: 0.78 | AF42: 0.86 | AG42: 0.48 | AH42: 0.81 | AI42: 0.79 | AJ42: 0.9 | AK42: 0.83 | AL42: 0.88 | AM42: 0.84 | AN42: 0.77 | AO42: 0.8 | AP42: 1
B43: U.S. Core Real Estate | C43: 0.33 | D43: 0.18 | E43: -0.27 | F43: 0.19 | G43: 0.08 | H43: -0.13 | I43: -0.09 | J43: 0.23 | K43: -0.13 | L43: 0 | M43: -0.02 | N43: 0.35 | O43: 0.44 | P43: -0.19 | Q43: -0.16 | R43: -0.16 | S43: -0.13 | T43: 0.11 | U43: 0.12 | V43: 0.22 | W43: 0.2 | X43: 0.34 | Y43: 0.35 | Z43: 0.33 | AA43: 0.29 | AB43: 0.21 | AC43: 0.24 | AD43: 0.21 | AE43: 0.33 | AF43: 0.27 | AG43: 0.14 | AH43: 0.29 | AI43: 0.27 | AJ43: 0.32 | AK43: 0.33 | AL43: 0.32 | AM43: 0.31 | AN43: 0.36 | AO43: 0.32 | AP43: 0.24 | AQ43: 1
B44: U.S. Value-Added Real Estate | C44: 0.33 | D44: 0.18 | E44: -0.27 | F44: 0.19 | G44: 0.08 | H44: -0.13 | I44: -0.09 | J44: 0.23 | K44: -0.13 | L44: 0 | M44: -0.02 | N44: 0.35 | O44: 0.44 | P44: -0.19 | Q44: -0.16 | R44: -0.16 | S44: -0.13 | T44: 0.11 | U44: 0.12 | V44: 0.22 | W44: 0.2 | X44: 0.34 | Y44: 0.35 | Z44: 0.33 | AA44: 0.29 | AB44: 0.21 | AC44: 0.24 | AD44: 0.21 | AE44: 0.33 | AF44: 0.27 | AG44: 0.14 | AH44: 0.29 | AI44: 0.27 | AJ44: 0.32 | AK44: 0.33 | AL44: 0.32 | AM44: 0.31 | AN44: 0.36 | AO44: 0.32 | AP44: 0.24 | AQ44: 1 | AR44: 1
B45: European Core Real Estate | C45: 0.37 | D45: 0.09 | E45: -0.3 | F45: 0.27 | G45: 0.2 | H45: -0.08 | I45: -0.04 | J45: -0.12 | K45: -0.11 | L45: 0.15 | M45: 0.08 | N45: 0.51 | O45: 0.53 | P45: -0.21 | Q45: 0.05 | R45: -0.15 | S45: 0.12 | T45: 0.3 | U45: 0.37 | V45: 0.41 | W45: 0.06 | X45: 0.36 | Y45: 0.53 | Z45: 0.5 | AA45: 0.43 | AB45: 0.49 | AC45: 0.4 | AD45: 0.48 | AE45: 0.57 | AF45: 0.53 | AG45: 0.41 | AH45: 0.6 | AI45: 0.57 | AJ45: 0.57 | AK45: 0.47 | AL45: 0.52 | AM45: 0.48 | AN45: 0.43 | AO45: 0.43 | AP45: 0.54 | AQ45: 0.66 | AR45: 0.66 | AS45: 1
B46: Asia Pacific Core Real Estate | C46: 0.2 | D46: 0.09 | E46: -0.25 | F46: 0.23 | G46: 0.25 | H46: 0.04 | I46: 0.07 | J46: 0.03 | K46: 0.02 | L46: 0.33 | M46: 0.26 | N46: 0.66 | O46: 0.64 | P46: -0.19 | Q46: 0.15 | R46: -0.13 | S46: 0.23 | T46: 0.48 | U46: 0.51 | V46: 0.55 | W46: 0.15 | X46: 0.49 | Y46: 0.6 | Z46: 0.63 | AA46: 0.54 | AB46: 0.62 | AC46: 0.52 | AD46: 0.64 | AE46: 0.7 | AF46: 0.68 | AG46: 0.36 | AH46: 0.7 | AI46: 0.68 | AJ46: 0.67 | AK46: 0.61 | AL46: 0.6 | AM46: 0.57 | AN46: 0.61 | AO46: 0.64 | AP46: 0.61 | AQ46: 0.58 | AR46: 0.58 | AS46: 0.64 | AT46: 1
B47: U.S. REITs | C47: -0.02 | D47: 0.06 | E47: 0.1 | F47: 0.19 | G47: 0.38 | H47: 0.39 | I47: 0.38 | J47: 0.18 | K47: 0.4 | L47: 0.53 | M47: 0.54 | N47: 0.67 | O47: 0.42 | P47: 0.25 | Q47: 0.38 | R47: 0.3 | S47: 0.41 | T47: 0.61 | U47: 0.58 | V47: 0.51 | W47: 0.32 | X47: 0.35 | Y47: 0.77 | Z47: 0.79 | AA47: 0.76 | AB47: 0.69 | AC47: 0.57 | AD47: 0.47 | AE47: 0.64 | AF47: 0.71 | AG47: 0.17 | AH47: 0.59 | AI47: 0.57 | AJ47: 0.75 | AK47: 0.78 | AL47: 0.74 | AM47: 0.78 | AN47: 0.83 | AO47: 0.81 | AP47: 0.66 | AQ47: 0.46 | AR47: 0.46 | AS47: 0.36 | AT47: 0.6 | AU47: 1
B48: Commercial Mortgage Loans | C48: 0.08 | D48: 0.02 | E48: 0.24 | F48: 0.24 | G48: 0.55 | H48: 0.48 | I48: 0.5 | J48: 0.32 | K48: 0.38 | L48: 0.51 | M48: 0.45 | N48: 0.49 | O48: 0.43 | P48: 0.35 | Q48: 0.3 | R48: 0.37 | S48: 0.31 | T48: 0.57 | U48: 0.41 | V48: 0.53 | W48: 0.51 | X48: 0.59 | Y48: 0.31 | Z48: 0.33 | AA48: 0.24 | AB48: 0.29 | AC48: 0.15 | AD48: 0.3 | AE48: 0.28 | AF48: 0.29 | AG48: 0.23 | AH48: 0.37 | AI48: 0.35 | AJ48: 0.32 | AK48: 0.27 | AL48: 0.35 | AM48: 0.33 | AN48: 0.38 | AO48: 0.32 | AP48: 0.35 | AQ48: 0.31 | AR48: 0.31 | AS48: 0.31 | AT48: 0.42 | AU48: 0.41 | AV48: 1
B49: Global Core Infrastructure | C49: 0.19 | D49: 0.05 | E49: -0.22 | F49: 0.24 | G49: 0.24 | H49: 0.04 | I49: 0.07 | J49: 0.02 | K49: -0.02 | L49: 0.26 | M49: 0.2 | N49: 0.57 | O49: 0.59 | P49: -0.17 | Q49: 0.18 | R49: -0.11 | S49: 0.27 | T49: 0.48 | U49: 0.52 | V49: 0.49 | W49: 0.13 | X49: 0.34 | Y49: 0.47 | Z49: 0.47 | AA49: 0.41 | AB49: 0.54 | AC49: 0.43 | AD49: 0.52 | AE49: 0.58 | AF49: 0.55 | AG49: 0.17 | AH49: 0.58 | AI49: 0.52 | AJ49: 0.54 | AK49: 0.46 | AL49: 0.47 | AM49: 0.46 | AN49: 0.44 | AO49: 0.46 | AP49: 0.45 | AQ49: 0.32 | AR49: 0.32 | AS49: 0.47 | AT49: 0.55 | AU49: 0.36 | AV49: 0.41 | AW49: 1
B50: Global Core Transport | C50: 0.22 | D50: 0.15 | E50: 0.04 | F50: 0.06 | G50: -0.06 | H50: -0.09 | I50: -0.05 | J50: 0.09 | K50: -0.08 | L50: -0.27 | M50: -0.22 | N50: 0.2 | O50: -0.12 | P50: 0 | Q50: -0.07 | R50: -0.04 | S50: -0.11 | T50: -0.25 | U50: -0.1 | V50: 0.25 | W50: -0.18 | X50: 0.04 | Y50: -0.06 | Z50: -0.11 | AA50: -0.08 | AB50: 0.07 | AC50: -0.24 | AD50: 0.09 | AE50: -0.12 | AF50: -0.12 | AG50: -0.14 | AH50: 0.13 | AI50: -0.12 | AJ50: -0.1 | AK50: 0.09 | AL50: -0.08 | AM50: 0.05 | AN50: -0.03 | AO50: -0.08 | AP50: 0.25 | AQ50: 0.18 | AR50: 0.18 | AS50: -0.01 | AT50: 0.01 | AU50: 0.1 | AV50: 0.1 | AW50: 0.05 | AX50: 1
B51: Global Timberland | C51: -0.05 | D51: 0.18 | E51: -0.08 | F51: 0.17 | G51: 0.17 | H51: 0.09 | I51: 0.11 | J51: 0.13 | K51: 0.04 | L51: 0.26 | M51: 0.22 | N51: 0.38 | O51: 0.3 | P51: -0.07 | Q51: 0.24 | R51: -0.02 | S51: 0.31 | T51: 0.41 | U51: 0.51 | V51: 0.36 | W51: 0.13 | X51: 0.14 | Y51: 0.46 | Z51: 0.48 | AA51: 0.46 | AB51: 0.57 | AC51: 0.39 | AD51: 0.53 | AE51: 0.54 | AF51: 0.56 | AG51: 0.34 | AH51: 0.54 | AI51: 0.5 | AJ51: 0.53 | AK51: 0.47 | AL51: 0.46 | AM51: 0.46 | AN51: 0.47 | AO51: 0.48 | AP51: 0.41 | AQ51: 0.01 | AR51: 0.01 | AS51: 0.25 | AT51: 0.42 | AU51: 0.35 | AV51: 0.09 | AW51: 0.45 | AX51: 0.01 | AY51: 1
B52: Commodities | C52: 0.27 | D52: 0.03 | E52: -0.17 | F52: 0.23 | G52: 0.26 | H52: -0.01 | I52: -0.02 | J52: 0.02 | K52: -0.02 | L52: 0.19 | M52: 0.16 | N52: 0.44 | O52: 0.41 | P52: -0.22 | Q52: 0.2 | R52: -0.18 | S52: 0.28 | T52: 0.33 | U52: 0.45 | V52: 0.34 | W52: 0.05 | X52: 0.19 | Y52: 0.44 | Z52: 0.46 | AA52: 0.38 | AB52: 0.46 | AC52: 0.38 | AD52: 0.42 | AE52: 0.59 | AF52: 0.52 | AG52: 0.19 | AH52: 0.56 | AI52: 0.48 | AJ52: 0.52 | AK52: 0.42 | AL52: 0.44 | AM52: 0.41 | AN52: 0.4 | AO52: 0.46 | AP52: 0.43 | AQ52: 0.35 | AR52: 0.35 | AS52: 0.55 | AT52: 0.56 | AU52: 0.3 | AV52: 0.12 | AW52: 0.44 | AX52: -0.12 | AY52: 0.4 | AZ52: 1
B53: Gold | C53: -0.01 | D53: 0.1 | E53: 0.36 | F53: 0.3 | G53: 0.47 | H53: 0.39 | I53: 0.33 | J53: 0.37 | K53: 0.34 | L53: 0.36 | M53: 0.32 | N53: 0.13 | O53: 0.04 | P53: 0.28 | Q53: 0.51 | R53: 0.22 | S53: 0.5 | T53: 0.33 | U53: 0.39 | V53: 0.31 | W53: 0.24 | X53: 0.16 | Y53: 0.04 | Z53: 0.04 | AA53: -0.03 | AB53: 0.11 | AC53: 0.05 | AD53: 0.22 | AE53: 0.13 | AF53: 0.13 | AG53: 0.2 | AH53: 0.25 | AI53: 0.22 | AJ53: 0.11 | AK53: 0 | AL53: 0.06 | AM53: 0.06 | AN53: 0.08 | AO53: 0.05 | AP53: 0.12 | AQ53: 0.08 | AR53: 0.08 | AS53: 0.1 | AT53: 0.23 | AU53: 0.09 | AV53: 0.39 | AW53: 0.17 | AX53: 0.08 | AY53: 0.23 | AZ53: 0.35 | BA53: 1
B54: Private Equity | C54: 0.09 | D54: 0 | E54: -0.33 | F54: 0.37 | G54: 0.18 | H54: 0 | I54: 0.02 | J54: 0.02 | K54: -0.06 | L54: 0.36 | M54: 0.26 | N54: 0.72 | O54: 0.68 | P54: -0.24 | Q54: 0.09 | R54: -0.15 | S54: 0.2 | T54: 0.59 | U54: 0.6 | V54: 0.62 | W54: 0.13 | X54: 0.38 | Y54: 0.78 | Z54: 0.8 | AA54: 0.75 | AB54: 0.77 | AC54: 0.61 | AD54: 0.68 | AE54: 0.79 | AF54: 0.8 | AG54: 0.5 | AH54: 0.8 | AI54: 0.77 | AJ54: 0.83 | AK54: 0.77 | AL54: 0.79 | AM54: 0.77 | AN54: 0.72 | AO54: 0.74 | AP54: 0.81 | AQ54: 0.34 | AR54: 0.34 | AS54: 0.63 | AT54: 0.7 | AU54: 0.53 | AV54: 0.35 | AW54: 0.62 | AX54: -0.19 | AY54: 0.59 | AZ54: 0.55 | BA54: 0.11 | BB54: 1
B55: Venture Capital | C55: -0.06 | D55: 0.07 | E55: -0.24 | F55: 0.24 | G55: 0.16 | H55: 0.03 | I55: 0.05 | J55: 0.03 | K55: -0.02 | L55: 0.27 | M55: 0.2 | N55: 0.54 | O55: 0.51 | P55: -0.11 | Q55: 0.02 | R55: -0.03 | S55: 0.1 | T55: 0.45 | U55: 0.4 | V55: 0.47 | W55: 0.12 | X55: 0.33 | Y55: 0.64 | Z55: 0.67 | AA55: 0.7 | AB55: 0.55 | AC55: 0.51 | AD55: 0.5 | AE55: 0.55 | AF55: 0.58 | AG55: 0.47 | AH55: 0.61 | AI55: 0.6 | AJ55: 0.64 | AK55: 0.6 | AL55: 0.67 | AM55: 0.62 | AN55: 0.54 | AO55: 0.55 | AP55: 0.73 | AQ55: 0.26 | AR55: 0.26 | AS55: 0.52 | AT55: 0.44 | AU55: 0.35 | AV55: 0.29 | AW55: 0.42 | AX55: -0.15 | AY55: 0.4 | AZ55: 0.3 | BA55: 0 | BB55: 0.76 | BC55: 1
B56: Diversified Hedge Funds | C56: 0.08 | D56: 0.04 | E56: -0.3 | F56: 0.21 | G56: 0.2 | H56: 0.04 | I56: 0.02 | J56: 0.05 | K56: 0.06 | L56: 0.35 | M56: 0.31 | N56: 0.61 | O56: 0.67 | P56: -0.17 | Q56: 0.04 | R56: -0.09 | S56: 0.12 | T56: 0.46 | U56: 0.41 | V56: 0.5 | W56: 0.1 | X56: 0.41 | Y56: 0.68 | Z56: 0.71 | AA56: 0.64 | AB56: 0.64 | AC56: 0.59 | AD56: 0.56 | AE56: 0.69 | AF56: 0.7 | AG56: 0.44 | AH56: 0.68 | AI56: 0.64 | AJ56: 0.73 | AK56: 0.63 | AL56: 0.74 | AM56: 0.65 | AN56: 0.6 | AO56: 0.61 | AP56: 0.79 | AQ56: 0.32 | AR56: 0.32 | AS56: 0.56 | AT56: 0.6 | AU56: 0.42 | AV56: 0.27 | AW56: 0.43 | AX56: -0.18 | AY56: 0.47 | AZ56: 0.51 | BA56: 0.12 | BB56: 0.79 | BC56: 0.7 | BD56: 1
B57: Event Driven Hedge Funds | C57: 0.07 | D57: 0.02 | E57: -0.23 | F57: 0.21 | G57: 0.24 | H57: 0.12 | I57: 0.13 | J57: 0.06 | K57: 0.11 | L57: 0.42 | M57: 0.38 | N57: 0.77 | O57: 0.76 | P57: -0.12 | Q57: 0.15 | R57: -0.03 | S57: 0.24 | T57: 0.56 | U57: 0.54 | V57: 0.58 | W57: 0.16 | X57: 0.4 | Y57: 0.8 | Z57: 0.85 | AA57: 0.82 | AB57: 0.77 | AC57: 0.69 | AD57: 0.61 | AE57: 0.8 | AF57: 0.82 | AG57: 0.41 | AH57: 0.75 | AI57: 0.71 | AJ57: 0.85 | AK57: 0.81 | AL57: 0.81 | AM57: 0.78 | AN57: 0.72 | AO57: 0.79 | AP57: 0.87 | AQ57: 0.35 | AR57: 0.35 | AS57: 0.54 | AT57: 0.67 | AU57: 0.59 | AV57: 0.3 | AW57: 0.49 | AX57: -0.16 | AY57: 0.48 | AZ57: 0.55 | BA57: 0.06 | BB57: 0.83 | BC57: 0.67 | BD57: 0.86 | BE57: 1
B58: Long Bias Hedge Funds | C58: 0 | D58: 0 | E58: -0.16 | F58: 0.14 | G58: 0.28 | H58: 0.2 | I58: 0.2 | J58: 0.13 | K58: 0.19 | L58: 0.48 | M58: 0.44 | N58: 0.77 | O58: 0.68 | P58: -0.05 | Q58: 0.26 | R58: 0.02 | S58: 0.35 | T58: 0.62 | U58: 0.62 | V58: 0.62 | W58: 0.19 | X58: 0.34 | Y58: 0.87 | Z58: 0.9 | AA58: 0.86 | AB58: 0.83 | AC58: 0.76 | AD58: 0.71 | AE58: 0.84 | AF58: 0.89 | AG58: 0.48 | AH58: 0.85 | AI58: 0.82 | AJ58: 0.92 | AK58: 0.86 | AL58: 0.89 | AM58: 0.85 | AN58: 0.78 | AO58: 0.82 | AP58: 0.93 | AQ58: 0.28 | AR58: 0.28 | AS58: 0.56 | AT58: 0.65 | AU58: 0.62 | AV58: 0.3 | AW58: 0.51 | AX58: -0.18 | AY58: 0.51 | AZ58: 0.56 | BA58: 0.15 | BB58: 0.85 | BC58: 0.73 | BD58: 0.86 | BE58: 0.93 | BF58: 1
B59: Relative Value Hedge Funds | C59: 0.13 | D59: 0.04 | E59: -0.27 | F59: 0.22 | G59: 0.26 | H59: 0.13 | I59: 0.13 | J59: 0.07 | K59: 0.11 | L59: 0.45 | M59: 0.39 | N59: 0.82 | O59: 0.86 | P59: -0.14 | Q59: 0.09 | R59: -0.06 | S59: 0.18 | T59: 0.59 | U59: 0.55 | V59: 0.64 | W59: 0.19 | X59: 0.47 | Y59: 0.69 | Z59: 0.74 | AA59: 0.67 | AB59: 0.69 | AC59: 0.65 | AD59: 0.65 | AE59: 0.75 | AF59: 0.75 | AG59: 0.44 | AH59: 0.76 | AI59: 0.72 | AJ59: 0.77 | AK59: 0.7 | AL59: 0.71 | AM59: 0.66 | AN59: 0.64 | AO59: 0.69 | AP59: 0.82 | AQ59: 0.4 | AR59: 0.4 | AS59: 0.59 | AT59: 0.71 | AU59: 0.51 | AV59: 0.39 | AW59: 0.54 | AX59: -0.18 | AY59: 0.44 | AZ59: 0.56 | BA59: 0.09 | BB59: 0.79 | BC59: 0.6 | BD59: 0.83 | BE59: 0.91 | BF59: 0.86 | BG59: 1
B60: Macro Hedge Funds | C60: 0 | D60: 0.05 | E60: -0.11 | F60: 0.09 | G60: 0.07 | H60: -0.08 | I60: -0.16 | J60: 0.01 | K60: -0.02 | L60: 0.04 | M60: 0.05 | N60: 0.1 | O60: 0.07 | P60: -0.11 | Q60: 0.09 | R60: -0.08 | S60: 0.11 | T60: 0.08 | U60: 0.16 | V60: 0.05 | W60: -0.1 | X60: 0.06 | Y60: 0.16 | Z60: 0.19 | AA60: 0.14 | AB60: 0.21 | AC60: 0.14 | AD60: 0.18 | AE60: 0.26 | AF60: 0.24 | AG60: 0.11 | AH60: 0.26 | AI60: 0.23 | AJ60: 0.23 | AK60: 0.16 | AL60: 0.19 | AM60: 0.16 | AN60: 0.18 | AO60: 0.19 | AP60: 0.24 | AQ60: 0.01 | AR60: 0.01 | AS60: 0.13 | AT60: 0.14 | AU60: 0.1 | AV60: -0.16 | AW60: 0 | AX60: -0.14 | AY60: 0.33 | AZ60: 0.42 | BA60: 0.31 | BB60: 0.26 | BC60: 0.14 | BD60: 0.48 | BE60: 0.29 | BF60: 0.33 | BG60: 0.28 | BH60: 1
B61: Direct Lending | C61: 0.21 | D61: 0.03 | E61: -0.29 | F61: 0.27 | G61: 0.18 | H61: 0.04 | I61: 0.13 | J61: 0.06 | K61: 0 | L61: 0.28 | M61: 0.24 | N61: 0.67 | O61: 0.67 | P61: -0.15 | Q61: -0.02 | R61: -0.05 | S61: 0.07 | T61: 0.48 | U61: 0.43 | V61: 0.5 | W61: 0.17 | X61: 0.46 | Y61: 0.65 | Z61: 0.69 | AA61: 0.64 | AB61: 0.58 | AC61: 0.48 | AD61: 0.46 | AE61: 0.63 | AF61: 0.61 | AG61: 0.23 | AH61: 0.57 | AI61: 0.52 | AJ61: 0.65 | AK61: 0.67 | AL61: 0.65 | AM61: 0.63 | AN61: 0.63 | AO61: 0.66 | AP61: 0.61 | AQ61: 0.43 | AR61: 0.43 | AS61: 0.48 | AT61: 0.68 | AU61: 0.55 | AV61: 0.48 | AW61: 0.48 | AX61: 0.05 | AY61: 0.37 | AZ61: 0.47 | BA61: 0.06 | BB61: 0.68 | BC61: 0.48 | BD61: 0.63 | BE61: 0.73 | BF61: 0.68 | BG61: 0.74 | BH61: 0.06 | BI61: 1
G67: US Treasuries, Short/Intermediate | H67: US Treasuries, Long | I67: Residential Mortgage-Backed Securities | J67: US Public Corporates IG AAA | K67: US Public Corporates, HY Intermediate | L67: Corporate HY Private (Leveraged Loans) | M67: Global ex-US Government, hedged | N67: US Taxable Munis | O67: Real Estate (via partnerships, equity) | P67: Residential Mortgage Whole Loans | Q67: Private Equity | R67: Corporate IG Private Placement A | Y67: US Treasuries, Short/Intermediate | Z67: US Treasuries, Long | AA67: US Taxable Munis | AB67: Global ex-US Government, hedged | AC67: US Public Corporates IG AAA | AD67: US Public Corporates IG AA | AE67: US Public Corporates IG A | AF67: US Public Corporates IG BBB | AG67: US Public Corporates, HY Intermediate | AH67: US Public Corporates, HY Long | AI67: Global ex-US Corporates, hedged | AJ67: Residential Mortgage-Backed Securities | AK67: Commercial Mortgage-Backed Securities | AL67: Asset-Backed Securities | AM67: Corporate IG Private Placement A | AN67: Corporate IG Private Placement BBB | AO67: Corporate HY Private (Leveraged Loans) | AP67: Residential Mortgage Whole Loans | AQ67: Commercial Mortgage Whole Loans | AR67: Private Equity | AS67: Real Estate (via partnerships, equity)
I68: Commercial Mortgage-Backed Securities | J68: US Public Corporates IG AA | K68: US Public Corporates, HY Long | M68: Global ex-US Corporates, hedged | P68: Commercial Mortgage Whole Loans | R68: Corporate IG Private Placement BBB | X68: US Treasuries, Short/Intermediate | Y68: =IFERROR(INDEX($G$72:$R$83,MATCH($X68,$B$72:$B$83,0),MATCH(Y$67,$G$67:$R$67,0)), IFERROR(INDEX($G$72:$R$83,MATCH($X68,$B$72:$B$83,0),MATCH(Y$67,$G$68:$R$68,0)), IFERROR(INDEX($G$72:$R$83,MATCH($X68,$B$72:$B$83,0),MATCH(Y$67,$G$69:$R$69,0)), IFERROR(INDEX($G$72:$R$83,MATCH($X68,$B$72:$B$83,0),MATCH(Y$67,$G$70:$R$70,0)), IFERROR(INDEX($G$72:$R$83,MATCH($X68,$C$72:$C$83,0),MATCH(Y$67,$G$67:$R$67,0)), IFERROR(INDEX($G$72:$R$83,MATCH($X68,$C$72:$C$83,0),MATCH(Y$67,$G$68:$R$68,0)), IFERROR(INDEX($G$72:$R$83,MATCH($X68,$C$72:$C$83,0),MATCH(Y$67,$G$69:$R$69,0)), IFERROR(INDEX($G$72:$R$83,MATCH($X68,$C$72:$C$83,0),MATCH(Y$67,$G$70:$R$70,0)), IFERROR(INDEX($G$72:$R$83,MATCH($X68,$D$72:$D$83,0),MATCH(Y$67,$G$67:$R$67,0)), IFERROR(INDEX($G$72:$R$83,MATCH($X68,$D$72:$D$83,0),MATCH(Y$67,$G$68:$R$68,0)), IFERROR(INDEX($G$72:$R$83,MATCH($X68,$D$72:$D$83,0),MATCH(Y$67,$G$69:$R$69,0)), IFERROR(INDEX($G$72:$R$83,MATCH($X68,$D$72:$D$83,0),MATCH(Y$67,$G$70:$R$70,0)), IFERROR(INDEX($G$72:$R$83,MATCH($X68,$E$72:$E$83,0),MATCH(Y$67,$G$67:$R$67,0)), IFERROR(INDEX($G$72:$R$83,MATCH($X68,$E$72:$E$83,0),MATCH(Y$67,$G$68:$R$68,0)), IFERROR(INDEX($G$72:$R$83,MATCH($X68,$E$72:$E$83,0),MATCH(Y$67,$G$69:$R$69,0)), INDEX($G$72:$R$83,MATCH($X68,$E$72:$E$83,0),MATCH(Y$67,$G$70:$R$70,0))))))))))))))))) -> 1 | Z68: =IFERROR(INDEX($G$72:$R$83,MATCH($X68,$B$72:$B$83,0),MATCH(Z$67,$G$67:$R$67,0)), IFERROR(INDEX($G$72:$R$83,MATCH($X68,$B$72:$B$83,0),MATCH(Z$67,$G$68:$R$68,0)), IFERROR(INDEX($G$72:$R$83,MATCH($X68,$B$72:$B$83,0),MATCH(Z$67,$G$69:$R$69,0)), IFERROR(INDEX($G$72:$R$83,MATCH($X68,$B$72:$B$83,0),MATCH(Z$67,$G$70:$R$70,0)), IFERROR(INDEX($G$72:$R$83,MATCH($X68,$C$72:$C$83,0),MATCH(Z$67,$G$67:$R$67,0)), IFERROR(INDEX($G$72:$R$83,MATCH($X68,$C$72:$C$83,0),MATCH(Z$67,$G$68:$R$68,0)), IFERROR(INDEX($G$72:$R$83,MATCH($X68,$C$72:$C$83,0),MATCH(Z$67,$G$69:$R$69,0)), IFERROR(INDEX($G$72:$R$83,MATCH($X68,$C$72:$C$83,0),MATCH(Z$67,$G$70:$R$70,0)), IFERROR(INDEX($G$72:$R$83,MATCH($X68,$D$72:$D$83,0),MATCH(Z$67,$G$67:$R$67,0)), IFERROR(INDEX($G$72:$R$83,MATCH($X68,$D$72:$D$83,0),MATCH(Z$67,$G$68:$R$68,0)), IFERROR(INDEX($G$72:$R$83,MATCH($X68,$D$72:$D$83,0),MATCH(Z$67,$G$69:$R$69,0)), IFERROR(INDEX($G$72:$R$83,MATCH($X68,$D$72:$D$83,0),MATCH(Z$67,$G$70:$R$70,0)), IFERROR(INDEX($G$72:$R$83,MATCH($X68,$E$72:$E$83,0),MATCH(Z$67,$G$67:$R$67,0)), IFERROR(INDEX($G$72:$R$83,MATCH($X68,$E$72:$E$83,0),MATCH(Z$67,$G$68:$R$68,0)), IFERROR(INDEX($G$72:$R$83,MATCH($X68,$E$72:$E$83,0),MATCH(Z$67,$G$69:$R$69,0)), INDEX($G$72:$R$83,MATCH($X68,$E$72:$E$83,0),MATCH(Z$67,$G$70:$R$70,0))))))))))))))))) -> 0.83 | AA68: =IFERROR(INDEX($G$72:$R$83,MATCH($X68,$B$72:$B$83,0),MATCH(AA$67,$G$67:$R$67,0)), IFERROR(INDEX($G$72:$R$83,MATCH($X68,$B$72:$B$83,0),MATCH(AA$67,$G$68:$R$68,0)), IFERROR(INDEX($G$72:$R$83,MATCH($X68,$B$72:$B$83,0),MATCH(AA$67,$G$69:$R$69,0)), IFERROR(INDEX($G$72:$R$83,MATCH($X68,$B$72:$B$83,0),MATCH(AA$67,$G$70:$R$70,0)), IFERROR(INDEX($G$72:$R$83,MATCH($X68,$C$72:$C$83,0),MATCH(AA$67,$G$67:$R$67,0)), IFERROR(INDEX($G$72:$R$83,MATCH($X68,$C$72:$C$83,0),MATCH(AA$67,$G$68:$R$68,0)), IFERROR(INDEX($G$72:$R$83,MATCH($X68,$C$72:$C$83,0),MATCH(AA$67,$G$69:$R$69,0)), IFERROR(INDEX($G$72:$R$83,MATCH($X68,$C$72:$C$83,0),MATCH(AA$67,$G$70:$R$70,0)), IFERROR(INDEX($G$72:$R$83,MATCH($X68,$D$72:$D$83,0),MATCH(AA$67,$G$67:$R$67,0)), IFERROR(INDEX($G$72:$R$83,MATCH($X68,$D$72:$D$83,0),MATCH(AA$67,$G$68:$R$68,0)), IFERROR(INDEX($G$72:$R$83,MATCH($X68,$D$72:$D$83,0),MATCH(AA$67,$G$69:$R$69,0)), IFERROR(INDEX($G$72:$R$83,MATCH($X68,$D$72:$D$83,0),MATCH(AA$67,$G$70:$R$70,0)), IFERROR(INDEX($G$72:$R$83,MATCH($X68,$E$72:$E$83,0),MATCH(AA$67,$G$67:$R$67,0)), IFERROR(INDEX($G$72:$R$83,MATCH($X68,$E$72:$E$83,0),MATCH(AA$67,$G$68:$R$68,0)), IFERROR(INDEX($G$72:$R$83,MATCH($X68,$E$72:$E$83,0),MATCH(AA$67,$G$69:$R$69,0)), INDEX($G$72:$R$83,MATCH($X68,$E$72:$E$83,0),MATCH(AA$67,$G$70:$R$70,0))))))))))))))))) -> 0.52 | AB68: =IFERROR(INDEX($G$72:$R$83,MATCH($X68,$B$72:$B$83,0),MATCH(AB$67,$G$67:$R$67,0)), IFERROR(INDEX($G$72:$R$83,MATCH($X68,$B$72:$B$83,0),MATCH(AB$67,$G$68:$R$68,0)), IFERROR(INDEX($G$72:$R$83,MATCH($X68,$B$72:$B$83,0),MATCH(AB$67,$G$69:$R$69,0)), IFERROR(INDEX($G$72:$R$83,MATCH($X68,$B$72:$B$83,0),MATCH(AB$67,$G$70:$R$70,0)), IFERROR(INDEX($G$72:$R$83,MATCH($X68,$C$72:$C$83,0),MATCH(AB$67,$G$67:$R$67,0)), IFERROR(INDEX($G$72:$R$83,MATCH($X68,$C$72:$C$83,0),MATCH(AB$67,$G$68:$R$68,0)), IFERROR(INDEX($G$72:$R$83,MATCH($X68,$C$72:$C$83,0),MATCH(AB$67,$G$69:$R$69,0)), IFERROR(INDEX($G$72:$R$83,MATCH($X68,$C$72:$C$83,0),MATCH(AB$67,$G$70:$R$70,0)), IFERROR(INDEX($G$72:$R$83,MATCH($X68,$D$72:$D$83,0),MATCH(AB$67,$G$67:$R$67,0)), IFERROR(INDEX($G$72:$R$83,MATCH($X68,$D$72:$D$83,0),MATCH(AB$67,$G$68:$R$68,0)), IFERROR(INDEX($G$72:$R$83,MATCH($X68,$D$72:$D$83,0),MATCH(AB$67,$G$69:$R$69,0)), IFERROR(INDEX($G$72:$R$83,MATCH($X68,$D$72:$D$83,0),MATCH(AB$67,$G$70:$R$70,0)), IFERROR(INDEX($G$72:$R$83,MATCH($X68,$E$72:$E$83,0),MATCH(AB$67,$G$67:$R$67,0)), IFERROR(INDEX($G$72:$R$83,MATCH($X68,$E$72:$E$83,0),MATCH(AB$67,$G$68:$R$68,0)), IFERROR(INDEX($G$72:$R$83,MATCH($X68,$E$72:$E$83,0),MATCH(AB$67,$G$69:$R$69,0)), INDEX($G$72:$R$83,MATCH($X68,$E$72:$E$83,0),MATCH(AB$67,$G$70:$R$70,0))))))))))))))))) -> 0.72 | AC68: =IFERROR(INDEX($G$72:$R$83,MATCH($X68,$B$72:$B$83,0),MATCH(AC$67,$G$67:$R$67,0)), IFERROR(INDEX($G$72:$R$83,MATCH($X68,$B$72:$B$83,0),MATCH(AC$67,$G$68:$R$68,0)), IFERROR(INDEX($G$72:$R$83,MATCH($X68,$B$72:$B$83,0),MATCH(AC$67,$G$69:$R$69,0)), IFERROR(INDEX($G$72:$R$83,MATCH($X68,$B$72:$B$83,0),MATCH(AC$67,$G$70:$R$70,0)), IFERROR(INDEX($G$72:$R$83,MATCH($X68,$C$72:$C$83,0),MATCH(AC$67,$G$67:$R$67,0)), IFERROR(INDEX($G$72:$R$83,MATCH($X68,$C$72:$C$83,0),MATCH(AC$67,$G$68:$R$68,0)), IFERROR(INDEX($G$72:$R$83,MATCH($X68,$C$72:$C$83,0),MATCH(AC$67,$G$69:$R$69,0)), IFERROR(INDEX($G$72:$R$83,MATCH($X68,$C$72:$C$83,0),MATCH(AC$67,$G$70:$R$70,0)), IFERROR(INDEX($G$72:$R$83,MATCH($X68,$D$72:$D$83,0),MATCH(AC$67,$G$67:$R$67,0)), IFERROR(INDEX($G$72:$R$83,MATCH($X68,$D$72:$D$83,0),MATCH(AC$67,$G$68:$R$68,0)), IFERROR(INDEX($G$72:$R$83,MATCH($X68,$D$72:$D$83,0),MATCH(AC$67,$G$69:$R$69,0)), IFERROR(INDEX($G$72:$R$83,MATCH($X68,$D$72:$D$83,0),MATCH(AC$67,$G$70:$R$70,0)), IFERROR(INDEX($G$72:$R$83,MATCH($X68,$E$72:$E$83,0),MATCH(AC$67,$G$67:$R$67,0)), IFERROR(INDEX($G$72:$R$83,MATCH($X68,$E$72:$E$83,0),MATCH(AC$67,$G$68:$R$68,0)), IFERROR(INDEX($G$72:$R$83,MATCH($X68,$E$72:$E$83,0),MATCH(AC$67,$G$69:$R$69,0)), INDEX($G$72:$R$83,MATCH($X68,$E$72:$E$83,0),MATCH(AC$67,$G$70:$R$70,0))))))))))))))))) -> 0.52 | AD68: =IFERROR(INDEX($G$72:$R$83,MATCH($X68,$B$72:$B$83,0),MATCH(AD$67,$G$67:$R$67,0)), IFERROR(INDEX($G$72:$R$83,MATCH($X68,$B$72:$B$83,0),MATCH(AD$67,$G$68:$R$68,0)), IFERROR(INDEX($G$72:$R$83,MATCH($X68,$B$72:$B$83,0),MATCH(AD$67,$G$69:$R$69,0)), IFERROR(INDEX($G$72:$R$83,MATCH($X68,$B$72:$B$83,0),MATCH(AD$67,$G$70:$R$70,0)), IFERROR(INDEX($G$72:$R$83,MATCH($X68,$C$72:$C$83,0),MATCH(AD$67,$G$67:$R$67,0)), IFERROR(INDEX($G$72:$R$83,MATCH($X68,$C$72:$C$83,0),MATCH(AD$67,$G$68:$R$68,0)), IFERROR(INDEX($G$72:$R$83,MATCH($X68,$C$72:$C$83,0),MATCH(AD$67,$G$69:$R$69,0)), IFERROR(INDEX($G$72:$R$83,MATCH($X68,$C$72:$C$83,0),MATCH(AD$67,$G$70:$R$70,0)), IFERROR(INDEX($G$72:$R$83,MATCH($X68,$D$72:$D$83,0),MATCH(AD$67,$G$67:$R$67,0)), IFERROR(INDEX($G$72:$R$83,MATCH($X68,$D$72:$D$83,0),MATCH(AD$67,$G$68:$R$68,0)), IFERROR(INDEX($G$72:$R$83,MATCH($X68,$D$72:$D$83,0),MATCH(AD$67,$G$69:$R$69,0)), IFERROR(INDEX($G$72:$R$83,MATCH($X68,$D$72:$D$83,0),MATCH(AD$67,$G$70:$R$70,0)), IFERROR(INDEX($G$72:$R$83,MATCH($X68,$E$72:$E$83,0),MATCH(AD$67,$G$67:$R$67,0)), IFERROR(INDEX($G$72:$R$83,MATCH($X68,$E$72:$E$83,0),MATCH(AD$67,$G$68:$R$68,0)), IFERROR(INDEX($G$72:$R$83,MATCH($X68,$E$72:$E$83,0),MATCH(AD$67,$G$69:$R$69,0)), INDEX($G$72:$R$83,MATCH($X68,$E$72:$E$83,0),MATCH(AD$67,$G$70:$R$70,0))))))))))))))))) -> 0.52 | AE68: =IFERROR(INDEX($G$72:$R$83,MATCH($X68,$B$72:$B$83,0),MATCH(AE$67,$G$67:$R$67,0)), IFERROR(INDEX($G$72:$R$83,MATCH($X68,$B$72:$B$83,0),MATCH(AE$67,$G$68:$R$68,0)), IFERROR(INDEX($G$72:$R$83,MATCH($X68,$B$72:$B$83,0),MATCH(AE$67,$G$69:$R$69,0)), IFERROR(INDEX($G$72:$R$83,MATCH($X68,$B$72:$B$83,0),MATCH(AE$67,$G$70:$R$70,0)), IFERROR(INDEX($G$72:$R$83,MATCH($X68,$C$72:$C$83,0),MATCH(AE$67,$G$67:$R$67,0)), IFERROR(INDEX($G$72:$R$83,MATCH($X68,$C$72:$C$83,0),MATCH(AE$67,$G$68:$R$68,0)), IFERROR(INDEX($G$72:$R$83,MATCH($X68,$C$72:$C$83,0),MATCH(AE$67,$G$69:$R$69,0)), IFERROR(INDEX($G$72:$R$83,MATCH($X68,$C$72:$C$83,0),MATCH(AE$67,$G$70:$R$70,0)), IFERROR(INDEX($G$72:$R$83,MATCH($X68,$D$72:$D$83,0),MATCH(AE$67,$G$67:$R$67,0)), IFERROR(INDEX($G$72:$R$83,MATCH($X68,$D$72:$D$83,0),MATCH(AE$67,$G$68:$R$68,0)), IFERROR(INDEX($G$72:$R$83,MATCH($X68,$D$72:$D$83,0),MATCH(AE$67,$G$69:$R$69,0)), IFERROR(INDEX($G$72:$R$83,MATCH($X68,$D$72:$D$83,0),MATCH(AE$67,$G$70:$R$70,0)), IFERROR(INDEX($G$72:$R$83,MATCH($X68,$E$72:$E$83,0),MATCH(AE$67,$G$67:$R$67,0)), IFERROR(INDEX($G$72:$R$83,MATCH($X68,$E$72:$E$83,0),MATCH(AE$67,$G$68:$R$68,0)), IFERROR(INDEX($G$72:$R$83,MATCH($X68,$E$72:$E$83,0),MATCH(AE$67,$G$69:$R$69,0)), INDEX($G$72:$R$83,MATCH($X68,$E$72:$E$83,0),MATCH(AE$67,$G$70:$R$70,0))))))))))))))))) -> 0.52 | AF68: =IFERROR(INDEX($G$72:$R$83,MATCH($X68,$B$72:$B$83,0),MATCH(AF$67,$G$67:$R$67,0)), IFERROR(INDEX($G$72:$R$83,MATCH($X68,$B$72:$B$83,0),MATCH(AF$67,$G$68:$R$68,0)), IFERROR(INDEX($G$72:$R$83,MATCH($X68,$B$72:$B$83,0),MATCH(AF$67,$G$69:$R$69,0)), IFERROR(INDEX($G$72:$R$83,MATCH($X68,$B$72:$B$83,0),MATCH(AF$67,$G$70:$R$70,0)), IFERROR(INDEX($G$72:$R$83,MATCH($X68,$C$72:$C$83,0),MATCH(AF$67,$G$67:$R$67,0)), IFERROR(INDEX($G$72:$R$83,MATCH($X68,$C$72:$C$83,0),MATCH(AF$67,$G$68:$R$68,0)), IFERROR(INDEX($G$72:$R$83,MATCH($X68,$C$72:$C$83,0),MATCH(AF$67,$G$69:$R$69,0)), IFERROR(INDEX($G$72:$R$83,MATCH($X68,$C$72:$C$83,0),MATCH(AF$67,$G$70:$R$70,0)), IFERROR(INDEX($G$72:$R$83,MATCH($X68,$D$72:$D$83,0),MATCH(AF$67,$G$67:$R$67,0)), IFERROR(INDEX($G$72:$R$83,MATCH($X68,$D$72:$D$83,0),MATCH(AF$67,$G$68:$R$68,0)), IFERROR(INDEX($G$72:$R$83,MATCH($X68,$D$72:$D$83,0),MATCH(AF$67,$G$69:$R$69,0)), IFERROR(INDEX($G$72:$R$83,MATCH($X68,$D$72:$D$83,0),MATCH(AF$67,$G$70:$R$70,0)), IFERROR(INDEX($G$72:$R$83,MATCH($X68,$E$72:$E$83,0),MATCH(AF$67,$G$67:$R$67,0)), IFERROR(INDEX($G$72:$R$83,MATCH($X68,$E$72:$E$83,0),MATCH(AF$67,$G$68:$R$68,0)), IFERROR(INDEX($G$72:$R$83,MATCH($X68,$E$72:$E$83,0),MATCH(AF$67,$G$69:$R$69,0)), INDEX($G$72:$R$83,MATCH($X68,$E$72:$E$83,0),MATCH(AF$67,$G$70:$R$70,0))))))))))))))))) -> 0.52 | ... AS68: =IFERROR(INDEX($G$72:$R$83,MATCH($X68,$B$72:$B$83,0),MATCH(AS$67,$G$67:$R$67,0)), IFERROR(INDEX($G$72:$R$83,MATCH($X68,$B$72:$B$83,0),MATCH(AS$67,$G$68:$R$68,0)), IFERROR(INDEX($G$72:$R$83,MATCH($X68,$B$72:$B$83,0),MATCH(AS$67,$G$69:$R$69,0)), IFERROR(INDEX($G$72:$R$83,MATCH($X68,$B$72:$B$83,0),MATCH(AS$67,$G$70:$R$70,0)), IFERROR(INDEX($G$72:$R$83,MATCH($X68,$C$72:$C$83,0),MATCH(AS$67,$G$67:$R$67,0)), IFERROR(INDEX($G$72:$R$83,MATCH($X68,$C$72:$C$83,0),MATCH(AS$67,$G$68:$R$68,0)), IFERROR(INDEX($G$72:$R$83,MATCH($X68,$C$72:$C$83,0),MATCH(AS$67,$G$69:$R$69,0)), IFERROR(INDEX($G$72:$R$83,MATCH($X68,$C$72:$C$83,0),MATCH(AS$67,$G$70:$R$70,0)), IFERROR(INDEX($G$72:$R$83,MATCH($X68,$D$72:$D$83,0),MATCH(AS$67,$G$67:$R$67,0)), IFERROR(INDEX($G$72:$R$83,MATCH($X68,$D$72:$D$83,0),MATCH(AS$67,$G$68:$R$68,0)), IFERROR(INDEX($G$72:$R$83,MATCH($X68,$D$72:$D$83,0),MATCH(AS$67,$G$69:$R$69,0)), IFERROR(INDEX($G$72:$R$83,MATCH($X68,$D$72:$D$83,0),MATCH(AS$67,$G$70:$R$70,0)), IFERROR(INDEX($G$72:$R$83,MATCH($X68,$E$72:$E$83,0),MATCH(AS$67,$G$67:$R$67,0)), IFERROR(INDEX($G$72:$R$83,MATCH($X68,$E$72:$E$83,0),MATCH(AS$67,$G$68:$R$68,0)), IFERROR(INDEX($G$72:$R$83,MATCH($X68,$E$72:$E$83,0),MATCH(AS$67,$G$69:$R$69,0)), INDEX($G$72:$R$83,MATCH($X68,$E$72:$E$83,0),MATCH(AS$67,$G$70:$R$70,0))))))))))))))))) -> -0.27
I69: Asset-Backed Securities | J69: US Public Corporates IG A | X69: US Treasuries, Long | Y69: =IFERROR(INDEX($G$72:$R$83,MATCH($X69,$B$72:$B$83,0),MATCH(Y$67,$G$67:$R$67,0)), IFERROR(INDEX($G$72:$R$83,MATCH($X69,$B$72:$B$83,0),MATCH(Y$67,$G$68:$R$68,0)), IFERROR(INDEX($G$72:$R$83,MATCH($X69,$B$72:$B$83,0),MATCH(Y$67,$G$69:$R$69,0)), IFERROR(INDEX($G$72:$R$83,MATCH($X69,$B$72:$B$83,0),MATCH(Y$67,$G$70:$R$70,0)), IFERROR(INDEX($G$72:$R$83,MATCH($X69,$C$72:$C$83,0),MATCH(Y$67,$G$67:$R$67,0)), IFERROR(INDEX($G$72:$R$83,MATCH($X69,$C$72:$C$83,0),MATCH(Y$67,$G$68:$R$68,0)), IFERROR(INDEX($G$72:$R$83,MATCH($X69,$C$72:$C$83,0),MATCH(Y$67,$G$69:$R$69,0)), IFERROR(INDEX($G$72:$R$83,MATCH($X69,$C$72:$C$83,0),MATCH(Y$67,$G$70:$R$70,0)), IFERROR(INDEX($G$72:$R$83,MATCH($X69,$D$72:$D$83,0),MATCH(Y$67,$G$67:$R$67,0)), IFERROR(INDEX($G$72:$R$83,MATCH($X69,$D$72:$D$83,0),MATCH(Y$67,$G$68:$R$68,0)), IFERROR(INDEX($G$72:$R$83,MATCH($X69,$D$72:$D$83,0),MATCH(Y$67,$G$69:$R$69,0)), IFERROR(INDEX($G$72:$R$83,MATCH($X69,$D$72:$D$83,0),MATCH(Y$67,$G$70:$R$70,0)), IFERROR(INDEX($G$72:$R$83,MATCH($X69,$E$72:$E$83,0),MATCH(Y$67,$G$67:$R$67,0)), IFERROR(INDEX($G$72:$R$83,MATCH($X69,$E$72:$E$83,0),MATCH(Y$67,$G$68:$R$68,0)), IFERROR(INDEX($G$72:$R$83,MATCH($X69,$E$72:$E$83,0),MATCH(Y$67,$G$69:$R$69,0)), INDEX($G$72:$R$83,MATCH($X69,$E$72:$E$83,0),MATCH(Y$67,$G$70:$R$70,0))))))))))))))))) -> 0.83 | Z69: =IFERROR(INDEX($G$72:$R$83,MATCH($X69,$B$72:$B$83,0),MATCH(Z$67,$G$67:$R$67,0)), IFERROR(INDEX($G$72:$R$83,MATCH($X69,$B$72:$B$83,0),MATCH(Z$67,$G$68:$R$68,0)), IFERROR(INDEX($G$72:$R$83,MATCH($X69,$B$72:$B$83,0),MATCH(Z$67,$G$69:$R$69,0)), IFERROR(INDEX($G$72:$R$83,MATCH($X69,$B$72:$B$83,0),MATCH(Z$67,$G$70:$R$70,0)), IFERROR(INDEX($G$72:$R$83,MATCH($X69,$C$72:$C$83,0),MATCH(Z$67,$G$67:$R$67,0)), IFERROR(INDEX($G$72:$R$83,MATCH($X69,$C$72:$C$83,0),MATCH(Z$67,$G$68:$R$68,0)), IFERROR(INDEX($G$72:$R$83,MATCH($X69,$C$72:$C$83,0),MATCH(Z$67,$G$69:$R$69,0)), IFERROR(INDEX($G$72:$R$83,MATCH($X69,$C$72:$C$83,0),MATCH(Z$67,$G$70:$R$70,0)), IFERROR(INDEX($G$72:$R$83,MATCH($X69,$D$72:$D$83,0),MATCH(Z$67,$G$67:$R$67,0)), IFERROR(INDEX($G$72:$R$83,MATCH($X69,$D$72:$D$83,0),MATCH(Z$67,$G$68:$R$68,0)), IFERROR(INDEX($G$72:$R$83,MATCH($X69,$D$72:$D$83,0),MATCH(Z$67,$G$69:$R$69,0)), IFERROR(INDEX($G$72:$R$83,MATCH($X69,$D$72:$D$83,0),MATCH(Z$67,$G$70:$R$70,0)), IFERROR(INDEX($G$72:$R$83,MATCH($X69,$E$72:$E$83,0),MATCH(Z$67,$G$67:$R$67,0)), IFERROR(INDEX($G$72:$R$83,MATCH($X69,$E$72:$E$83,0),MATCH(Z$67,$G$68:$R$68,0)), IFERROR(INDEX($G$72:$R$83,MATCH($X69,$E$72:$E$83,0),MATCH(Z$67,$G$69:$R$69,0)), INDEX($G$72:$R$83,MATCH($X69,$E$72:$E$83,0),MATCH(Z$67,$G$70:$R$70,0))))))))))))))))) -> 1 | AA69: =IFERROR(INDEX($G$72:$R$83,MATCH($X69,$B$72:$B$83,0),MATCH(AA$67,$G$67:$R$67,0)), IFERROR(INDEX($G$72:$R$83,MATCH($X69,$B$72:$B$83,0),MATCH(AA$67,$G$68:$R$68,0)), IFERROR(INDEX($G$72:$R$83,MATCH($X69,$B$72:$B$83,0),MATCH(AA$67,$G$69:$R$69,0)), IFERROR(INDEX($G$72:$R$83,MATCH($X69,$B$72:$B$83,0),MATCH(AA$67,$G$70:$R$70,0)), IFERROR(INDEX($G$72:$R$83,MATCH($X69,$C$72:$C$83,0),MATCH(AA$67,$G$67:$R$67,0)), IFERROR(INDEX($G$72:$R$83,MATCH($X69,$C$72:$C$83,0),MATCH(AA$67,$G$68:$R$68,0)), IFERROR(INDEX($G$72:$R$83,MATCH($X69,$C$72:$C$83,0),MATCH(AA$67,$G$69:$R$69,0)), IFERROR(INDEX($G$72:$R$83,MATCH($X69,$C$72:$C$83,0),MATCH(AA$67,$G$70:$R$70,0)), IFERROR(INDEX($G$72:$R$83,MATCH($X69,$D$72:$D$83,0),MATCH(AA$67,$G$67:$R$67,0)), IFERROR(INDEX($G$72:$R$83,MATCH($X69,$D$72:$D$83,0),MATCH(AA$67,$G$68:$R$68,0)), IFERROR(INDEX($G$72:$R$83,MATCH($X69,$D$72:$D$83,0),MATCH(AA$67,$G$69:$R$69,0)), IFERROR(INDEX($G$72:$R$83,MATCH($X69,$D$72:$D$83,0),MATCH(AA$67,$G$70:$R$70,0)), IFERROR(INDEX($G$72:$R$83,MATCH($X69,$E$72:$E$83,0),MATCH(AA$67,$G$67:$R$67,0)), IFERROR(INDEX($G$72:$R$83,MATCH($X69,$E$72:$E$83,0),MATCH(AA$67,$G$68:$R$68,0)), IFERROR(INDEX($G$72:$R$83,MATCH($X69,$E$72:$E$83,0),MATCH(AA$67,$G$69:$R$69,0)), INDEX($G$72:$R$83,MATCH($X69,$E$72:$E$83,0),MATCH(AA$67,$G$70:$R$70,0))))))))))))))))) -> 0.51 | AB69: =IFERROR(INDEX($G$72:$R$83,MATCH($X69,$B$72:$B$83,0),MATCH(AB$67,$G$67:$R$67,0)), IFERROR(INDEX($G$72:$R$83,MATCH($X69,$B$72:$B$83,0),MATCH(AB$67,$G$68:$R$68,0)), IFERROR(INDEX($G$72:$R$83,MATCH($X69,$B$72:$B$83,0),MATCH(AB$67,$G$69:$R$69,0)), IFERROR(INDEX($G$72:$R$83,MATCH($X69,$B$72:$B$83,0),MATCH(AB$67,$G$70:$R$70,0)), IFERROR(INDEX($G$72:$R$83,MATCH($X69,$C$72:$C$83,0),MATCH(AB$67,$G$67:$R$67,0)), IFERROR(INDEX($G$72:$R$83,MATCH($X69,$C$72:$C$83,0),MATCH(AB$67,$G$68:$R$68,0)), IFERROR(INDEX($G$72:$R$83,MATCH($X69,$C$72:$C$83,0),MATCH(AB$67,$G$69:$R$69,0)), IFERROR(INDEX($G$72:$R$83,MATCH($X69,$C$72:$C$83,0),MATCH(AB$67,$G$70:$R$70,0)), IFERROR(INDEX($G$72:$R$83,MATCH($X69,$D$72:$D$83,0),MATCH(AB$67,$G$67:$R$67,0)), IFERROR(INDEX($G$72:$R$83,MATCH($X69,$D$72:$D$83,0),MATCH(AB$67,$G$68:$R$68,0)), IFERROR(INDEX($G$72:$R$83,MATCH($X69,$D$72:$D$83,0),MATCH(AB$67,$G$69:$R$69,0)), IFERROR(INDEX($G$72:$R$83,MATCH($X69,$D$72:$D$83,0),MATCH(AB$67,$G$70:$R$70,0)), IFERROR(INDEX($G$72:$R$83,MATCH($X69,$E$72:$E$83,0),MATCH(AB$67,$G$67:$R$67,0)), IFERROR(INDEX($G$72:$R$83,MATCH($X69,$E$72:$E$83,0),MATCH(AB$67,$G$68:$R$68,0)), IFERROR(INDEX($G$72:$R$83,MATCH($X69,$E$72:$E$83,0),MATCH(AB$67,$G$69:$R$69,0)), INDEX($G$72:$R$83,MATCH($X69,$E$72:$E$83,0),MATCH(AB$67,$G$70:$R$70,0))))))))))))))))) -> 0.74 | AC69: =IFERROR(INDEX($G$72:$R$83,MATCH($X69,$B$72:$B$83,0),MATCH(AC$67,$G$67:$R$67,0)), IFERROR(INDEX($G$72:$R$83,MATCH($X69,$B$72:$B$83,0),MATCH(AC$67,$G$68:$R$68,0)), IFERROR(INDEX($G$72:$R$83,MATCH($X69,$B$72:$B$83,0),MATCH(AC$67,$G$69:$R$69,0)), IFERROR(INDEX($G$72:$R$83,MATCH($X69,$B$72:$B$83,0),MATCH(AC$67,$G$70:$R$70,0)), IFERROR(INDEX($G$72:$R$83,MATCH($X69,$C$72:$C$83,0),MATCH(AC$67,$G$67:$R$67,0)), IFERROR(INDEX($G$72:$R$83,MATCH($X69,$C$72:$C$83,0),MATCH(AC$67,$G$68:$R$68,0)), IFERROR(INDEX($G$72:$R$83,MATCH($X69,$C$72:$C$83,0),MATCH(AC$67,$G$69:$R$69,0)), IFERROR(INDEX($G$72:$R$83,MATCH($X69,$C$72:$C$83,0),MATCH(AC$67,$G$70:$R$70,0)), IFERROR(INDEX($G$72:$R$83,MATCH($X69,$D$72:$D$83,0),MATCH(AC$67,$G$67:$R$67,0)), IFERROR(INDEX($G$72:$R$83,MATCH($X69,$D$72:$D$83,0),MATCH(AC$67,$G$68:$R$68,0)), IFERROR(INDEX($G$72:$R$83,MATCH($X69,$D$72:$D$83,0),MATCH(AC$67,$G$69:$R$69,0)), IFERROR(INDEX($G$72:$R$83,MATCH($X69,$D$72:$D$83,0),MATCH(AC$67,$G$70:$R$70,0)), IFERROR(INDEX($G$72:$R$83,MATCH($X69,$E$72:$E$83,0),MATCH(AC$67,$G$67:$R$67,0)), IFERROR(INDEX($G$72:$R$83,MATCH($X69,$E$72:$E$83,0),MATCH(AC$67,$G$68:$R$68,0)), IFERROR(INDEX($G$72:$R$83,MATCH($X69,$E$72:$E$83,0),MATCH(AC$67,$G$69:$R$69,0)), INDEX($G$72:$R$83,MATCH($X69,$E$72:$E$83,0),MATCH(AC$67,$G$70:$R$70,0))))))))))))))))) -> 0.6 | AD69: =IFERROR(INDEX($G$72:$R$83,MATCH($X69,$B$72:$B$83,0),MATCH(AD$67,$G$67:$R$67,0)), IFERROR(INDEX($G$72:$R$83,MATCH($X69,$B$72:$B$83,0),MATCH(AD$67,$G$68:$R$68,0)), IFERROR(INDEX($G$72:$R$83,MATCH($X69,$B$72:$B$83,0),MATCH(AD$67,$G$69:$R$69,0)), IFERROR(INDEX($G$72:$R$83,MATCH($X69,$B$72:$B$83,0),MATCH(AD$67,$G$70:$R$70,0)), IFERROR(INDEX($G$72:$R$83,MATCH($X69,$C$72:$C$83,0),MATCH(AD$67,$G$67:$R$67,0)), IFERROR(INDEX($G$72:$R$83,MATCH($X69,$C$72:$C$83,0),MATCH(AD$67,$G$68:$R$68,0)), IFERROR(INDEX($G$72:$R$83,MATCH($X69,$C$72:$C$83,0),MATCH(AD$67,$G$69:$R$69,0)), IFERROR(INDEX($G$72:$R$83,MATCH($X69,$C$72:$C$83,0),MATCH(AD$67,$G$70:$R$70,0)), IFERROR(INDEX($G$72:$R$83,MATCH($X69,$D$72:$D$83,0),MATCH(AD$67,$G$67:$R$67,0)), IFERROR(INDEX($G$72:$R$83,MATCH($X69,$D$72:$D$83,0),MATCH(AD$67,$G$68:$R$68,0)), IFERROR(INDEX($G$72:$R$83,MATCH($X69,$D$72:$D$83,0),MATCH(AD$67,$G$69:$R$69,0)), IFERROR(INDEX($G$72:$R$83,MATCH($X69,$D$72:$D$83,0),MATCH(AD$67,$G$70:$R$70,0)), IFERROR(INDEX($G$72:$R$83,MATCH($X69,$E$72:$E$83,0),MATCH(AD$67,$G$67:$R$67,0)), IFERROR(INDEX($G$72:$R$83,MATCH($X69,$E$72:$E$83,0),MATCH(AD$67,$G$68:$R$68,0)), IFERROR(INDEX($G$72:$R$83,MATCH($X69,$E$72:$E$83,0),MATCH(AD$67,$G$69:$R$69,0)), INDEX($G$72:$R$83,MATCH($X69,$E$72:$E$83,0),MATCH(AD$67,$G$70:$R$70,0))))))))))))))))) -> 0.6 | AE69: =IFERROR(INDEX($G$72:$R$83,MATCH($X69,$B$72:$B$83,0),MATCH(AE$67,$G$67:$R$67,0)), IFERROR(INDEX($G$72:$R$83,MATCH($X69,$B$72:$B$83,0),MATCH(AE$67,$G$68:$R$68,0)), IFERROR(INDEX($G$72:$R$83,MATCH($X69,$B$72:$B$83,0),MATCH(AE$67,$G$69:$R$69,0)), IFERROR(INDEX($G$72:$R$83,MATCH($X69,$B$72:$B$83,0),MATCH(AE$67,$G$70:$R$70,0)), IFERROR(INDEX($G$72:$R$83,MATCH($X69,$C$72:$C$83,0),MATCH(AE$67,$G$67:$R$67,0)), IFERROR(INDEX($G$72:$R$83,MATCH($X69,$C$72:$C$83,0),MATCH(AE$67,$G$68:$R$68,0)), IFERROR(INDEX($G$72:$R$83,MATCH($X69,$C$72:$C$83,0),MATCH(AE$67,$G$69:$R$69,0)), IFERROR(INDEX($G$72:$R$83,MATCH($X69,$C$72:$C$83,0),MATCH(AE$67,$G$70:$R$70,0)), IFERROR(INDEX($G$72:$R$83,MATCH($X69,$D$72:$D$83,0),MATCH(AE$67,$G$67:$R$67,0)), IFERROR(INDEX($G$72:$R$83,MATCH($X69,$D$72:$D$83,0),MATCH(AE$67,$G$68:$R$68,0)), IFERROR(INDEX($G$72:$R$83,MATCH($X69,$D$72:$D$83,0),MATCH(AE$67,$G$69:$R$69,0)), IFERROR(INDEX($G$72:$R$83,MATCH($X69,$D$72:$D$83,0),MATCH(AE$67,$G$70:$R$70,0)), IFERROR(INDEX($G$72:$R$83,MATCH($X69,$E$72:$E$83,0),MATCH(AE$67,$G$67:$R$67,0)), IFERROR(INDEX($G$72:$R$83,MATCH($X69,$E$72:$E$83,0),MATCH(AE$67,$G$68:$R$68,0)), IFERROR(INDEX($G$72:$R$83,MATCH($X69,$E$72:$E$83,0),MATCH(AE$67,$G$69:$R$69,0)), INDEX($G$72:$R$83,MATCH($X69,$E$72:$E$83,0),MATCH(AE$67,$G$70:$R$70,0))))))))))))))))) -> 0.6 | AF69: =IFERROR(INDEX($G$72:$R$83,MATCH($X69,$B$72:$B$83,0),MATCH(AF$67,$G$67:$R$67,0)), IFERROR(INDEX($G$72:$R$83,MATCH($X69,$B$72:$B$83,0),MATCH(AF$67,$G$68:$R$68,0)), IFERROR(INDEX($G$72:$R$83,MATCH($X69,$B$72:$B$83,0),MATCH(AF$67,$G$69:$R$69,0)), IFERROR(INDEX($G$72:$R$83,MATCH($X69,$B$72:$B$83,0),MATCH(AF$67,$G$70:$R$70,0)), IFERROR(INDEX($G$72:$R$83,MATCH($X69,$C$72:$C$83,0),MATCH(AF$67,$G$67:$R$67,0)), IFERROR(INDEX($G$72:$R$83,MATCH($X69,$C$72:$C$83,0),MATCH(AF$67,$G$68:$R$68,0)), IFERROR(INDEX($G$72:$R$83,MATCH($X69,$C$72:$C$83,0),MATCH(AF$67,$G$69:$R$69,0)), IFERROR(INDEX($G$72:$R$83,MATCH($X69,$C$72:$C$83,0),MATCH(AF$67,$G$70:$R$70,0)), IFERROR(INDEX($G$72:$R$83,MATCH($X69,$D$72:$D$83,0),MATCH(AF$67,$G$67:$R$67,0)), IFERROR(INDEX($G$72:$R$83,MATCH($X69,$D$72:$D$83,0),MATCH(AF$67,$G$68:$R$68,0)), IFERROR(INDEX($G$72:$R$83,MATCH($X69,$D$72:$D$83,0),MATCH(AF$67,$G$69:$R$69,0)), IFERROR(INDEX($G$72:$R$83,MATCH($X69,$D$72:$D$83,0),MATCH(AF$67,$G$70:$R$70,0)), IFERROR(INDEX($G$72:$R$83,MATCH($X69,$E$72:$E$83,0),MATCH(AF$67,$G$67:$R$67,0)), IFERROR(INDEX($G$72:$R$83,MATCH($X69,$E$72:$E$83,0),MATCH(AF$67,$G$68:$R$68,0)), IFERROR(INDEX($G$72:$R$83,MATCH($X69,$E$72:$E$83,0),MATCH(AF$67,$G$69:$R$69,0)), INDEX($G$72:$R$83,MATCH($X69,$E$72:$E$83,0),MATCH(AF$67,$G$70:$R$70,0))))))))))))))))) -> 0.6 | ... AS69: =IFERROR(INDEX($G$72:$R$83,MATCH($X69,$B$72:$B$83,0),MATCH(AS$67,$G$67:$R$67,0)), IFERROR(INDEX($G$72:$R$83,MATCH($X69,$B$72:$B$83,0),MATCH(AS$67,$G$68:$R$68,0)), IFERROR(INDEX($G$72:$R$83,MATCH($X69,$B$72:$B$83,0),MATCH(AS$67,$G$69:$R$69,0)), IFERROR(INDEX($G$72:$R$83,MATCH($X69,$B$72:$B$83,0),MATCH(AS$67,$G$70:$R$70,0)), IFERROR(INDEX($G$72:$R$83,MATCH($X69,$C$72:$C$83,0),MATCH(AS$67,$G$67:$R$67,0)), IFERROR(INDEX($G$72:$R$83,MATCH($X69,$C$72:$C$83,0),MATCH(AS$67,$G$68:$R$68,0)), IFERROR(INDEX($G$72:$R$83,MATCH($X69,$C$72:$C$83,0),MATCH(AS$67,$G$69:$R$69,0)), IFERROR(INDEX($G$72:$R$83,MATCH($X69,$C$72:$C$83,0),MATCH(AS$67,$G$70:$R$70,0)), IFERROR(INDEX($G$72:$R$83,MATCH($X69,$D$72:$D$83,0),MATCH(AS$67,$G$67:$R$67,0)), IFERROR(INDEX($G$72:$R$83,MATCH($X69,$D$72:$D$83,0),MATCH(AS$67,$G$68:$R$68,0)), IFERROR(INDEX($G$72:$R$83,MATCH($X69,$D$72:$D$83,0),MATCH(AS$67,$G$69:$R$69,0)), IFERROR(INDEX($G$72:$R$83,MATCH($X69,$D$72:$D$83,0),MATCH(AS$67,$G$70:$R$70,0)), IFERROR(INDEX($G$72:$R$83,MATCH($X69,$E$72:$E$83,0),MATCH(AS$67,$G$67:$R$67,0)), IFERROR(INDEX($G$72:$R$83,MATCH($X69,$E$72:$E$83,0),MATCH(AS$67,$G$68:$R$68,0)), IFERROR(INDEX($G$72:$R$83,MATCH($X69,$E$72:$E$83,0),MATCH(AS$67,$G$69:$R$69,0)), INDEX($G$72:$R$83,MATCH($X69,$E$72:$E$83,0),MATCH(AS$67,$G$70:$R$70,0))))))))))))))))) -> 0.19
J70: US Public Corporates IG BBB | X70: US Taxable Munis | Y70: =IFERROR(INDEX($G$72:$R$83,MATCH($X70,$B$72:$B$83,0),MATCH(Y$67,$G$67:$R$67,0)), IFERROR(INDEX($G$72:$R$83,MATCH($X70,$B$72:$B$83,0),MATCH(Y$67,$G$68:$R$68,0)), IFERROR(INDEX($G$72:$R$83,MATCH($X70,$B$72:$B$83,0),MATCH(Y$67,$G$69:$R$69,0)), IFERROR(INDEX($G$72:$R$83,MATCH($X70,$B$72:$B$83,0),MATCH(Y$67,$G$70:$R$70,0)), IFERROR(INDEX($G$72:$R$83,MATCH($X70,$C$72:$C$83,0),MATCH(Y$67,$G$67:$R$67,0)), IFERROR(INDEX($G$72:$R$83,MATCH($X70,$C$72:$C$83,0),MATCH(Y$67,$G$68:$R$68,0)), IFERROR(INDEX($G$72:$R$83,MATCH($X70,$C$72:$C$83,0),MATCH(Y$67,$G$69:$R$69,0)), IFERROR(INDEX($G$72:$R$83,MATCH($X70,$C$72:$C$83,0),MATCH(Y$67,$G$70:$R$70,0)), IFERROR(INDEX($G$72:$R$83,MATCH($X70,$D$72:$D$83,0),MATCH(Y$67,$G$67:$R$67,0)), IFERROR(INDEX($G$72:$R$83,MATCH($X70,$D$72:$D$83,0),MATCH(Y$67,$G$68:$R$68,0)), IFERROR(INDEX($G$72:$R$83,MATCH($X70,$D$72:$D$83,0),MATCH(Y$67,$G$69:$R$69,0)), IFERROR(INDEX($G$72:$R$83,MATCH($X70,$D$72:$D$83,0),MATCH(Y$67,$G$70:$R$70,0)), IFERROR(INDEX($G$72:$R$83,MATCH($X70,$E$72:$E$83,0),MATCH(Y$67,$G$67:$R$67,0)), IFERROR(INDEX($G$72:$R$83,MATCH($X70,$E$72:$E$83,0),MATCH(Y$67,$G$68:$R$68,0)), IFERROR(INDEX($G$72:$R$83,MATCH($X70,$E$72:$E$83,0),MATCH(Y$67,$G$69:$R$69,0)), INDEX($G$72:$R$83,MATCH($X70,$E$72:$E$83,0),MATCH(Y$67,$G$70:$R$70,0))))))))))))))))) -> 0.52 | Z70: =IFERROR(INDEX($G$72:$R$83,MATCH($X70,$B$72:$B$83,0),MATCH(Z$67,$G$67:$R$67,0)), IFERROR(INDEX($G$72:$R$83,MATCH($X70,$B$72:$B$83,0),MATCH(Z$67,$G$68:$R$68,0)), IFERROR(INDEX($G$72:$R$83,MATCH($X70,$B$72:$B$83,0),MATCH(Z$67,$G$69:$R$69,0)), IFERROR(INDEX($G$72:$R$83,MATCH($X70,$B$72:$B$83,0),MATCH(Z$67,$G$70:$R$70,0)), IFERROR(INDEX($G$72:$R$83,MATCH($X70,$C$72:$C$83,0),MATCH(Z$67,$G$67:$R$67,0)), IFERROR(INDEX($G$72:$R$83,MATCH($X70,$C$72:$C$83,0),MATCH(Z$67,$G$68:$R$68,0)), IFERROR(INDEX($G$72:$R$83,MATCH($X70,$C$72:$C$83,0),MATCH(Z$67,$G$69:$R$69,0)), IFERROR(INDEX($G$72:$R$83,MATCH($X70,$C$72:$C$83,0),MATCH(Z$67,$G$70:$R$70,0)), IFERROR(INDEX($G$72:$R$83,MATCH($X70,$D$72:$D$83,0),MATCH(Z$67,$G$67:$R$67,0)), IFERROR(INDEX($G$72:$R$83,MATCH($X70,$D$72:$D$83,0),MATCH(Z$67,$G$68:$R$68,0)), IFERROR(INDEX($G$72:$R$83,MATCH($X70,$D$72:$D$83,0),MATCH(Z$67,$G$69:$R$69,0)), IFERROR(INDEX($G$72:$R$83,MATCH($X70,$D$72:$D$83,0),MATCH(Z$67,$G$70:$R$70,0)), IFERROR(INDEX($G$72:$R$83,MATCH($X70,$E$72:$E$83,0),MATCH(Z$67,$G$67:$R$67,0)), IFERROR(INDEX($G$72:$R$83,MATCH($X70,$E$72:$E$83,0),MATCH(Z$67,$G$68:$R$68,0)), IFERROR(INDEX($G$72:$R$83,MATCH($X70,$E$72:$E$83,0),MATCH(Z$67,$G$69:$R$69,0)), INDEX($G$72:$R$83,MATCH($X70,$E$72:$E$83,0),MATCH(Z$67,$G$70:$R$70,0))))))))))))))))) -> 0.51 | AA70: =IFERROR(INDEX($G$72:$R$83,MATCH($X70,$B$72:$B$83,0),MATCH(AA$67,$G$67:$R$67,0)), IFERROR(INDEX($G$72:$R$83,MATCH($X70,$B$72:$B$83,0),MATCH(AA$67,$G$68:$R$68,0)), IFERROR(INDEX($G$72:$R$83,MATCH($X70,$B$72:$B$83,0),MATCH(AA$67,$G$69:$R$69,0)), IFERROR(INDEX($G$72:$R$83,MATCH($X70,$B$72:$B$83,0),MATCH(AA$67,$G$70:$R$70,0)), IFERROR(INDEX($G$72:$R$83,MATCH($X70,$C$72:$C$83,0),MATCH(AA$67,$G$67:$R$67,0)), IFERROR(INDEX($G$72:$R$83,MATCH($X70,$C$72:$C$83,0),MATCH(AA$67,$G$68:$R$68,0)), IFERROR(INDEX($G$72:$R$83,MATCH($X70,$C$72:$C$83,0),MATCH(AA$67,$G$69:$R$69,0)), IFERROR(INDEX($G$72:$R$83,MATCH($X70,$C$72:$C$83,0),MATCH(AA$67,$G$70:$R$70,0)), IFERROR(INDEX($G$72:$R$83,MATCH($X70,$D$72:$D$83,0),MATCH(AA$67,$G$67:$R$67,0)), IFERROR(INDEX($G$72:$R$83,MATCH($X70,$D$72:$D$83,0),MATCH(AA$67,$G$68:$R$68,0)), IFERROR(INDEX($G$72:$R$83,MATCH($X70,$D$72:$D$83,0),MATCH(AA$67,$G$69:$R$69,0)), IFERROR(INDEX($G$72:$R$83,MATCH($X70,$D$72:$D$83,0),MATCH(AA$67,$G$70:$R$70,0)), IFERROR(INDEX($G$72:$R$83,MATCH($X70,$E$72:$E$83,0),MATCH(AA$67,$G$67:$R$67,0)), IFERROR(INDEX($G$72:$R$83,MATCH($X70,$E$72:$E$83,0),MATCH(AA$67,$G$68:$R$68,0)), IFERROR(INDEX($G$72:$R$83,MATCH($X70,$E$72:$E$83,0),MATCH(AA$67,$G$69:$R$69,0)), INDEX($G$72:$R$83,MATCH($X70,$E$72:$E$83,0),MATCH(AA$67,$G$70:$R$70,0))))))))))))))))) -> 1 | AB70: =IFERROR(INDEX($G$72:$R$83,MATCH($X70,$B$72:$B$83,0),MATCH(AB$67,$G$67:$R$67,0)), IFERROR(INDEX($G$72:$R$83,MATCH($X70,$B$72:$B$83,0),MATCH(AB$67,$G$68:$R$68,0)), IFERROR(INDEX($G$72:$R$83,MATCH($X70,$B$72:$B$83,0),MATCH(AB$67,$G$69:$R$69,0)), IFERROR(INDEX($G$72:$R$83,MATCH($X70,$B$72:$B$83,0),MATCH(AB$67,$G$70:$R$70,0)), IFERROR(INDEX($G$72:$R$83,MATCH($X70,$C$72:$C$83,0),MATCH(AB$67,$G$67:$R$67,0)), IFERROR(INDEX($G$72:$R$83,MATCH($X70,$C$72:$C$83,0),MATCH(AB$67,$G$68:$R$68,0)), IFERROR(INDEX($G$72:$R$83,MATCH($X70,$C$72:$C$83,0),MATCH(AB$67,$G$69:$R$69,0)), IFERROR(INDEX($G$72:$R$83,MATCH($X70,$C$72:$C$83,0),MATCH(AB$67,$G$70:$R$70,0)), IFERROR(INDEX($G$72:$R$83,MATCH($X70,$D$72:$D$83,0),MATCH(AB$67,$G$67:$R$67,0)), IFERROR(INDEX($G$72:$R$83,MATCH($X70,$D$72:$D$83,0),MATCH(AB$67,$G$68:$R$68,0)), IFERROR(INDEX($G$72:$R$83,MATCH($X70,$D$72:$D$83,0),MATCH(AB$67,$G$69:$R$69,0)), IFERROR(INDEX($G$72:$R$83,MATCH($X70,$D$72:$D$83,0),MATCH(AB$67,$G$70:$R$70,0)), IFERROR(INDEX($G$72:$R$83,MATCH($X70,$E$72:$E$83,0),MATCH(AB$67,$G$67:$R$67,0)), IFERROR(INDEX($G$72:$R$83,MATCH($X70,$E$72:$E$83,0),MATCH(AB$67,$G$68:$R$68,0)), IFERROR(INDEX($G$72:$R$83,MATCH($X70,$E$72:$E$83,0),MATCH(AB$67,$G$69:$R$69,0)), INDEX($G$72:$R$83,MATCH($X70,$E$72:$E$83,0),MATCH(AB$67,$G$70:$R$70,0))))))))))))))))) -> 0.59 | AC70: =IFERROR(INDEX($G$72:$R$83,MATCH($X70,$B$72:$B$83,0),MATCH(AC$67,$G$67:$R$67,0)), IFERROR(INDEX($G$72:$R$83,MATCH($X70,$B$72:$B$83,0),MATCH(AC$67,$G$68:$R$68,0)), IFERROR(INDEX($G$72:$R$83,MATCH($X70,$B$72:$B$83,0),MATCH(AC$67,$G$69:$R$69,0)), IFERROR(INDEX($G$72:$R$83,MATCH($X70,$B$72:$B$83,0),MATCH(AC$67,$G$70:$R$70,0)), IFERROR(INDEX($G$72:$R$83,MATCH($X70,$C$72:$C$83,0),MATCH(AC$67,$G$67:$R$67,0)), IFERROR(INDEX($G$72:$R$83,MATCH($X70,$C$72:$C$83,0),MATCH(AC$67,$G$68:$R$68,0)), IFERROR(INDEX($G$72:$R$83,MATCH($X70,$C$72:$C$83,0),MATCH(AC$67,$G$69:$R$69,0)), IFERROR(INDEX($G$72:$R$83,MATCH($X70,$C$72:$C$83,0),MATCH(AC$67,$G$70:$R$70,0)), IFERROR(INDEX($G$72:$R$83,MATCH($X70,$D$72:$D$83,0),MATCH(AC$67,$G$67:$R$67,0)), IFERROR(INDEX($G$72:$R$83,MATCH($X70,$D$72:$D$83,0),MATCH(AC$67,$G$68:$R$68,0)), IFERROR(INDEX($G$72:$R$83,MATCH($X70,$D$72:$D$83,0),MATCH(AC$67,$G$69:$R$69,0)), IFERROR(INDEX($G$72:$R$83,MATCH($X70,$D$72:$D$83,0),MATCH(AC$67,$G$70:$R$70,0)), IFERROR(INDEX($G$72:$R$83,MATCH($X70,$E$72:$E$83,0),MATCH(AC$67,$G$67:$R$67,0)), IFERROR(INDEX($G$72:$R$83,MATCH($X70,$E$72:$E$83,0),MATCH(AC$67,$G$68:$R$68,0)), IFERROR(INDEX($G$72:$R$83,MATCH($X70,$E$72:$E$83,0),MATCH(AC$67,$G$69:$R$69,0)), INDEX($G$72:$R$83,MATCH($X70,$E$72:$E$83,0),MATCH(AC$67,$G$70:$R$70,0))))))))))))))))) -> 0.69 | AD70: =IFERROR(INDEX($G$72:$R$83,MATCH($X70,$B$72:$B$83,0),MATCH(AD$67,$G$67:$R$67,0)), IFERROR(INDEX($G$72:$R$83,MATCH($X70,$B$72:$B$83,0),MATCH(AD$67,$G$68:$R$68,0)), IFERROR(INDEX($G$72:$R$83,MATCH($X70,$B$72:$B$83,0),MATCH(AD$67,$G$69:$R$69,0)), IFERROR(INDEX($G$72:$R$83,MATCH($X70,$B$72:$B$83,0),MATCH(AD$67,$G$70:$R$70,0)), IFERROR(INDEX($G$72:$R$83,MATCH($X70,$C$72:$C$83,0),MATCH(AD$67,$G$67:$R$67,0)), IFERROR(INDEX($G$72:$R$83,MATCH($X70,$C$72:$C$83,0),MATCH(AD$67,$G$68:$R$68,0)), IFERROR(INDEX($G$72:$R$83,MATCH($X70,$C$72:$C$83,0),MATCH(AD$67,$G$69:$R$69,0)), IFERROR(INDEX($G$72:$R$83,MATCH($X70,$C$72:$C$83,0),MATCH(AD$67,$G$70:$R$70,0)), IFERROR(INDEX($G$72:$R$83,MATCH($X70,$D$72:$D$83,0),MATCH(AD$67,$G$67:$R$67,0)), IFERROR(INDEX($G$72:$R$83,MATCH($X70,$D$72:$D$83,0),MATCH(AD$67,$G$68:$R$68,0)), IFERROR(INDEX($G$72:$R$83,MATCH($X70,$D$72:$D$83,0),MATCH(AD$67,$G$69:$R$69,0)), IFERROR(INDEX($G$72:$R$83,MATCH($X70,$D$72:$D$83,0),MATCH(AD$67,$G$70:$R$70,0)), IFERROR(INDEX($G$72:$R$83,MATCH($X70,$E$72:$E$83,0),MATCH(AD$67,$G$67:$R$67,0)), IFERROR(INDEX($G$72:$R$83,MATCH($X70,$E$72:$E$83,0),MATCH(AD$67,$G$68:$R$68,0)), IFERROR(INDEX($G$72:$R$83,MATCH($X70,$E$72:$E$83,0),MATCH(AD$67,$G$69:$R$69,0)), INDEX($G$72:$R$83,MATCH($X70,$E$72:$E$83,0),MATCH(AD$67,$G$70:$R$70,0))))))))))))))))) -> 0.69 | AE70: =IFERROR(INDEX($G$72:$R$83,MATCH($X70,$B$72:$B$83,0),MATCH(AE$67,$G$67:$R$67,0)), IFERROR(INDEX($G$72:$R$83,MATCH($X70,$B$72:$B$83,0),MATCH(AE$67,$G$68:$R$68,0)), IFERROR(INDEX($G$72:$R$83,MATCH($X70,$B$72:$B$83,0),MATCH(AE$67,$G$69:$R$69,0)), IFERROR(INDEX($G$72:$R$83,MATCH($X70,$B$72:$B$83,0),MATCH(AE$67,$G$70:$R$70,0)), IFERROR(INDEX($G$72:$R$83,MATCH($X70,$C$72:$C$83,0),MATCH(AE$67,$G$67:$R$67,0)), IFERROR(INDEX($G$72:$R$83,MATCH($X70,$C$72:$C$83,0),MATCH(AE$67,$G$68:$R$68,0)), IFERROR(INDEX($G$72:$R$83,MATCH($X70,$C$72:$C$83,0),MATCH(AE$67,$G$69:$R$69,0)), IFERROR(INDEX($G$72:$R$83,MATCH($X70,$C$72:$C$83,0),MATCH(AE$67,$G$70:$R$70,0)), IFERROR(INDEX($G$72:$R$83,MATCH($X70,$D$72:$D$83,0),MATCH(AE$67,$G$67:$R$67,0)), IFERROR(INDEX($G$72:$R$83,MATCH($X70,$D$72:$D$83,0),MATCH(AE$67,$G$68:$R$68,0)), IFERROR(INDEX($G$72:$R$83,MATCH($X70,$D$72:$D$83,0),MATCH(AE$67,$G$69:$R$69,0)), IFERROR(INDEX($G$72:$R$83,MATCH($X70,$D$72:$D$83,0),MATCH(AE$67,$G$70:$R$70,0)), IFERROR(INDEX($G$72:$R$83,MATCH($X70,$E$72:$E$83,0),MATCH(AE$67,$G$67:$R$67,0)), IFERROR(INDEX($G$72:$R$83,MATCH($X70,$E$72:$E$83,0),MATCH(AE$67,$G$68:$R$68,0)), IFERROR(INDEX($G$72:$R$83,MATCH($X70,$E$72:$E$83,0),MATCH(AE$67,$G$69:$R$69,0)), INDEX($G$72:$R$83,MATCH($X70,$E$72:$E$83,0),MATCH(AE$67,$G$70:$R$70,0))))))))))))))))) -> 0.69 | AF70: =IFERROR(INDEX($G$72:$R$83,MATCH($X70,$B$72:$B$83,0),MATCH(AF$67,$G$67:$R$67,0)), IFERROR(INDEX($G$72:$R$83,MATCH($X70,$B$72:$B$83,0),MATCH(AF$67,$G$68:$R$68,0)), IFERROR(INDEX($G$72:$R$83,MATCH($X70,$B$72:$B$83,0),MATCH(AF$67,$G$69:$R$69,0)), IFERROR(INDEX($G$72:$R$83,MATCH($X70,$B$72:$B$83,0),MATCH(AF$67,$G$70:$R$70,0)), IFERROR(INDEX($G$72:$R$83,MATCH($X70,$C$72:$C$83,0),MATCH(AF$67,$G$67:$R$67,0)), IFERROR(INDEX($G$72:$R$83,MATCH($X70,$C$72:$C$83,0),MATCH(AF$67,$G$68:$R$68,0)), IFERROR(INDEX($G$72:$R$83,MATCH($X70,$C$72:$C$83,0),MATCH(AF$67,$G$69:$R$69,0)), IFERROR(INDEX($G$72:$R$83,MATCH($X70,$C$72:$C$83,0),MATCH(AF$67,$G$70:$R$70,0)), IFERROR(INDEX($G$72:$R$83,MATCH($X70,$D$72:$D$83,0),MATCH(AF$67,$G$67:$R$67,0)), IFERROR(INDEX($G$72:$R$83,MATCH($X70,$D$72:$D$83,0),MATCH(AF$67,$G$68:$R$68,0)), IFERROR(INDEX($G$72:$R$83,MATCH($X70,$D$72:$D$83,0),MATCH(AF$67,$G$69:$R$69,0)), IFERROR(INDEX($G$72:$R$83,MATCH($X70,$D$72:$D$83,0),MATCH(AF$67,$G$70:$R$70,0)), IFERROR(INDEX($G$72:$R$83,MATCH($X70,$E$72:$E$83,0),MATCH(AF$67,$G$67:$R$67,0)), IFERROR(INDEX($G$72:$R$83,MATCH($X70,$E$72:$E$83,0),MATCH(AF$67,$G$68:$R$68,0)), IFERROR(INDEX($G$72:$R$83,MATCH($X70,$E$72:$E$83,0),MATCH(AF$67,$G$69:$R$69,0)), INDEX($G$72:$R$83,MATCH($X70,$E$72:$E$83,0),MATCH(AF$67,$G$70:$R$70,0))))))))))))))))) -> 0.69 | ... AS70: =IFERROR(INDEX($G$72:$R$83,MATCH($X70,$B$72:$B$83,0),MATCH(AS$67,$G$67:$R$67,0)), IFERROR(INDEX($G$72:$R$83,MATCH($X70,$B$72:$B$83,0),MATCH(AS$67,$G$68:$R$68,0)), IFERROR(INDEX($G$72:$R$83,MATCH($X70,$B$72:$B$83,0),MATCH(AS$67,$G$69:$R$69,0)), IFERROR(INDEX($G$72:$R$83,MATCH($X70,$B$72:$B$83,0),MATCH(AS$67,$G$70:$R$70,0)), IFERROR(INDEX($G$72:$R$83,MATCH($X70,$C$72:$C$83,0),MATCH(AS$67,$G$67:$R$67,0)), IFERROR(INDEX($G$72:$R$83,MATCH($X70,$C$72:$C$83,0),MATCH(AS$67,$G$68:$R$68,0)), IFERROR(INDEX($G$72:$R$83,MATCH($X70,$C$72:$C$83,0),MATCH(AS$67,$G$69:$R$69,0)), IFERROR(INDEX($G$72:$R$83,MATCH($X70,$C$72:$C$83,0),MATCH(AS$67,$G$70:$R$70,0)), IFERROR(INDEX($G$72:$R$83,MATCH($X70,$D$72:$D$83,0),MATCH(AS$67,$G$67:$R$67,0)), IFERROR(INDEX($G$72:$R$83,MATCH($X70,$D$72:$D$83,0),MATCH(AS$67,$G$68:$R$68,0)), IFERROR(INDEX($G$72:$R$83,MATCH($X70,$D$72:$D$83,0),MATCH(AS$67,$G$69:$R$69,0)), IFERROR(INDEX($G$72:$R$83,MATCH($X70,$D$72:$D$83,0),MATCH(AS$67,$G$70:$R$70,0)), IFERROR(INDEX($G$72:$R$83,MATCH($X70,$E$72:$E$83,0),MATCH(AS$67,$G$67:$R$67,0)), IFERROR(INDEX($G$72:$R$83,MATCH($X70,$E$72:$E$83,0),MATCH(AS$67,$G$68:$R$68,0)), IFERROR(INDEX($G$72:$R$83,MATCH($X70,$E$72:$E$83,0),MATCH(AS$67,$G$69:$R$69,0)), INDEX($G$72:$R$83,MATCH($X70,$E$72:$E$83,0),MATCH(AS$67,$G$70:$R$70,0))))))))))))))))) -> 0.2
G71: U.S. Intermediate Treasuries | H71: U.S. Long Treasuries | I71: U.S. Securitized | J71: U.S. Inv Grade Corporate Bonds | K71: U.S. High Yield Bonds | L71: U.S. Leveraged Loans | M71: World ex-U.S. Government Bonds hedged | N71: U.S. Muni 1-15 Yr Blend | O71: U.S. Core Real Estate | P71: Commercial Mortgage Loans | Q71: Private Equity | R71: Direct Lending | X71: Global ex-US Government, hedged | Y71: =IFERROR(INDEX($G$72:$R$83,MATCH($X71,$B$72:$B$83,0),MATCH(Y$67,$G$67:$R$67,0)), IFERROR(INDEX($G$72:$R$83,MATCH($X71,$B$72:$B$83,0),MATCH(Y$67,$G$68:$R$68,0)), IFERROR(INDEX($G$72:$R$83,MATCH($X71,$B$72:$B$83,0),MATCH(Y$67,$G$69:$R$69,0)), IFERROR(INDEX($G$72:$R$83,MATCH($X71,$B$72:$B$83,0),MATCH(Y$67,$G$70:$R$70,0)), IFERROR(INDEX($G$72:$R$83,MATCH($X71,$C$72:$C$83,0),MATCH(Y$67,$G$67:$R$67,0)), IFERROR(INDEX($G$72:$R$83,MATCH($X71,$C$72:$C$83,0),MATCH(Y$67,$G$68:$R$68,0)), IFERROR(INDEX($G$72:$R$83,MATCH($X71,$C$72:$C$83,0),MATCH(Y$67,$G$69:$R$69,0)), IFERROR(INDEX($G$72:$R$83,MATCH($X71,$C$72:$C$83,0),MATCH(Y$67,$G$70:$R$70,0)), IFERROR(INDEX($G$72:$R$83,MATCH($X71,$D$72:$D$83,0),MATCH(Y$67,$G$67:$R$67,0)), IFERROR(INDEX($G$72:$R$83,MATCH($X71,$D$72:$D$83,0),MATCH(Y$67,$G$68:$R$68,0)), IFERROR(INDEX($G$72:$R$83,MATCH($X71,$D$72:$D$83,0),MATCH(Y$67,$G$69:$R$69,0)), IFERROR(INDEX($G$72:$R$83,MATCH($X71,$D$72:$D$83,0),MATCH(Y$67,$G$70:$R$70,0)), IFERROR(INDEX($G$72:$R$83,MATCH($X71,$E$72:$E$83,0),MATCH(Y$67,$G$67:$R$67,0)), IFERROR(INDEX($G$72:$R$83,MATCH($X71,$E$72:$E$83,0),MATCH(Y$67,$G$68:$R$68,0)), IFERROR(INDEX($G$72:$R$83,MATCH($X71,$E$72:$E$83,0),MATCH(Y$67,$G$69:$R$69,0)), INDEX($G$72:$R$83,MATCH($X71,$E$72:$E$83,0),MATCH(Y$67,$G$70:$R$70,0))))))))))))))))) -> 0.72 | Z71: =IFERROR(INDEX($G$72:$R$83,MATCH($X71,$B$72:$B$83,0),MATCH(Z$67,$G$67:$R$67,0)), IFERROR(INDEX($G$72:$R$83,MATCH($X71,$B$72:$B$83,0),MATCH(Z$67,$G$68:$R$68,0)), IFERROR(INDEX($G$72:$R$83,MATCH($X71,$B$72:$B$83,0),MATCH(Z$67,$G$69:$R$69,0)), IFERROR(INDEX($G$72:$R$83,MATCH($X71,$B$72:$B$83,0),MATCH(Z$67,$G$70:$R$70,0)), IFERROR(INDEX($G$72:$R$83,MATCH($X71,$C$72:$C$83,0),MATCH(Z$67,$G$67:$R$67,0)), IFERROR(INDEX($G$72:$R$83,MATCH($X71,$C$72:$C$83,0),MATCH(Z$67,$G$68:$R$68,0)), IFERROR(INDEX($G$72:$R$83,MATCH($X71,$C$72:$C$83,0),MATCH(Z$67,$G$69:$R$69,0)), IFERROR(INDEX($G$72:$R$83,MATCH($X71,$C$72:$C$83,0),MATCH(Z$67,$G$70:$R$70,0)), IFERROR(INDEX($G$72:$R$83,MATCH($X71,$D$72:$D$83,0),MATCH(Z$67,$G$67:$R$67,0)), IFERROR(INDEX($G$72:$R$83,MATCH($X71,$D$72:$D$83,0),MATCH(Z$67,$G$68:$R$68,0)), IFERROR(INDEX($G$72:$R$83,MATCH($X71,$D$72:$D$83,0),MATCH(Z$67,$G$69:$R$69,0)), IFERROR(INDEX($G$72:$R$83,MATCH($X71,$D$72:$D$83,0),MATCH(Z$67,$G$70:$R$70,0)), IFERROR(INDEX($G$72:$R$83,MATCH($X71,$E$72:$E$83,0),MATCH(Z$67,$G$67:$R$67,0)), IFERROR(INDEX($G$72:$R$83,MATCH($X71,$E$72:$E$83,0),MATCH(Z$67,$G$68:$R$68,0)), IFERROR(INDEX($G$72:$R$83,MATCH($X71,$E$72:$E$83,0),MATCH(Z$67,$G$69:$R$69,0)), INDEX($G$72:$R$83,MATCH($X71,$E$72:$E$83,0),MATCH(Z$67,$G$70:$R$70,0))))))))))))))))) -> 0.74 | AA71: =IFERROR(INDEX($G$72:$R$83,MATCH($X71,$B$72:$B$83,0),MATCH(AA$67,$G$67:$R$67,0)), IFERROR(INDEX($G$72:$R$83,MATCH($X71,$B$72:$B$83,0),MATCH(AA$67,$G$68:$R$68,0)), IFERROR(INDEX($G$72:$R$83,MATCH($X71,$B$72:$B$83,0),MATCH(AA$67,$G$69:$R$69,0)), IFERROR(INDEX($G$72:$R$83,MATCH($X71,$B$72:$B$83,0),MATCH(AA$67,$G$70:$R$70,0)), IFERROR(INDEX($G$72:$R$83,MATCH($X71,$C$72:$C$83,0),MATCH(AA$67,$G$67:$R$67,0)), IFERROR(INDEX($G$72:$R$83,MATCH($X71,$C$72:$C$83,0),MATCH(AA$67,$G$68:$R$68,0)), IFERROR(INDEX($G$72:$R$83,MATCH($X71,$C$72:$C$83,0),MATCH(AA$67,$G$69:$R$69,0)), IFERROR(INDEX($G$72:$R$83,MATCH($X71,$C$72:$C$83,0),MATCH(AA$67,$G$70:$R$70,0)), IFERROR(INDEX($G$72:$R$83,MATCH($X71,$D$72:$D$83,0),MATCH(AA$67,$G$67:$R$67,0)), IFERROR(INDEX($G$72:$R$83,MATCH($X71,$D$72:$D$83,0),MATCH(AA$67,$G$68:$R$68,0)), IFERROR(INDEX($G$72:$R$83,MATCH($X71,$D$72:$D$83,0),MATCH(AA$67,$G$69:$R$69,0)), IFERROR(INDEX($G$72:$R$83,MATCH($X71,$D$72:$D$83,0),MATCH(AA$67,$G$70:$R$70,0)), IFERROR(INDEX($G$72:$R$83,MATCH($X71,$E$72:$E$83,0),MATCH(AA$67,$G$67:$R$67,0)), IFERROR(INDEX($G$72:$R$83,MATCH($X71,$E$72:$E$83,0),MATCH(AA$67,$G$68:$R$68,0)), IFERROR(INDEX($G$72:$R$83,MATCH($X71,$E$72:$E$83,0),MATCH(AA$67,$G$69:$R$69,0)), INDEX($G$72:$R$83,MATCH($X71,$E$72:$E$83,0),MATCH(AA$67,$G$70:$R$70,0))))))))))))))))) -> 0.59 | AB71: =IFERROR(INDEX($G$72:$R$83,MATCH($X71,$B$72:$B$83,0),MATCH(AB$67,$G$67:$R$67,0)), IFERROR(INDEX($G$72:$R$83,MATCH($X71,$B$72:$B$83,0),MATCH(AB$67,$G$68:$R$68,0)), IFERROR(INDEX($G$72:$R$83,MATCH($X71,$B$72:$B$83,0),MATCH(AB$67,$G$69:$R$69,0)), IFERROR(INDEX($G$72:$R$83,MATCH($X71,$B$72:$B$83,0),MATCH(AB$67,$G$70:$R$70,0)), IFERROR(INDEX($G$72:$R$83,MATCH($X71,$C$72:$C$83,0),MATCH(AB$67,$G$67:$R$67,0)), IFERROR(INDEX($G$72:$R$83,MATCH($X71,$C$72:$C$83,0),MATCH(AB$67,$G$68:$R$68,0)), IFERROR(INDEX($G$72:$R$83,MATCH($X71,$C$72:$C$83,0),MATCH(AB$67,$G$69:$R$69,0)), IFERROR(INDEX($G$72:$R$83,MATCH($X71,$C$72:$C$83,0),MATCH(AB$67,$G$70:$R$70,0)), IFERROR(INDEX($G$72:$R$83,MATCH($X71,$D$72:$D$83,0),MATCH(AB$67,$G$67:$R$67,0)), IFERROR(INDEX($G$72:$R$83,MATCH($X71,$D$72:$D$83,0),MATCH(AB$67,$G$68:$R$68,0)), IFERROR(INDEX($G$72:$R$83,MATCH($X71,$D$72:$D$83,0),MATCH(AB$67,$G$69:$R$69,0)), IFERROR(INDEX($G$72:$R$83,MATCH($X71,$D$72:$D$83,0),MATCH(AB$67,$G$70:$R$70,0)), IFERROR(INDEX($G$72:$R$83,MATCH($X71,$E$72:$E$83,0),MATCH(AB$67,$G$67:$R$67,0)), IFERROR(INDEX($G$72:$R$83,MATCH($X71,$E$72:$E$83,0),MATCH(AB$67,$G$68:$R$68,0)), IFERROR(INDEX($G$72:$R$83,MATCH($X71,$E$72:$E$83,0),MATCH(AB$67,$G$69:$R$69,0)), INDEX($G$72:$R$83,MATCH($X71,$E$72:$E$83,0),MATCH(AB$67,$G$70:$R$70,0))))))))))))))))) -> 1 | AC71: =IFERROR(INDEX($G$72:$R$83,MATCH($X71,$B$72:$B$83,0),MATCH(AC$67,$G$67:$R$67,0)), IFERROR(INDEX($G$72:$R$83,MATCH($X71,$B$72:$B$83,0),MATCH(AC$67,$G$68:$R$68,0)), IFERROR(INDEX($G$72:$R$83,MATCH($X71,$B$72:$B$83,0),MATCH(AC$67,$G$69:$R$69,0)), IFERROR(INDEX($G$72:$R$83,MATCH($X71,$B$72:$B$83,0),MATCH(AC$67,$G$70:$R$70,0)), IFERROR(INDEX($G$72:$R$83,MATCH($X71,$C$72:$C$83,0),MATCH(AC$67,$G$67:$R$67,0)), IFERROR(INDEX($G$72:$R$83,MATCH($X71,$C$72:$C$83,0),MATCH(AC$67,$G$68:$R$68,0)), IFERROR(INDEX($G$72:$R$83,MATCH($X71,$C$72:$C$83,0),MATCH(AC$67,$G$69:$R$69,0)), IFERROR(INDEX($G$72:$R$83,MATCH($X71,$C$72:$C$83,0),MATCH(AC$67,$G$70:$R$70,0)), IFERROR(INDEX($G$72:$R$83,MATCH($X71,$D$72:$D$83,0),MATCH(AC$67,$G$67:$R$67,0)), IFERROR(INDEX($G$72:$R$83,MATCH($X71,$D$72:$D$83,0),MATCH(AC$67,$G$68:$R$68,0)), IFERROR(INDEX($G$72:$R$83,MATCH($X71,$D$72:$D$83,0),MATCH(AC$67,$G$69:$R$69,0)), IFERROR(INDEX($G$72:$R$83,MATCH($X71,$D$72:$D$83,0),MATCH(AC$67,$G$70:$R$70,0)), IFERROR(INDEX($G$72:$R$83,MATCH($X71,$E$72:$E$83,0),MATCH(AC$67,$G$67:$R$67,0)), IFERROR(INDEX($G$72:$R$83,MATCH($X71,$E$72:$E$83,0),MATCH(AC$67,$G$68:$R$68,0)), IFERROR(INDEX($G$72:$R$83,MATCH($X71,$E$72:$E$83,0),MATCH(AC$67,$G$69:$R$69,0)), INDEX($G$72:$R$83,MATCH($X71,$E$72:$E$83,0),MATCH(AC$67,$G$70:$R$70,0))))))))))))))))) -> 0.64 | AD71: =IFERROR(INDEX($G$72:$R$83,MATCH($X71,$B$72:$B$83,0),MATCH(AD$67,$G$67:$R$67,0)), IFERROR(INDEX($G$72:$R$83,MATCH($X71,$B$72:$B$83,0),MATCH(AD$67,$G$68:$R$68,0)), IFERROR(INDEX($G$72:$R$83,MATCH($X71,$B$72:$B$83,0),MATCH(AD$67,$G$69:$R$69,0)), IFERROR(INDEX($G$72:$R$83,MATCH($X71,$B$72:$B$83,0),MATCH(AD$67,$G$70:$R$70,0)), IFERROR(INDEX($G$72:$R$83,MATCH($X71,$C$72:$C$83,0),MATCH(AD$67,$G$67:$R$67,0)), IFERROR(INDEX($G$72:$R$83,MATCH($X71,$C$72:$C$83,0),MATCH(AD$67,$G$68:$R$68,0)), IFERROR(INDEX($G$72:$R$83,MATCH($X71,$C$72:$C$83,0),MATCH(AD$67,$G$69:$R$69,0)), IFERROR(INDEX($G$72:$R$83,MATCH($X71,$C$72:$C$83,0),MATCH(AD$67,$G$70:$R$70,0)), IFERROR(INDEX($G$72:$R$83,MATCH($X71,$D$72:$D$83,0),MATCH(AD$67,$G$67:$R$67,0)), IFERROR(INDEX($G$72:$R$83,MATCH($X71,$D$72:$D$83,0),MATCH(AD$67,$G$68:$R$68,0)), IFERROR(INDEX($G$72:$R$83,MATCH($X71,$D$72:$D$83,0),MATCH(AD$67,$G$69:$R$69,0)), IFERROR(INDEX($G$72:$R$83,MATCH($X71,$D$72:$D$83,0),MATCH(AD$67,$G$70:$R$70,0)), IFERROR(INDEX($G$72:$R$83,MATCH($X71,$E$72:$E$83,0),MATCH(AD$67,$G$67:$R$67,0)), IFERROR(INDEX($G$72:$R$83,MATCH($X71,$E$72:$E$83,0),MATCH(AD$67,$G$68:$R$68,0)), IFERROR(INDEX($G$72:$R$83,MATCH($X71,$E$72:$E$83,0),MATCH(AD$67,$G$69:$R$69,0)), INDEX($G$72:$R$83,MATCH($X71,$E$72:$E$83,0),MATCH(AD$67,$G$70:$R$70,0))))))))))))))))) -> 0.64 | AE71: =IFERROR(INDEX($G$72:$R$83,MATCH($X71,$B$72:$B$83,0),MATCH(AE$67,$G$67:$R$67,0)), IFERROR(INDEX($G$72:$R$83,MATCH($X71,$B$72:$B$83,0),MATCH(AE$67,$G$68:$R$68,0)), IFERROR(INDEX($G$72:$R$83,MATCH($X71,$B$72:$B$83,0),MATCH(AE$67,$G$69:$R$69,0)), IFERROR(INDEX($G$72:$R$83,MATCH($X71,$B$72:$B$83,0),MATCH(AE$67,$G$70:$R$70,0)), IFERROR(INDEX($G$72:$R$83,MATCH($X71,$C$72:$C$83,0),MATCH(AE$67,$G$67:$R$67,0)), IFERROR(INDEX($G$72:$R$83,MATCH($X71,$C$72:$C$83,0),MATCH(AE$67,$G$68:$R$68,0)), IFERROR(INDEX($G$72:$R$83,MATCH($X71,$C$72:$C$83,0),MATCH(AE$67,$G$69:$R$69,0)), IFERROR(INDEX($G$72:$R$83,MATCH($X71,$C$72:$C$83,0),MATCH(AE$67,$G$70:$R$70,0)), IFERROR(INDEX($G$72:$R$83,MATCH($X71,$D$72:$D$83,0),MATCH(AE$67,$G$67:$R$67,0)), IFERROR(INDEX($G$72:$R$83,MATCH($X71,$D$72:$D$83,0),MATCH(AE$67,$G$68:$R$68,0)), IFERROR(INDEX($G$72:$R$83,MATCH($X71,$D$72:$D$83,0),MATCH(AE$67,$G$69:$R$69,0)), IFERROR(INDEX($G$72:$R$83,MATCH($X71,$D$72:$D$83,0),MATCH(AE$67,$G$70:$R$70,0)), IFERROR(INDEX($G$72:$R$83,MATCH($X71,$E$72:$E$83,0),MATCH(AE$67,$G$67:$R$67,0)), IFERROR(INDEX($G$72:$R$83,MATCH($X71,$E$72:$E$83,0),MATCH(AE$67,$G$68:$R$68,0)), IFERROR(INDEX($G$72:$R$83,MATCH($X71,$E$72:$E$83,0),MATCH(AE$67,$G$69:$R$69,0)), INDEX($G$72:$R$83,MATCH($X71,$E$72:$E$83,0),MATCH(AE$67,$G$70:$R$70,0))))))))))))))))) -> 0.64 | AF71: =IFERROR(INDEX($G$72:$R$83,MATCH($X71,$B$72:$B$83,0),MATCH(AF$67,$G$67:$R$67,0)), IFERROR(INDEX($G$72:$R$83,MATCH($X71,$B$72:$B$83,0),MATCH(AF$67,$G$68:$R$68,0)), IFERROR(INDEX($G$72:$R$83,MATCH($X71,$B$72:$B$83,0),MATCH(AF$67,$G$69:$R$69,0)), IFERROR(INDEX($G$72:$R$83,MATCH($X71,$B$72:$B$83,0),MATCH(AF$67,$G$70:$R$70,0)), IFERROR(INDEX($G$72:$R$83,MATCH($X71,$C$72:$C$83,0),MATCH(AF$67,$G$67:$R$67,0)), IFERROR(INDEX($G$72:$R$83,MATCH($X71,$C$72:$C$83,0),MATCH(AF$67,$G$68:$R$68,0)), IFERROR(INDEX($G$72:$R$83,MATCH($X71,$C$72:$C$83,0),MATCH(AF$67,$G$69:$R$69,0)), IFERROR(INDEX($G$72:$R$83,MATCH($X71,$C$72:$C$83,0),MATCH(AF$67,$G$70:$R$70,0)), IFERROR(INDEX($G$72:$R$83,MATCH($X71,$D$72:$D$83,0),MATCH(AF$67,$G$67:$R$67,0)), IFERROR(INDEX($G$72:$R$83,MATCH($X71,$D$72:$D$83,0),MATCH(AF$67,$G$68:$R$68,0)), IFERROR(INDEX($G$72:$R$83,MATCH($X71,$D$72:$D$83,0),MATCH(AF$67,$G$69:$R$69,0)), IFERROR(INDEX($G$72:$R$83,MATCH($X71,$D$72:$D$83,0),MATCH(AF$67,$G$70:$R$70,0)), IFERROR(INDEX($G$72:$R$83,MATCH($X71,$E$72:$E$83,0),MATCH(AF$67,$G$67:$R$67,0)), IFERROR(INDEX($G$72:$R$83,MATCH($X71,$E$72:$E$83,0),MATCH(AF$67,$G$68:$R$68,0)), IFERROR(INDEX($G$72:$R$83,MATCH($X71,$E$72:$E$83,0),MATCH(AF$67,$G$69:$R$69,0)), INDEX($G$72:$R$83,MATCH($X71,$E$72:$E$83,0),MATCH(AF$67,$G$70:$R$70,0))))))))))))))))) -> 0.64 | ... AS71: =IFERROR(INDEX($G$72:$R$83,MATCH($X71,$B$72:$B$83,0),MATCH(AS$67,$G$67:$R$67,0)), IFERROR(INDEX($G$72:$R$83,MATCH($X71,$B$72:$B$83,0),MATCH(AS$67,$G$68:$R$68,0)), IFERROR(INDEX($G$72:$R$83,MATCH($X71,$B$72:$B$83,0),MATCH(AS$67,$G$69:$R$69,0)), IFERROR(INDEX($G$72:$R$83,MATCH($X71,$B$72:$B$83,0),MATCH(AS$67,$G$70:$R$70,0)), IFERROR(INDEX($G$72:$R$83,MATCH($X71,$C$72:$C$83,0),MATCH(AS$67,$G$67:$R$67,0)), IFERROR(INDEX($G$72:$R$83,MATCH($X71,$C$72:$C$83,0),MATCH(AS$67,$G$68:$R$68,0)), IFERROR(INDEX($G$72:$R$83,MATCH($X71,$C$72:$C$83,0),MATCH(AS$67,$G$69:$R$69,0)), IFERROR(INDEX($G$72:$R$83,MATCH($X71,$C$72:$C$83,0),MATCH(AS$67,$G$70:$R$70,0)), IFERROR(INDEX($G$72:$R$83,MATCH($X71,$D$72:$D$83,0),MATCH(AS$67,$G$67:$R$67,0)), IFERROR(INDEX($G$72:$R$83,MATCH($X71,$D$72:$D$83,0),MATCH(AS$67,$G$68:$R$68,0)), IFERROR(INDEX($G$72:$R$83,MATCH($X71,$D$72:$D$83,0),MATCH(AS$67,$G$69:$R$69,0)), IFERROR(INDEX($G$72:$R$83,MATCH($X71,$D$72:$D$83,0),MATCH(AS$67,$G$70:$R$70,0)), IFERROR(INDEX($G$72:$R$83,MATCH($X71,$E$72:$E$83,0),MATCH(AS$67,$G$67:$R$67,0)), IFERROR(INDEX($G$72:$R$83,MATCH($X71,$E$72:$E$83,0),MATCH(AS$67,$G$68:$R$68,0)), IFERROR(INDEX($G$72:$R$83,MATCH($X71,$E$72:$E$83,0),MATCH(AS$67,$G$69:$R$69,0)), INDEX($G$72:$R$83,MATCH($X71,$E$72:$E$83,0),MATCH(AS$67,$G$70:$R$70,0))))))))))))))))) -> -0.16
B72: US Treasuries, Short/Intermediate | F72: U.S. Intermediate Treasuries | G72: 1 | H72: 0.83 | I72: 0.78 | J72: 0.52 | K72: -0.02 | L72: -0.37 | M72: 0.72 | N72: 0.52 | O72: -0.27 | P72: 0.24 | Q72: -0.33 | R72: -0.29 | X72: US Public Corporates IG AAA | Y72: =IFERROR(INDEX($G$72:$R$83,MATCH($X72,$B$72:$B$83,0),MATCH(Y$67,$G$67:$R$67,0)), IFERROR(INDEX($G$72:$R$83,MATCH($X72,$B$72:$B$83,0),MATCH(Y$67,$G$68:$R$68,0)), IFERROR(INDEX($G$72:$R$83,MATCH($X72,$B$72:$B$83,0),MATCH(Y$67,$G$69:$R$69,0)), IFERROR(INDEX($G$72:$R$83,MATCH($X72,$B$72:$B$83,0),MATCH(Y$67,$G$70:$R$70,0)), IFERROR(INDEX($G$72:$R$83,MATCH($X72,$C$72:$C$83,0),MATCH(Y$67,$G$67:$R$67,0)), IFERROR(INDEX($G$72:$R$83,MATCH($X72,$C$72:$C$83,0),MATCH(Y$67,$G$68:$R$68,0)), IFERROR(INDEX($G$72:$R$83,MATCH($X72,$C$72:$C$83,0),MATCH(Y$67,$G$69:$R$69,0)), IFERROR(INDEX($G$72:$R$83,MATCH($X72,$C$72:$C$83,0),MATCH(Y$67,$G$70:$R$70,0)), IFERROR(INDEX($G$72:$R$83,MATCH($X72,$D$72:$D$83,0),MATCH(Y$67,$G$67:$R$67,0)), IFERROR(INDEX($G$72:$R$83,MATCH($X72,$D$72:$D$83,0),MATCH(Y$67,$G$68:$R$68,0)), IFERROR(INDEX($G$72:$R$83,MATCH($X72,$D$72:$D$83,0),MATCH(Y$67,$G$69:$R$69,0)), IFERROR(INDEX($G$72:$R$83,MATCH($X72,$D$72:$D$83,0),MATCH(Y$67,$G$70:$R$70,0)), IFERROR(INDEX($G$72:$R$83,MATCH($X72,$E$72:$E$83,0),MATCH(Y$67,$G$67:$R$67,0)), IFERROR(INDEX($G$72:$R$83,MATCH($X72,$E$72:$E$83,0),MATCH(Y$67,$G$68:$R$68,0)), IFERROR(INDEX($G$72:$R$83,MATCH($X72,$E$72:$E$83,0),MATCH(Y$67,$G$69:$R$69,0)), INDEX($G$72:$R$83,MATCH($X72,$E$72:$E$83,0),MATCH(Y$67,$G$70:$R$70,0))))))))))))))))) -> 0.52 | Z72: =IFERROR(INDEX($G$72:$R$83,MATCH($X72,$B$72:$B$83,0),MATCH(Z$67,$G$67:$R$67,0)), IFERROR(INDEX($G$72:$R$83,MATCH($X72,$B$72:$B$83,0),MATCH(Z$67,$G$68:$R$68,0)), IFERROR(INDEX($G$72:$R$83,MATCH($X72,$B$72:$B$83,0),MATCH(Z$67,$G$69:$R$69,0)), IFERROR(INDEX($G$72:$R$83,MATCH($X72,$B$72:$B$83,0),MATCH(Z$67,$G$70:$R$70,0)), IFERROR(INDEX($G$72:$R$83,MATCH($X72,$C$72:$C$83,0),MATCH(Z$67,$G$67:$R$67,0)), IFERROR(INDEX($G$72:$R$83,MATCH($X72,$C$72:$C$83,0),MATCH(Z$67,$G$68:$R$68,0)), IFERROR(INDEX($G$72:$R$83,MATCH($X72,$C$72:$C$83,0),MATCH(Z$67,$G$69:$R$69,0)), IFERROR(INDEX($G$72:$R$83,MATCH($X72,$C$72:$C$83,0),MATCH(Z$67,$G$70:$R$70,0)), IFERROR(INDEX($G$72:$R$83,MATCH($X72,$D$72:$D$83,0),MATCH(Z$67,$G$67:$R$67,0)), IFERROR(INDEX($G$72:$R$83,MATCH($X72,$D$72:$D$83,0),MATCH(Z$67,$G$68:$R$68,0)), IFERROR(INDEX($G$72:$R$83,MATCH($X72,$D$72:$D$83,0),MATCH(Z$67,$G$69:$R$69,0)), IFERROR(INDEX($G$72:$R$83,MATCH($X72,$D$72:$D$83,0),MATCH(Z$67,$G$70:$R$70,0)), IFERROR(INDEX($G$72:$R$83,MATCH($X72,$E$72:$E$83,0),MATCH(Z$67,$G$67:$R$67,0)), IFERROR(INDEX($G$72:$R$83,MATCH($X72,$E$72:$E$83,0),MATCH(Z$67,$G$68:$R$68,0)), IFERROR(INDEX($G$72:$R$83,MATCH($X72,$E$72:$E$83,0),MATCH(Z$67,$G$69:$R$69,0)), INDEX($G$72:$R$83,MATCH($X72,$E$72:$E$83,0),MATCH(Z$67,$G$70:$R$70,0))))))))))))))))) -> 0.6 | AA72: =IFERROR(INDEX($G$72:$R$83,MATCH($X72,$B$72:$B$83,0),MATCH(AA$67,$G$67:$R$67,0)), IFERROR(INDEX($G$72:$R$83,MATCH($X72,$B$72:$B$83,0),MATCH(AA$67,$G$68:$R$68,0)), IFERROR(INDEX($G$72:$R$83,MATCH($X72,$B$72:$B$83,0),MATCH(AA$67,$G$69:$R$69,0)), IFERROR(INDEX($G$72:$R$83,MATCH($X72,$B$72:$B$83,0),MATCH(AA$67,$G$70:$R$70,0)), IFERROR(INDEX($G$72:$R$83,MATCH($X72,$C$72:$C$83,0),MATCH(AA$67,$G$67:$R$67,0)), IFERROR(INDEX($G$72:$R$83,MATCH($X72,$C$72:$C$83,0),MATCH(AA$67,$G$68:$R$68,0)), IFERROR(INDEX($G$72:$R$83,MATCH($X72,$C$72:$C$83,0),MATCH(AA$67,$G$69:$R$69,0)), IFERROR(INDEX($G$72:$R$83,MATCH($X72,$C$72:$C$83,0),MATCH(AA$67,$G$70:$R$70,0)), IFERROR(INDEX($G$72:$R$83,MATCH($X72,$D$72:$D$83,0),MATCH(AA$67,$G$67:$R$67,0)), IFERROR(INDEX($G$72:$R$83,MATCH($X72,$D$72:$D$83,0),MATCH(AA$67,$G$68:$R$68,0)), IFERROR(INDEX($G$72:$R$83,MATCH($X72,$D$72:$D$83,0),MATCH(AA$67,$G$69:$R$69,0)), IFERROR(INDEX($G$72:$R$83,MATCH($X72,$D$72:$D$83,0),MATCH(AA$67,$G$70:$R$70,0)), IFERROR(INDEX($G$72:$R$83,MATCH($X72,$E$72:$E$83,0),MATCH(AA$67,$G$67:$R$67,0)), IFERROR(INDEX($G$72:$R$83,MATCH($X72,$E$72:$E$83,0),MATCH(AA$67,$G$68:$R$68,0)), IFERROR(INDEX($G$72:$R$83,MATCH($X72,$E$72:$E$83,0),MATCH(AA$67,$G$69:$R$69,0)), INDEX($G$72:$R$83,MATCH($X72,$E$72:$E$83,0),MATCH(AA$67,$G$70:$R$70,0))))))))))))))))) -> 0.69 | AB72: =IFERROR(INDEX($G$72:$R$83,MATCH($X72,$B$72:$B$83,0),MATCH(AB$67,$G$67:$R$67,0)), IFERROR(INDEX($G$72:$R$83,MATCH($X72,$B$72:$B$83,0),MATCH(AB$67,$G$68:$R$68,0)), IFERROR(INDEX($G$72:$R$83,MATCH($X72,$B$72:$B$83,0),MATCH(AB$67,$G$69:$R$69,0)), IFERROR(INDEX($G$72:$R$83,MATCH($X72,$B$72:$B$83,0),MATCH(AB$67,$G$70:$R$70,0)), IFERROR(INDEX($G$72:$R$83,MATCH($X72,$C$72:$C$83,0),MATCH(AB$67,$G$67:$R$67,0)), IFERROR(INDEX($G$72:$R$83,MATCH($X72,$C$72:$C$83,0),MATCH(AB$67,$G$68:$R$68,0)), IFERROR(INDEX($G$72:$R$83,MATCH($X72,$C$72:$C$83,0),MATCH(AB$67,$G$69:$R$69,0)), IFERROR(INDEX($G$72:$R$83,MATCH($X72,$C$72:$C$83,0),MATCH(AB$67,$G$70:$R$70,0)), IFERROR(INDEX($G$72:$R$83,MATCH($X72,$D$72:$D$83,0),MATCH(AB$67,$G$67:$R$67,0)), IFERROR(INDEX($G$72:$R$83,MATCH($X72,$D$72:$D$83,0),MATCH(AB$67,$G$68:$R$68,0)), IFERROR(INDEX($G$72:$R$83,MATCH($X72,$D$72:$D$83,0),MATCH(AB$67,$G$69:$R$69,0)), IFERROR(INDEX($G$72:$R$83,MATCH($X72,$D$72:$D$83,0),MATCH(AB$67,$G$70:$R$70,0)), IFERROR(INDEX($G$72:$R$83,MATCH($X72,$E$72:$E$83,0),MATCH(AB$67,$G$67:$R$67,0)), IFERROR(INDEX($G$72:$R$83,MATCH($X72,$E$72:$E$83,0),MATCH(AB$67,$G$68:$R$68,0)), IFERROR(INDEX($G$72:$R$83,MATCH($X72,$E$72:$E$83,0),MATCH(AB$67,$G$69:$R$69,0)), INDEX($G$72:$R$83,MATCH($X72,$E$72:$E$83,0),MATCH(AB$67,$G$70:$R$70,0))))))))))))))))) -> 0.64 | AC72: =IFERROR(INDEX($G$72:$R$83,MATCH($X72,$B$72:$B$83,0),MATCH(AC$67,$G$67:$R$67,0)), IFERROR(INDEX($G$72:$R$83,MATCH($X72,$B$72:$B$83,0),MATCH(AC$67,$G$68:$R$68,0)), IFERROR(INDEX($G$72:$R$83,MATCH($X72,$B$72:$B$83,0),MATCH(AC$67,$G$69:$R$69,0)), IFERROR(INDEX($G$72:$R$83,MATCH($X72,$B$72:$B$83,0),MATCH(AC$67,$G$70:$R$70,0)), IFERROR(INDEX($G$72:$R$83,MATCH($X72,$C$72:$C$83,0),MATCH(AC$67,$G$67:$R$67,0)), IFERROR(INDEX($G$72:$R$83,MATCH($X72,$C$72:$C$83,0),MATCH(AC$67,$G$68:$R$68,0)), IFERROR(INDEX($G$72:$R$83,MATCH($X72,$C$72:$C$83,0),MATCH(AC$67,$G$69:$R$69,0)), IFERROR(INDEX($G$72:$R$83,MATCH($X72,$C$72:$C$83,0),MATCH(AC$67,$G$70:$R$70,0)), IFERROR(INDEX($G$72:$R$83,MATCH($X72,$D$72:$D$83,0),MATCH(AC$67,$G$67:$R$67,0)), IFERROR(INDEX($G$72:$R$83,MATCH($X72,$D$72:$D$83,0),MATCH(AC$67,$G$68:$R$68,0)), IFERROR(INDEX($G$72:$R$83,MATCH($X72,$D$72:$D$83,0),MATCH(AC$67,$G$69:$R$69,0)), IFERROR(INDEX($G$72:$R$83,MATCH($X72,$D$72:$D$83,0),MATCH(AC$67,$G$70:$R$70,0)), IFERROR(INDEX($G$72:$R$83,MATCH($X72,$E$72:$E$83,0),MATCH(AC$67,$G$67:$R$67,0)), IFERROR(INDEX($G$72:$R$83,MATCH($X72,$E$72:$E$83,0),MATCH(AC$67,$G$68:$R$68,0)), IFERROR(INDEX($G$72:$R$83,MATCH($X72,$E$72:$E$83,0),MATCH(AC$67,$G$69:$R$69,0)), INDEX($G$72:$R$83,MATCH($X72,$E$72:$E$83,0),MATCH(AC$67,$G$70:$R$70,0))))))))))))))))) -> 1 | AD72: =IFERROR(INDEX($G$72:$R$83,MATCH($X72,$B$72:$B$83,0),MATCH(AD$67,$G$67:$R$67,0)), IFERROR(INDEX($G$72:$R$83,MATCH($X72,$B$72:$B$83,0),MATCH(AD$67,$G$68:$R$68,0)), IFERROR(INDEX($G$72:$R$83,MATCH($X72,$B$72:$B$83,0),MATCH(AD$67,$G$69:$R$69,0)), IFERROR(INDEX($G$72:$R$83,MATCH($X72,$B$72:$B$83,0),MATCH(AD$67,$G$70:$R$70,0)), IFERROR(INDEX($G$72:$R$83,MATCH($X72,$C$72:$C$83,0),MATCH(AD$67,$G$67:$R$67,0)), IFERROR(INDEX($G$72:$R$83,MATCH($X72,$C$72:$C$83,0),MATCH(AD$67,$G$68:$R$68,0)), IFERROR(INDEX($G$72:$R$83,MATCH($X72,$C$72:$C$83,0),MATCH(AD$67,$G$69:$R$69,0)), IFERROR(INDEX($G$72:$R$83,MATCH($X72,$C$72:$C$83,0),MATCH(AD$67,$G$70:$R$70,0)), IFERROR(INDEX($G$72:$R$83,MATCH($X72,$D$72:$D$83,0),MATCH(AD$67,$G$67:$R$67,0)), IFERROR(INDEX($G$72:$R$83,MATCH($X72,$D$72:$D$83,0),MATCH(AD$67,$G$68:$R$68,0)), IFERROR(INDEX($G$72:$R$83,MATCH($X72,$D$72:$D$83,0),MATCH(AD$67,$G$69:$R$69,0)), IFERROR(INDEX($G$72:$R$83,MATCH($X72,$D$72:$D$83,0),MATCH(AD$67,$G$70:$R$70,0)), IFERROR(INDEX($G$72:$R$83,MATCH($X72,$E$72:$E$83,0),MATCH(AD$67,$G$67:$R$67,0)), IFERROR(INDEX($G$72:$R$83,MATCH($X72,$E$72:$E$83,0),MATCH(AD$67,$G$68:$R$68,0)), IFERROR(INDEX($G$72:$R$83,MATCH($X72,$E$72:$E$83,0),MATCH(AD$67,$G$69:$R$69,0)), INDEX($G$72:$R$83,MATCH($X72,$E$72:$E$83,0),MATCH(AD$67,$G$70:$R$70,0))))))))))))))))) -> 1 | AE72: =IFERROR(INDEX($G$72:$R$83,MATCH($X72,$B$72:$B$83,0),MATCH(AE$67,$G$67:$R$67,0)), IFERROR(INDEX($G$72:$R$83,MATCH($X72,$B$72:$B$83,0),MATCH(AE$67,$G$68:$R$68,0)), IFERROR(INDEX($G$72:$R$83,MATCH($X72,$B$72:$B$83,0),MATCH(AE$67,$G$69:$R$69,0)), IFERROR(INDEX($G$72:$R$83,MATCH($X72,$B$72:$B$83,0),MATCH(AE$67,$G$70:$R$70,0)), IFERROR(INDEX($G$72:$R$83,MATCH($X72,$C$72:$C$83,0),MATCH(AE$67,$G$67:$R$67,0)), IFERROR(INDEX($G$72:$R$83,MATCH($X72,$C$72:$C$83,0),MATCH(AE$67,$G$68:$R$68,0)), IFERROR(INDEX($G$72:$R$83,MATCH($X72,$C$72:$C$83,0),MATCH(AE$67,$G$69:$R$69,0)), IFERROR(INDEX($G$72:$R$83,MATCH($X72,$C$72:$C$83,0),MATCH(AE$67,$G$70:$R$70,0)), IFERROR(INDEX($G$72:$R$83,MATCH($X72,$D$72:$D$83,0),MATCH(AE$67,$G$67:$R$67,0)), IFERROR(INDEX($G$72:$R$83,MATCH($X72,$D$72:$D$83,0),MATCH(AE$67,$G$68:$R$68,0)), IFERROR(INDEX($G$72:$R$83,MATCH($X72,$D$72:$D$83,0),MATCH(AE$67,$G$69:$R$69,0)), IFERROR(INDEX($G$72:$R$83,MATCH($X72,$D$72:$D$83,0),MATCH(AE$67,$G$70:$R$70,0)), IFERROR(INDEX($G$72:$R$83,MATCH($X72,$E$72:$E$83,0),MATCH(AE$67,$G$67:$R$67,0)), IFERROR(INDEX($G$72:$R$83,MATCH($X72,$E$72:$E$83,0),MATCH(AE$67,$G$68:$R$68,0)), IFERROR(INDEX($G$72:$R$83,MATCH($X72,$E$72:$E$83,0),MATCH(AE$67,$G$69:$R$69,0)), INDEX($G$72:$R$83,MATCH($X72,$E$72:$E$83,0),MATCH(AE$67,$G$70:$R$70,0))))))))))))))))) -> 1 | AF72: =IFERROR(INDEX($G$72:$R$83,MATCH($X72,$B$72:$B$83,0),MATCH(AF$67,$G$67:$R$67,0)), IFERROR(INDEX($G$72:$R$83,MATCH($X72,$B$72:$B$83,0),MATCH(AF$67,$G$68:$R$68,0)), IFERROR(INDEX($G$72:$R$83,MATCH($X72,$B$72:$B$83,0),MATCH(AF$67,$G$69:$R$69,0)), IFERROR(INDEX($G$72:$R$83,MATCH($X72,$B$72:$B$83,0),MATCH(AF$67,$G$70:$R$70,0)), IFERROR(INDEX($G$72:$R$83,MATCH($X72,$C$72:$C$83,0),MATCH(AF$67,$G$67:$R$67,0)), IFERROR(INDEX($G$72:$R$83,MATCH($X72,$C$72:$C$83,0),MATCH(AF$67,$G$68:$R$68,0)), IFERROR(INDEX($G$72:$R$83,MATCH($X72,$C$72:$C$83,0),MATCH(AF$67,$G$69:$R$69,0)), IFERROR(INDEX($G$72:$R$83,MATCH($X72,$C$72:$C$83,0),MATCH(AF$67,$G$70:$R$70,0)), IFERROR(INDEX($G$72:$R$83,MATCH($X72,$D$72:$D$83,0),MATCH(AF$67,$G$67:$R$67,0)), IFERROR(INDEX($G$72:$R$83,MATCH($X72,$D$72:$D$83,0),MATCH(AF$67,$G$68:$R$68,0)), IFERROR(INDEX($G$72:$R$83,MATCH($X72,$D$72:$D$83,0),MATCH(AF$67,$G$69:$R$69,0)), IFERROR(INDEX($G$72:$R$83,MATCH($X72,$D$72:$D$83,0),MATCH(AF$67,$G$70:$R$70,0)), IFERROR(INDEX($G$72:$R$83,MATCH($X72,$E$72:$E$83,0),MATCH(AF$67,$G$67:$R$67,0)), IFERROR(INDEX($G$72:$R$83,MATCH($X72,$E$72:$E$83,0),MATCH(AF$67,$G$68:$R$68,0)), IFERROR(INDEX($G$72:$R$83,MATCH($X72,$E$72:$E$83,0),MATCH(AF$67,$G$69:$R$69,0)), INDEX($G$72:$R$83,MATCH($X72,$E$72:$E$83,0),MATCH(AF$67,$G$70:$R$70,0))))))))))))))))) -> 1 | ... AS72: =IFERROR(INDEX($G$72:$R$83,MATCH($X72,$B$72:$B$83,0),MATCH(AS$67,$G$67:$R$67,0)), IFERROR(INDEX($G$72:$R$83,MATCH($X72,$B$72:$B$83,0),MATCH(AS$67,$G$68:$R$68,0)), IFERROR(INDEX($G$72:$R$83,MATCH($X72,$B$72:$B$83,0),MATCH(AS$67,$G$69:$R$69,0)), IFERROR(INDEX($G$72:$R$83,MATCH($X72,$B$72:$B$83,0),MATCH(AS$67,$G$70:$R$70,0)), IFERROR(INDEX($G$72:$R$83,MATCH($X72,$C$72:$C$83,0),MATCH(AS$67,$G$67:$R$67,0)), IFERROR(INDEX($G$72:$R$83,MATCH($X72,$C$72:$C$83,0),MATCH(AS$67,$G$68:$R$68,0)), IFERROR(INDEX($G$72:$R$83,MATCH($X72,$C$72:$C$83,0),MATCH(AS$67,$G$69:$R$69,0)), IFERROR(INDEX($G$72:$R$83,MATCH($X72,$C$72:$C$83,0),MATCH(AS$67,$G$70:$R$70,0)), IFERROR(INDEX($G$72:$R$83,MATCH($X72,$D$72:$D$83,0),MATCH(AS$67,$G$67:$R$67,0)), IFERROR(INDEX($G$72:$R$83,MATCH($X72,$D$72:$D$83,0),MATCH(AS$67,$G$68:$R$68,0)), IFERROR(INDEX($G$72:$R$83,MATCH($X72,$D$72:$D$83,0),MATCH(AS$67,$G$69:$R$69,0)), IFERROR(INDEX($G$72:$R$83,MATCH($X72,$D$72:$D$83,0),MATCH(AS$67,$G$70:$R$70,0)), IFERROR(INDEX($G$72:$R$83,MATCH($X72,$E$72:$E$83,0),MATCH(AS$67,$G$67:$R$67,0)), IFERROR(INDEX($G$72:$R$83,MATCH($X72,$E$72:$E$83,0),MATCH(AS$67,$G$68:$R$68,0)), IFERROR(INDEX($G$72:$R$83,MATCH($X72,$E$72:$E$83,0),MATCH(AS$67,$G$69:$R$69,0)), INDEX($G$72:$R$83,MATCH($X72,$E$72:$E$83,0),MATCH(AS$67,$G$70:$R$70,0))))))))))))))))) -> 0
B73: US Treasuries, Long | F73: U.S. Long Treasuries | G73: 0.83 | H73: 1 | I73: 0.74 | J73: 0.6 | K73: 0 | L73: 0.28 | M73: 0.74 | N73: 0.51 | O73: 0.19 | P73: 0.24 | Q73: 0.37 | R73: 0.27 | X73: US Public Corporates IG AA | Y73: =IFERROR(INDEX($G$72:$R$83,MATCH($X73,$B$72:$B$83,0),MATCH(Y$67,$G$67:$R$67,0)), IFERROR(INDEX($G$72:$R$83,MATCH($X73,$B$72:$B$83,0),MATCH(Y$67,$G$68:$R$68,0)), IFERROR(INDEX($G$72:$R$83,MATCH($X73,$B$72:$B$83,0),MATCH(Y$67,$G$69:$R$69,0)), IFERROR(INDEX($G$72:$R$83,MATCH($X73,$B$72:$B$83,0),MATCH(Y$67,$G$70:$R$70,0)), IFERROR(INDEX($G$72:$R$83,MATCH($X73,$C$72:$C$83,0),MATCH(Y$67,$G$67:$R$67,0)), IFERROR(INDEX($G$72:$R$83,MATCH($X73,$C$72:$C$83,0),MATCH(Y$67,$G$68:$R$68,0)), IFERROR(INDEX($G$72:$R$83,MATCH($X73,$C$72:$C$83,0),MATCH(Y$67,$G$69:$R$69,0)), IFERROR(INDEX($G$72:$R$83,MATCH($X73,$C$72:$C$83,0),MATCH(Y$67,$G$70:$R$70,0)), IFERROR(INDEX($G$72:$R$83,MATCH($X73,$D$72:$D$83,0),MATCH(Y$67,$G$67:$R$67,0)), IFERROR(INDEX($G$72:$R$83,MATCH($X73,$D$72:$D$83,0),MATCH(Y$67,$G$68:$R$68,0)), IFERROR(INDEX($G$72:$R$83,MATCH($X73,$D$72:$D$83,0),MATCH(Y$67,$G$69:$R$69,0)), IFERROR(INDEX($G$72:$R$83,MATCH($X73,$D$72:$D$83,0),MATCH(Y$67,$G$70:$R$70,0)), IFERROR(INDEX($G$72:$R$83,MATCH($X73,$E$72:$E$83,0),MATCH(Y$67,$G$67:$R$67,0)), IFERROR(INDEX($G$72:$R$83,MATCH($X73,$E$72:$E$83,0),MATCH(Y$67,$G$68:$R$68,0)), IFERROR(INDEX($G$72:$R$83,MATCH($X73,$E$72:$E$83,0),MATCH(Y$67,$G$69:$R$69,0)), INDEX($G$72:$R$83,MATCH($X73,$E$72:$E$83,0),MATCH(Y$67,$G$70:$R$70,0))))))))))))))))) -> 0.52 | Z73: =IFERROR(INDEX($G$72:$R$83,MATCH($X73,$B$72:$B$83,0),MATCH(Z$67,$G$67:$R$67,0)), IFERROR(INDEX($G$72:$R$83,MATCH($X73,$B$72:$B$83,0),MATCH(Z$67,$G$68:$R$68,0)), IFERROR(INDEX($G$72:$R$83,MATCH($X73,$B$72:$B$83,0),MATCH(Z$67,$G$69:$R$69,0)), IFERROR(INDEX($G$72:$R$83,MATCH($X73,$B$72:$B$83,0),MATCH(Z$67,$G$70:$R$70,0)), IFERROR(INDEX($G$72:$R$83,MATCH($X73,$C$72:$C$83,0),MATCH(Z$67,$G$67:$R$67,0)), IFERROR(INDEX($G$72:$R$83,MATCH($X73,$C$72:$C$83,0),MATCH(Z$67,$G$68:$R$68,0)), IFERROR(INDEX($G$72:$R$83,MATCH($X73,$C$72:$C$83,0),MATCH(Z$67,$G$69:$R$69,0)), IFERROR(INDEX($G$72:$R$83,MATCH($X73,$C$72:$C$83,0),MATCH(Z$67,$G$70:$R$70,0)), IFERROR(INDEX($G$72:$R$83,MATCH($X73,$D$72:$D$83,0),MATCH(Z$67,$G$67:$R$67,0)), IFERROR(INDEX($G$72:$R$83,MATCH($X73,$D$72:$D$83,0),MATCH(Z$67,$G$68:$R$68,0)), IFERROR(INDEX($G$72:$R$83,MATCH($X73,$D$72:$D$83,0),MATCH(Z$67,$G$69:$R$69,0)), IFERROR(INDEX($G$72:$R$83,MATCH($X73,$D$72:$D$83,0),MATCH(Z$67,$G$70:$R$70,0)), IFERROR(INDEX($G$72:$R$83,MATCH($X73,$E$72:$E$83,0),MATCH(Z$67,$G$67:$R$67,0)), IFERROR(INDEX($G$72:$R$83,MATCH($X73,$E$72:$E$83,0),MATCH(Z$67,$G$68:$R$68,0)), IFERROR(INDEX($G$72:$R$83,MATCH($X73,$E$72:$E$83,0),MATCH(Z$67,$G$69:$R$69,0)), INDEX($G$72:$R$83,MATCH($X73,$E$72:$E$83,0),MATCH(Z$67,$G$70:$R$70,0))))))))))))))))) -> 0.6 | AA73: =IFERROR(INDEX($G$72:$R$83,MATCH($X73,$B$72:$B$83,0),MATCH(AA$67,$G$67:$R$67,0)), IFERROR(INDEX($G$72:$R$83,MATCH($X73,$B$72:$B$83,0),MATCH(AA$67,$G$68:$R$68,0)), IFERROR(INDEX($G$72:$R$83,MATCH($X73,$B$72:$B$83,0),MATCH(AA$67,$G$69:$R$69,0)), IFERROR(INDEX($G$72:$R$83,MATCH($X73,$B$72:$B$83,0),MATCH(AA$67,$G$70:$R$70,0)), IFERROR(INDEX($G$72:$R$83,MATCH($X73,$C$72:$C$83,0),MATCH(AA$67,$G$67:$R$67,0)), IFERROR(INDEX($G$72:$R$83,MATCH($X73,$C$72:$C$83,0),MATCH(AA$67,$G$68:$R$68,0)), IFERROR(INDEX($G$72:$R$83,MATCH($X73,$C$72:$C$83,0),MATCH(AA$67,$G$69:$R$69,0)), IFERROR(INDEX($G$72:$R$83,MATCH($X73,$C$72:$C$83,0),MATCH(AA$67,$G$70:$R$70,0)), IFERROR(INDEX($G$72:$R$83,MATCH($X73,$D$72:$D$83,0),MATCH(AA$67,$G$67:$R$67,0)), IFERROR(INDEX($G$72:$R$83,MATCH($X73,$D$72:$D$83,0),MATCH(AA$67,$G$68:$R$68,0)), IFERROR(INDEX($G$72:$R$83,MATCH($X73,$D$72:$D$83,0),MATCH(AA$67,$G$69:$R$69,0)), IFERROR(INDEX($G$72:$R$83,MATCH($X73,$D$72:$D$83,0),MATCH(AA$67,$G$70:$R$70,0)), IFERROR(INDEX($G$72:$R$83,MATCH($X73,$E$72:$E$83,0),MATCH(AA$67,$G$67:$R$67,0)), IFERROR(INDEX($G$72:$R$83,MATCH($X73,$E$72:$E$83,0),MATCH(AA$67,$G$68:$R$68,0)), IFERROR(INDEX($G$72:$R$83,MATCH($X73,$E$72:$E$83,0),MATCH(AA$67,$G$69:$R$69,0)), INDEX($G$72:$R$83,MATCH($X73,$E$72:$E$83,0),MATCH(AA$67,$G$70:$R$70,0))))))))))))))))) -> 0.69 | AB73: =IFERROR(INDEX($G$72:$R$83,MATCH($X73,$B$72:$B$83,0),MATCH(AB$67,$G$67:$R$67,0)), IFERROR(INDEX($G$72:$R$83,MATCH($X73,$B$72:$B$83,0),MATCH(AB$67,$G$68:$R$68,0)), IFERROR(INDEX($G$72:$R$83,MATCH($X73,$B$72:$B$83,0),MATCH(AB$67,$G$69:$R$69,0)), IFERROR(INDEX($G$72:$R$83,MATCH($X73,$B$72:$B$83,0),MATCH(AB$67,$G$70:$R$70,0)), IFERROR(INDEX($G$72:$R$83,MATCH($X73,$C$72:$C$83,0),MATCH(AB$67,$G$67:$R$67,0)), IFERROR(INDEX($G$72:$R$83,MATCH($X73,$C$72:$C$83,0),MATCH(AB$67,$G$68:$R$68,0)), IFERROR(INDEX($G$72:$R$83,MATCH($X73,$C$72:$C$83,0),MATCH(AB$67,$G$69:$R$69,0)), IFERROR(INDEX($G$72:$R$83,MATCH($X73,$C$72:$C$83,0),MATCH(AB$67,$G$70:$R$70,0)), IFERROR(INDEX($G$72:$R$83,MATCH($X73,$D$72:$D$83,0),MATCH(AB$67,$G$67:$R$67,0)), IFERROR(INDEX($G$72:$R$83,MATCH($X73,$D$72:$D$83,0),MATCH(AB$67,$G$68:$R$68,0)), IFERROR(INDEX($G$72:$R$83,MATCH($X73,$D$72:$D$83,0),MATCH(AB$67,$G$69:$R$69,0)), IFERROR(INDEX($G$72:$R$83,MATCH($X73,$D$72:$D$83,0),MATCH(AB$67,$G$70:$R$70,0)), IFERROR(INDEX($G$72:$R$83,MATCH($X73,$E$72:$E$83,0),MATCH(AB$67,$G$67:$R$67,0)), IFERROR(INDEX($G$72:$R$83,MATCH($X73,$E$72:$E$83,0),MATCH(AB$67,$G$68:$R$68,0)), IFERROR(INDEX($G$72:$R$83,MATCH($X73,$E$72:$E$83,0),MATCH(AB$67,$G$69:$R$69,0)), INDEX($G$72:$R$83,MATCH($X73,$E$72:$E$83,0),MATCH(AB$67,$G$70:$R$70,0))))))))))))))))) -> 0.64 | AC73: =IFERROR(INDEX($G$72:$R$83,MATCH($X73,$B$72:$B$83,0),MATCH(AC$67,$G$67:$R$67,0)), IFERROR(INDEX($G$72:$R$83,MATCH($X73,$B$72:$B$83,0),MATCH(AC$67,$G$68:$R$68,0)), IFERROR(INDEX($G$72:$R$83,MATCH($X73,$B$72:$B$83,0),MATCH(AC$67,$G$69:$R$69,0)), IFERROR(INDEX($G$72:$R$83,MATCH($X73,$B$72:$B$83,0),MATCH(AC$67,$G$70:$R$70,0)), IFERROR(INDEX($G$72:$R$83,MATCH($X73,$C$72:$C$83,0),MATCH(AC$67,$G$67:$R$67,0)), IFERROR(INDEX($G$72:$R$83,MATCH($X73,$C$72:$C$83,0),MATCH(AC$67,$G$68:$R$68,0)), IFERROR(INDEX($G$72:$R$83,MATCH($X73,$C$72:$C$83,0),MATCH(AC$67,$G$69:$R$69,0)), IFERROR(INDEX($G$72:$R$83,MATCH($X73,$C$72:$C$83,0),MATCH(AC$67,$G$70:$R$70,0)), IFERROR(INDEX($G$72:$R$83,MATCH($X73,$D$72:$D$83,0),MATCH(AC$67,$G$67:$R$67,0)), IFERROR(INDEX($G$72:$R$83,MATCH($X73,$D$72:$D$83,0),MATCH(AC$67,$G$68:$R$68,0)), IFERROR(INDEX($G$72:$R$83,MATCH($X73,$D$72:$D$83,0),MATCH(AC$67,$G$69:$R$69,0)), IFERROR(INDEX($G$72:$R$83,MATCH($X73,$D$72:$D$83,0),MATCH(AC$67,$G$70:$R$70,0)), IFERROR(INDEX($G$72:$R$83,MATCH($X73,$E$72:$E$83,0),MATCH(AC$67,$G$67:$R$67,0)), IFERROR(INDEX($G$72:$R$83,MATCH($X73,$E$72:$E$83,0),MATCH(AC$67,$G$68:$R$68,0)), IFERROR(INDEX($G$72:$R$83,MATCH($X73,$E$72:$E$83,0),MATCH(AC$67,$G$69:$R$69,0)), INDEX($G$72:$R$83,MATCH($X73,$E$72:$E$83,0),MATCH(AC$67,$G$70:$R$70,0))))))))))))))))) -> 1 | AD73: =IFERROR(INDEX($G$72:$R$83,MATCH($X73,$B$72:$B$83,0),MATCH(AD$67,$G$67:$R$67,0)), IFERROR(INDEX($G$72:$R$83,MATCH($X73,$B$72:$B$83,0),MATCH(AD$67,$G$68:$R$68,0)), IFERROR(INDEX($G$72:$R$83,MATCH($X73,$B$72:$B$83,0),MATCH(AD$67,$G$69:$R$69,0)), IFERROR(INDEX($G$72:$R$83,MATCH($X73,$B$72:$B$83,0),MATCH(AD$67,$G$70:$R$70,0)), IFERROR(INDEX($G$72:$R$83,MATCH($X73,$C$72:$C$83,0),MATCH(AD$67,$G$67:$R$67,0)), IFERROR(INDEX($G$72:$R$83,MATCH($X73,$C$72:$C$83,0),MATCH(AD$67,$G$68:$R$68,0)), IFERROR(INDEX($G$72:$R$83,MATCH($X73,$C$72:$C$83,0),MATCH(AD$67,$G$69:$R$69,0)), IFERROR(INDEX($G$72:$R$83,MATCH($X73,$C$72:$C$83,0),MATCH(AD$67,$G$70:$R$70,0)), IFERROR(INDEX($G$72:$R$83,MATCH($X73,$D$72:$D$83,0),MATCH(AD$67,$G$67:$R$67,0)), IFERROR(INDEX($G$72:$R$83,MATCH($X73,$D$72:$D$83,0),MATCH(AD$67,$G$68:$R$68,0)), IFERROR(INDEX($G$72:$R$83,MATCH($X73,$D$72:$D$83,0),MATCH(AD$67,$G$69:$R$69,0)), IFERROR(INDEX($G$72:$R$83,MATCH($X73,$D$72:$D$83,0),MATCH(AD$67,$G$70:$R$70,0)), IFERROR(INDEX($G$72:$R$83,MATCH($X73,$E$72:$E$83,0),MATCH(AD$67,$G$67:$R$67,0)), IFERROR(INDEX($G$72:$R$83,MATCH($X73,$E$72:$E$83,0),MATCH(AD$67,$G$68:$R$68,0)), IFERROR(INDEX($G$72:$R$83,MATCH($X73,$E$72:$E$83,0),MATCH(AD$67,$G$69:$R$69,0)), INDEX($G$72:$R$83,MATCH($X73,$E$72:$E$83,0),MATCH(AD$67,$G$70:$R$70,0))))))))))))))))) -> 1 | AE73: =IFERROR(INDEX($G$72:$R$83,MATCH($X73,$B$72:$B$83,0),MATCH(AE$67,$G$67:$R$67,0)), IFERROR(INDEX($G$72:$R$83,MATCH($X73,$B$72:$B$83,0),MATCH(AE$67,$G$68:$R$68,0)), IFERROR(INDEX($G$72:$R$83,MATCH($X73,$B$72:$B$83,0),MATCH(AE$67,$G$69:$R$69,0)), IFERROR(INDEX($G$72:$R$83,MATCH($X73,$B$72:$B$83,0),MATCH(AE$67,$G$70:$R$70,0)), IFERROR(INDEX($G$72:$R$83,MATCH($X73,$C$72:$C$83,0),MATCH(AE$67,$G$67:$R$67,0)), IFERROR(INDEX($G$72:$R$83,MATCH($X73,$C$72:$C$83,0),MATCH(AE$67,$G$68:$R$68,0)), IFERROR(INDEX($G$72:$R$83,MATCH($X73,$C$72:$C$83,0),MATCH(AE$67,$G$69:$R$69,0)), IFERROR(INDEX($G$72:$R$83,MATCH($X73,$C$72:$C$83,0),MATCH(AE$67,$G$70:$R$70,0)), IFERROR(INDEX($G$72:$R$83,MATCH($X73,$D$72:$D$83,0),MATCH(AE$67,$G$67:$R$67,0)), IFERROR(INDEX($G$72:$R$83,MATCH($X73,$D$72:$D$83,0),MATCH(AE$67,$G$68:$R$68,0)), IFERROR(INDEX($G$72:$R$83,MATCH($X73,$D$72:$D$83,0),MATCH(AE$67,$G$69:$R$69,0)), IFERROR(INDEX($G$72:$R$83,MATCH($X73,$D$72:$D$83,0),MATCH(AE$67,$G$70:$R$70,0)), IFERROR(INDEX($G$72:$R$83,MATCH($X73,$E$72:$E$83,0),MATCH(AE$67,$G$67:$R$67,0)), IFERROR(INDEX($G$72:$R$83,MATCH($X73,$E$72:$E$83,0),MATCH(AE$67,$G$68:$R$68,0)), IFERROR(INDEX($G$72:$R$83,MATCH($X73,$E$72:$E$83,0),MATCH(AE$67,$G$69:$R$69,0)), INDEX($G$72:$R$83,MATCH($X73,$E$72:$E$83,0),MATCH(AE$67,$G$70:$R$70,0))))))))))))))))) -> 1 | AF73: =IFERROR(INDEX($G$72:$R$83,MATCH($X73,$B$72:$B$83,0),MATCH(AF$67,$G$67:$R$67,0)), IFERROR(INDEX($G$72:$R$83,MATCH($X73,$B$72:$B$83,0),MATCH(AF$67,$G$68:$R$68,0)), IFERROR(INDEX($G$72:$R$83,MATCH($X73,$B$72:$B$83,0),MATCH(AF$67,$G$69:$R$69,0)), IFERROR(INDEX($G$72:$R$83,MATCH($X73,$B$72:$B$83,0),MATCH(AF$67,$G$70:$R$70,0)), IFERROR(INDEX($G$72:$R$83,MATCH($X73,$C$72:$C$83,0),MATCH(AF$67,$G$67:$R$67,0)), IFERROR(INDEX($G$72:$R$83,MATCH($X73,$C$72:$C$83,0),MATCH(AF$67,$G$68:$R$68,0)), IFERROR(INDEX($G$72:$R$83,MATCH($X73,$C$72:$C$83,0),MATCH(AF$67,$G$69:$R$69,0)), IFERROR(INDEX($G$72:$R$83,MATCH($X73,$C$72:$C$83,0),MATCH(AF$67,$G$70:$R$70,0)), IFERROR(INDEX($G$72:$R$83,MATCH($X73,$D$72:$D$83,0),MATCH(AF$67,$G$67:$R$67,0)), IFERROR(INDEX($G$72:$R$83,MATCH($X73,$D$72:$D$83,0),MATCH(AF$67,$G$68:$R$68,0)), IFERROR(INDEX($G$72:$R$83,MATCH($X73,$D$72:$D$83,0),MATCH(AF$67,$G$69:$R$69,0)), IFERROR(INDEX($G$72:$R$83,MATCH($X73,$D$72:$D$83,0),MATCH(AF$67,$G$70:$R$70,0)), IFERROR(INDEX($G$72:$R$83,MATCH($X73,$E$72:$E$83,0),MATCH(AF$67,$G$67:$R$67,0)), IFERROR(INDEX($G$72:$R$83,MATCH($X73,$E$72:$E$83,0),MATCH(AF$67,$G$68:$R$68,0)), IFERROR(INDEX($G$72:$R$83,MATCH($X73,$E$72:$E$83,0),MATCH(AF$67,$G$69:$R$69,0)), INDEX($G$72:$R$83,MATCH($X73,$E$72:$E$83,0),MATCH(AF$67,$G$70:$R$70,0))))))))))))))))) -> 1 | ... AS73: =IFERROR(INDEX($G$72:$R$83,MATCH($X73,$B$72:$B$83,0),MATCH(AS$67,$G$67:$R$67,0)), IFERROR(INDEX($G$72:$R$83,MATCH($X73,$B$72:$B$83,0),MATCH(AS$67,$G$68:$R$68,0)), IFERROR(INDEX($G$72:$R$83,MATCH($X73,$B$72:$B$83,0),MATCH(AS$67,$G$69:$R$69,0)), IFERROR(INDEX($G$72:$R$83,MATCH($X73,$B$72:$B$83,0),MATCH(AS$67,$G$70:$R$70,0)), IFERROR(INDEX($G$72:$R$83,MATCH($X73,$C$72:$C$83,0),MATCH(AS$67,$G$67:$R$67,0)), IFERROR(INDEX($G$72:$R$83,MATCH($X73,$C$72:$C$83,0),MATCH(AS$67,$G$68:$R$68,0)), IFERROR(INDEX($G$72:$R$83,MATCH($X73,$C$72:$C$83,0),MATCH(AS$67,$G$69:$R$69,0)), IFERROR(INDEX($G$72:$R$83,MATCH($X73,$C$72:$C$83,0),MATCH(AS$67,$G$70:$R$70,0)), IFERROR(INDEX($G$72:$R$83,MATCH($X73,$D$72:$D$83,0),MATCH(AS$67,$G$67:$R$67,0)), IFERROR(INDEX($G$72:$R$83,MATCH($X73,$D$72:$D$83,0),MATCH(AS$67,$G$68:$R$68,0)), IFERROR(INDEX($G$72:$R$83,MATCH($X73,$D$72:$D$83,0),MATCH(AS$67,$G$69:$R$69,0)), IFERROR(INDEX($G$72:$R$83,MATCH($X73,$D$72:$D$83,0),MATCH(AS$67,$G$70:$R$70,0)), IFERROR(INDEX($G$72:$R$83,MATCH($X73,$E$72:$E$83,0),MATCH(AS$67,$G$67:$R$67,0)), IFERROR(INDEX($G$72:$R$83,MATCH($X73,$E$72:$E$83,0),MATCH(AS$67,$G$68:$R$68,0)), IFERROR(INDEX($G$72:$R$83,MATCH($X73,$E$72:$E$83,0),MATCH(AS$67,$G$69:$R$69,0)), INDEX($G$72:$R$83,MATCH($X73,$E$72:$E$83,0),MATCH(AS$67,$G$70:$R$70,0))))))))))))))))) -> 0
B74: Residential Mortgage-Backed Securities | C74: Commercial Mortgage-Backed Securities | D74: Asset-Backed Securities | F74: U.S. Securitized | G74: 0.78 | H74: 0.74 | I74: 1 | J74: 0.75 | K74: 0.38 | L74: 0.04 | M74: 0.7 | N74: 0.69 | O74: -0.09 | P74: 0.5 | Q74: 0.02 | R74: 0.13 | X74: US Public Corporates IG A | Y74: =IFERROR(INDEX($G$72:$R$83,MATCH($X74,$B$72:$B$83,0),MATCH(Y$67,$G$67:$R$67,0)), IFERROR(INDEX($G$72:$R$83,MATCH($X74,$B$72:$B$83,0),MATCH(Y$67,$G$68:$R$68,0)), IFERROR(INDEX($G$72:$R$83,MATCH($X74,$B$72:$B$83,0),MATCH(Y$67,$G$69:$R$69,0)), IFERROR(INDEX($G$72:$R$83,MATCH($X74,$B$72:$B$83,0),MATCH(Y$67,$G$70:$R$70,0)), IFERROR(INDEX($G$72:$R$83,MATCH($X74,$C$72:$C$83,0),MATCH(Y$67,$G$67:$R$67,0)), IFERROR(INDEX($G$72:$R$83,MATCH($X74,$C$72:$C$83,0),MATCH(Y$67,$G$68:$R$68,0)), IFERROR(INDEX($G$72:$R$83,MATCH($X74,$C$72:$C$83,0),MATCH(Y$67,$G$69:$R$69,0)), IFERROR(INDEX($G$72:$R$83,MATCH($X74,$C$72:$C$83,0),MATCH(Y$67,$G$70:$R$70,0)), IFERROR(INDEX($G$72:$R$83,MATCH($X74,$D$72:$D$83,0),MATCH(Y$67,$G$67:$R$67,0)), IFERROR(INDEX($G$72:$R$83,MATCH($X74,$D$72:$D$83,0),MATCH(Y$67,$G$68:$R$68,0)), IFERROR(INDEX($G$72:$R$83,MATCH($X74,$D$72:$D$83,0),MATCH(Y$67,$G$69:$R$69,0)), IFERROR(INDEX($G$72:$R$83,MATCH($X74,$D$72:$D$83,0),MATCH(Y$67,$G$70:$R$70,0)), IFERROR(INDEX($G$72:$R$83,MATCH($X74,$E$72:$E$83,0),MATCH(Y$67,$G$67:$R$67,0)), IFERROR(INDEX($G$72:$R$83,MATCH($X74,$E$72:$E$83,0),MATCH(Y$67,$G$68:$R$68,0)), IFERROR(INDEX($G$72:$R$83,MATCH($X74,$E$72:$E$83,0),MATCH(Y$67,$G$69:$R$69,0)), INDEX($G$72:$R$83,MATCH($X74,$E$72:$E$83,0),MATCH(Y$67,$G$70:$R$70,0))))))))))))))))) -> 0.52 | Z74: =IFERROR(INDEX($G$72:$R$83,MATCH($X74,$B$72:$B$83,0),MATCH(Z$67,$G$67:$R$67,0)), IFERROR(INDEX($G$72:$R$83,MATCH($X74,$B$72:$B$83,0),MATCH(Z$67,$G$68:$R$68,0)), IFERROR(INDEX($G$72:$R$83,MATCH($X74,$B$72:$B$83,0),MATCH(Z$67,$G$69:$R$69,0)), IFERROR(INDEX($G$72:$R$83,MATCH($X74,$B$72:$B$83,0),MATCH(Z$67,$G$70:$R$70,0)), IFERROR(INDEX($G$72:$R$83,MATCH($X74,$C$72:$C$83,0),MATCH(Z$67,$G$67:$R$67,0)), IFERROR(INDEX($G$72:$R$83,MATCH($X74,$C$72:$C$83,0),MATCH(Z$67,$G$68:$R$68,0)), IFERROR(INDEX($G$72:$R$83,MATCH($X74,$C$72:$C$83,0),MATCH(Z$67,$G$69:$R$69,0)), IFERROR(INDEX($G$72:$R$83,MATCH($X74,$C$72:$C$83,0),MATCH(Z$67,$G$70:$R$70,0)), IFERROR(INDEX($G$72:$R$83,MATCH($X74,$D$72:$D$83,0),MATCH(Z$67,$G$67:$R$67,0)), IFERROR(INDEX($G$72:$R$83,MATCH($X74,$D$72:$D$83,0),MATCH(Z$67,$G$68:$R$68,0)), IFERROR(INDEX($G$72:$R$83,MATCH($X74,$D$72:$D$83,0),MATCH(Z$67,$G$69:$R$69,0)), IFERROR(INDEX($G$72:$R$83,MATCH($X74,$D$72:$D$83,0),MATCH(Z$67,$G$70:$R$70,0)), IFERROR(INDEX($G$72:$R$83,MATCH($X74,$E$72:$E$83,0),MATCH(Z$67,$G$67:$R$67,0)), IFERROR(INDEX($G$72:$R$83,MATCH($X74,$E$72:$E$83,0),MATCH(Z$67,$G$68:$R$68,0)), IFERROR(INDEX($G$72:$R$83,MATCH($X74,$E$72:$E$83,0),MATCH(Z$67,$G$69:$R$69,0)), INDEX($G$72:$R$83,MATCH($X74,$E$72:$E$83,0),MATCH(Z$67,$G$70:$R$70,0))))))))))))))))) -> 0.6 | AA74: =IFERROR(INDEX($G$72:$R$83,MATCH($X74,$B$72:$B$83,0),MATCH(AA$67,$G$67:$R$67,0)), IFERROR(INDEX($G$72:$R$83,MATCH($X74,$B$72:$B$83,0),MATCH(AA$67,$G$68:$R$68,0)), IFERROR(INDEX($G$72:$R$83,MATCH($X74,$B$72:$B$83,0),MATCH(AA$67,$G$69:$R$69,0)), IFERROR(INDEX($G$72:$R$83,MATCH($X74,$B$72:$B$83,0),MATCH(AA$67,$G$70:$R$70,0)), IFERROR(INDEX($G$72:$R$83,MATCH($X74,$C$72:$C$83,0),MATCH(AA$67,$G$67:$R$67,0)), IFERROR(INDEX($G$72:$R$83,MATCH($X74,$C$72:$C$83,0),MATCH(AA$67,$G$68:$R$68,0)), IFERROR(INDEX($G$72:$R$83,MATCH($X74,$C$72:$C$83,0),MATCH(AA$67,$G$69:$R$69,0)), IFERROR(INDEX($G$72:$R$83,MATCH($X74,$C$72:$C$83,0),MATCH(AA$67,$G$70:$R$70,0)), IFERROR(INDEX($G$72:$R$83,MATCH($X74,$D$72:$D$83,0),MATCH(AA$67,$G$67:$R$67,0)), IFERROR(INDEX($G$72:$R$83,MATCH($X74,$D$72:$D$83,0),MATCH(AA$67,$G$68:$R$68,0)), IFERROR(INDEX($G$72:$R$83,MATCH($X74,$D$72:$D$83,0),MATCH(AA$67,$G$69:$R$69,0)), IFERROR(INDEX($G$72:$R$83,MATCH($X74,$D$72:$D$83,0),MATCH(AA$67,$G$70:$R$70,0)), IFERROR(INDEX($G$72:$R$83,MATCH($X74,$E$72:$E$83,0),MATCH(AA$67,$G$67:$R$67,0)), IFERROR(INDEX($G$72:$R$83,MATCH($X74,$E$72:$E$83,0),MATCH(AA$67,$G$68:$R$68,0)), IFERROR(INDEX($G$72:$R$83,MATCH($X74,$E$72:$E$83,0),MATCH(AA$67,$G$69:$R$69,0)), INDEX($G$72:$R$83,MATCH($X74,$E$72:$E$83,0),MATCH(AA$67,$G$70:$R$70,0))))))))))))))))) -> 0.69 | AB74: =IFERROR(INDEX($G$72:$R$83,MATCH($X74,$B$72:$B$83,0),MATCH(AB$67,$G$67:$R$67,0)), IFERROR(INDEX($G$72:$R$83,MATCH($X74,$B$72:$B$83,0),MATCH(AB$67,$G$68:$R$68,0)), IFERROR(INDEX($G$72:$R$83,MATCH($X74,$B$72:$B$83,0),MATCH(AB$67,$G$69:$R$69,0)), IFERROR(INDEX($G$72:$R$83,MATCH($X74,$B$72:$B$83,0),MATCH(AB$67,$G$70:$R$70,0)), IFERROR(INDEX($G$72:$R$83,MATCH($X74,$C$72:$C$83,0),MATCH(AB$67,$G$67:$R$67,0)), IFERROR(INDEX($G$72:$R$83,MATCH($X74,$C$72:$C$83,0),MATCH(AB$67,$G$68:$R$68,0)), IFERROR(INDEX($G$72:$R$83,MATCH($X74,$C$72:$C$83,0),MATCH(AB$67,$G$69:$R$69,0)), IFERROR(INDEX($G$72:$R$83,MATCH($X74,$C$72:$C$83,0),MATCH(AB$67,$G$70:$R$70,0)), IFERROR(INDEX($G$72:$R$83,MATCH($X74,$D$72:$D$83,0),MATCH(AB$67,$G$67:$R$67,0)), IFERROR(INDEX($G$72:$R$83,MATCH($X74,$D$72:$D$83,0),MATCH(AB$67,$G$68:$R$68,0)), IFERROR(INDEX($G$72:$R$83,MATCH($X74,$D$72:$D$83,0),MATCH(AB$67,$G$69:$R$69,0)), IFERROR(INDEX($G$72:$R$83,MATCH($X74,$D$72:$D$83,0),MATCH(AB$67,$G$70:$R$70,0)), IFERROR(INDEX($G$72:$R$83,MATCH($X74,$E$72:$E$83,0),MATCH(AB$67,$G$67:$R$67,0)), IFERROR(INDEX($G$72:$R$83,MATCH($X74,$E$72:$E$83,0),MATCH(AB$67,$G$68:$R$68,0)), IFERROR(INDEX($G$72:$R$83,MATCH($X74,$E$72:$E$83,0),MATCH(AB$67,$G$69:$R$69,0)), INDEX($G$72:$R$83,MATCH($X74,$E$72:$E$83,0),MATCH(AB$67,$G$70:$R$70,0))))))))))))))))) -> 0.64 | AC74: =IFERROR(INDEX($G$72:$R$83,MATCH($X74,$B$72:$B$83,0),MATCH(AC$67,$G$67:$R$67,0)), IFERROR(INDEX($G$72:$R$83,MATCH($X74,$B$72:$B$83,0),MATCH(AC$67,$G$68:$R$68,0)), IFERROR(INDEX($G$72:$R$83,MATCH($X74,$B$72:$B$83,0),MATCH(AC$67,$G$69:$R$69,0)), IFERROR(INDEX($G$72:$R$83,MATCH($X74,$B$72:$B$83,0),MATCH(AC$67,$G$70:$R$70,0)), IFERROR(INDEX($G$72:$R$83,MATCH($X74,$C$72:$C$83,0),MATCH(AC$67,$G$67:$R$67,0)), IFERROR(INDEX($G$72:$R$83,MATCH($X74,$C$72:$C$83,0),MATCH(AC$67,$G$68:$R$68,0)), IFERROR(INDEX($G$72:$R$83,MATCH($X74,$C$72:$C$83,0),MATCH(AC$67,$G$69:$R$69,0)), IFERROR(INDEX($G$72:$R$83,MATCH($X74,$C$72:$C$83,0),MATCH(AC$67,$G$70:$R$70,0)), IFERROR(INDEX($G$72:$R$83,MATCH($X74,$D$72:$D$83,0),MATCH(AC$67,$G$67:$R$67,0)), IFERROR(INDEX($G$72:$R$83,MATCH($X74,$D$72:$D$83,0),MATCH(AC$67,$G$68:$R$68,0)), IFERROR(INDEX($G$72:$R$83,MATCH($X74,$D$72:$D$83,0),MATCH(AC$67,$G$69:$R$69,0)), IFERROR(INDEX($G$72:$R$83,MATCH($X74,$D$72:$D$83,0),MATCH(AC$67,$G$70:$R$70,0)), IFERROR(INDEX($G$72:$R$83,MATCH($X74,$E$72:$E$83,0),MATCH(AC$67,$G$67:$R$67,0)), IFERROR(INDEX($G$72:$R$83,MATCH($X74,$E$72:$E$83,0),MATCH(AC$67,$G$68:$R$68,0)), IFERROR(INDEX($G$72:$R$83,MATCH($X74,$E$72:$E$83,0),MATCH(AC$67,$G$69:$R$69,0)), INDEX($G$72:$R$83,MATCH($X74,$E$72:$E$83,0),MATCH(AC$67,$G$70:$R$70,0))))))))))))))))) -> 1 | AD74: =IFERROR(INDEX($G$72:$R$83,MATCH($X74,$B$72:$B$83,0),MATCH(AD$67,$G$67:$R$67,0)), IFERROR(INDEX($G$72:$R$83,MATCH($X74,$B$72:$B$83,0),MATCH(AD$67,$G$68:$R$68,0)), IFERROR(INDEX($G$72:$R$83,MATCH($X74,$B$72:$B$83,0),MATCH(AD$67,$G$69:$R$69,0)), IFERROR(INDEX($G$72:$R$83,MATCH($X74,$B$72:$B$83,0),MATCH(AD$67,$G$70:$R$70,0)), IFERROR(INDEX($G$72:$R$83,MATCH($X74,$C$72:$C$83,0),MATCH(AD$67,$G$67:$R$67,0)), IFERROR(INDEX($G$72:$R$83,MATCH($X74,$C$72:$C$83,0),MATCH(AD$67,$G$68:$R$68,0)), IFERROR(INDEX($G$72:$R$83,MATCH($X74,$C$72:$C$83,0),MATCH(AD$67,$G$69:$R$69,0)), IFERROR(INDEX($G$72:$R$83,MATCH($X74,$C$72:$C$83,0),MATCH(AD$67,$G$70:$R$70,0)), IFERROR(INDEX($G$72:$R$83,MATCH($X74,$D$72:$D$83,0),MATCH(AD$67,$G$67:$R$67,0)), IFERROR(INDEX($G$72:$R$83,MATCH($X74,$D$72:$D$83,0),MATCH(AD$67,$G$68:$R$68,0)), IFERROR(INDEX($G$72:$R$83,MATCH($X74,$D$72:$D$83,0),MATCH(AD$67,$G$69:$R$69,0)), IFERROR(INDEX($G$72:$R$83,MATCH($X74,$D$72:$D$83,0),MATCH(AD$67,$G$70:$R$70,0)), IFERROR(INDEX($G$72:$R$83,MATCH($X74,$E$72:$E$83,0),MATCH(AD$67,$G$67:$R$67,0)), IFERROR(INDEX($G$72:$R$83,MATCH($X74,$E$72:$E$83,0),MATCH(AD$67,$G$68:$R$68,0)), IFERROR(INDEX($G$72:$R$83,MATCH($X74,$E$72:$E$83,0),MATCH(AD$67,$G$69:$R$69,0)), INDEX($G$72:$R$83,MATCH($X74,$E$72:$E$83,0),MATCH(AD$67,$G$70:$R$70,0))))))))))))))))) -> 1 | AE74: =IFERROR(INDEX($G$72:$R$83,MATCH($X74,$B$72:$B$83,0),MATCH(AE$67,$G$67:$R$67,0)), IFERROR(INDEX($G$72:$R$83,MATCH($X74,$B$72:$B$83,0),MATCH(AE$67,$G$68:$R$68,0)), IFERROR(INDEX($G$72:$R$83,MATCH($X74,$B$72:$B$83,0),MATCH(AE$67,$G$69:$R$69,0)), IFERROR(INDEX($G$72:$R$83,MATCH($X74,$B$72:$B$83,0),MATCH(AE$67,$G$70:$R$70,0)), IFERROR(INDEX($G$72:$R$83,MATCH($X74,$C$72:$C$83,0),MATCH(AE$67,$G$67:$R$67,0)), IFERROR(INDEX($G$72:$R$83,MATCH($X74,$C$72:$C$83,0),MATCH(AE$67,$G$68:$R$68,0)), IFERROR(INDEX($G$72:$R$83,MATCH($X74,$C$72:$C$83,0),MATCH(AE$67,$G$69:$R$69,0)), IFERROR(INDEX($G$72:$R$83,MATCH($X74,$C$72:$C$83,0),MATCH(AE$67,$G$70:$R$70,0)), IFERROR(INDEX($G$72:$R$83,MATCH($X74,$D$72:$D$83,0),MATCH(AE$67,$G$67:$R$67,0)), IFERROR(INDEX($G$72:$R$83,MATCH($X74,$D$72:$D$83,0),MATCH(AE$67,$G$68:$R$68,0)), IFERROR(INDEX($G$72:$R$83,MATCH($X74,$D$72:$D$83,0),MATCH(AE$67,$G$69:$R$69,0)), IFERROR(INDEX($G$72:$R$83,MATCH($X74,$D$72:$D$83,0),MATCH(AE$67,$G$70:$R$70,0)), IFERROR(INDEX($G$72:$R$83,MATCH($X74,$E$72:$E$83,0),MATCH(AE$67,$G$67:$R$67,0)), IFERROR(INDEX($G$72:$R$83,MATCH($X74,$E$72:$E$83,0),MATCH(AE$67,$G$68:$R$68,0)), IFERROR(INDEX($G$72:$R$83,MATCH($X74,$E$72:$E$83,0),MATCH(AE$67,$G$69:$R$69,0)), INDEX($G$72:$R$83,MATCH($X74,$E$72:$E$83,0),MATCH(AE$67,$G$70:$R$70,0))))))))))))))))) -> 1 | AF74: =IFERROR(INDEX($G$72:$R$83,MATCH($X74,$B$72:$B$83,0),MATCH(AF$67,$G$67:$R$67,0)), IFERROR(INDEX($G$72:$R$83,MATCH($X74,$B$72:$B$83,0),MATCH(AF$67,$G$68:$R$68,0)), IFERROR(INDEX($G$72:$R$83,MATCH($X74,$B$72:$B$83,0),MATCH(AF$67,$G$69:$R$69,0)), IFERROR(INDEX($G$72:$R$83,MATCH($X74,$B$72:$B$83,0),MATCH(AF$67,$G$70:$R$70,0)), IFERROR(INDEX($G$72:$R$83,MATCH($X74,$C$72:$C$83,0),MATCH(AF$67,$G$67:$R$67,0)), IFERROR(INDEX($G$72:$R$83,MATCH($X74,$C$72:$C$83,0),MATCH(AF$67,$G$68:$R$68,0)), IFERROR(INDEX($G$72:$R$83,MATCH($X74,$C$72:$C$83,0),MATCH(AF$67,$G$69:$R$69,0)), IFERROR(INDEX($G$72:$R$83,MATCH($X74,$C$72:$C$83,0),MATCH(AF$67,$G$70:$R$70,0)), IFERROR(INDEX($G$72:$R$83,MATCH($X74,$D$72:$D$83,0),MATCH(AF$67,$G$67:$R$67,0)), IFERROR(INDEX($G$72:$R$83,MATCH($X74,$D$72:$D$83,0),MATCH(AF$67,$G$68:$R$68,0)), IFERROR(INDEX($G$72:$R$83,MATCH($X74,$D$72:$D$83,0),MATCH(AF$67,$G$69:$R$69,0)), IFERROR(INDEX($G$72:$R$83,MATCH($X74,$D$72:$D$83,0),MATCH(AF$67,$G$70:$R$70,0)), IFERROR(INDEX($G$72:$R$83,MATCH($X74,$E$72:$E$83,0),MATCH(AF$67,$G$67:$R$67,0)), IFERROR(INDEX($G$72:$R$83,MATCH($X74,$E$72:$E$83,0),MATCH(AF$67,$G$68:$R$68,0)), IFERROR(INDEX($G$72:$R$83,MATCH($X74,$E$72:$E$83,0),MATCH(AF$67,$G$69:$R$69,0)), INDEX($G$72:$R$83,MATCH($X74,$E$72:$E$83,0),MATCH(AF$67,$G$70:$R$70,0))))))))))))))))) -> 1 | ... AS74: =IFERROR(INDEX($G$72:$R$83,MATCH($X74,$B$72:$B$83,0),MATCH(AS$67,$G$67:$R$67,0)), IFERROR(INDEX($G$72:$R$83,MATCH($X74,$B$72:$B$83,0),MATCH(AS$67,$G$68:$R$68,0)), IFERROR(INDEX($G$72:$R$83,MATCH($X74,$B$72:$B$83,0),MATCH(AS$67,$G$69:$R$69,0)), IFERROR(INDEX($G$72:$R$83,MATCH($X74,$B$72:$B$83,0),MATCH(AS$67,$G$70:$R$70,0)), IFERROR(INDEX($G$72:$R$83,MATCH($X74,$C$72:$C$83,0),MATCH(AS$67,$G$67:$R$67,0)), IFERROR(INDEX($G$72:$R$83,MATCH($X74,$C$72:$C$83,0),MATCH(AS$67,$G$68:$R$68,0)), IFERROR(INDEX($G$72:$R$83,MATCH($X74,$C$72:$C$83,0),MATCH(AS$67,$G$69:$R$69,0)), IFERROR(INDEX($G$72:$R$83,MATCH($X74,$C$72:$C$83,0),MATCH(AS$67,$G$70:$R$70,0)), IFERROR(INDEX($G$72:$R$83,MATCH($X74,$D$72:$D$83,0),MATCH(AS$67,$G$67:$R$67,0)), IFERROR(INDEX($G$72:$R$83,MATCH($X74,$D$72:$D$83,0),MATCH(AS$67,$G$68:$R$68,0)), IFERROR(INDEX($G$72:$R$83,MATCH($X74,$D$72:$D$83,0),MATCH(AS$67,$G$69:$R$69,0)), IFERROR(INDEX($G$72:$R$83,MATCH($X74,$D$72:$D$83,0),MATCH(AS$67,$G$70:$R$70,0)), IFERROR(INDEX($G$72:$R$83,MATCH($X74,$E$72:$E$83,0),MATCH(AS$67,$G$67:$R$67,0)), IFERROR(INDEX($G$72:$R$83,MATCH($X74,$E$72:$E$83,0),MATCH(AS$67,$G$68:$R$68,0)), IFERROR(INDEX($G$72:$R$83,MATCH($X74,$E$72:$E$83,0),MATCH(AS$67,$G$69:$R$69,0)), INDEX($G$72:$R$83,MATCH($X74,$E$72:$E$83,0),MATCH(AS$67,$G$70:$R$70,0))))))))))))))))) -> 0
B75: US Public Corporates IG AAA | C75: US Public Corporates IG AA | D75: US Public Corporates IG A | E75: US Public Corporates IG BBB | F75: U.S. Inv Grade Corporate Bonds | G75: 0.52 | H75: 0.6 | I75: 0.75 | J75: 1 | K75: 0.66 | L75: 0.36 | M75: 0.64 | N75: 0.69 | O75: 0 | P75: 0.51 | Q75: 0.36 | R75: 0.28 | X75: US Public Corporates IG BBB | Y75: =IFERROR(INDEX($G$72:$R$83,MATCH($X75,$B$72:$B$83,0),MATCH(Y$67,$G$67:$R$67,0)), IFERROR(INDEX($G$72:$R$83,MATCH($X75,$B$72:$B$83,0),MATCH(Y$67,$G$68:$R$68,0)), IFERROR(INDEX($G$72:$R$83,MATCH($X75,$B$72:$B$83,0),MATCH(Y$67,$G$69:$R$69,0)), IFERROR(INDEX($G$72:$R$83,MATCH($X75,$B$72:$B$83,0),MATCH(Y$67,$G$70:$R$70,0)), IFERROR(INDEX($G$72:$R$83,MATCH($X75,$C$72:$C$83,0),MATCH(Y$67,$G$67:$R$67,0)), IFERROR(INDEX($G$72:$R$83,MATCH($X75,$C$72:$C$83,0),MATCH(Y$67,$G$68:$R$68,0)), IFERROR(INDEX($G$72:$R$83,MATCH($X75,$C$72:$C$83,0),MATCH(Y$67,$G$69:$R$69,0)), IFERROR(INDEX($G$72:$R$83,MATCH($X75,$C$72:$C$83,0),MATCH(Y$67,$G$70:$R$70,0)), IFERROR(INDEX($G$72:$R$83,MATCH($X75,$D$72:$D$83,0),MATCH(Y$67,$G$67:$R$67,0)), IFERROR(INDEX($G$72:$R$83,MATCH($X75,$D$72:$D$83,0),MATCH(Y$67,$G$68:$R$68,0)), IFERROR(INDEX($G$72:$R$83,MATCH($X75,$D$72:$D$83,0),MATCH(Y$67,$G$69:$R$69,0)), IFERROR(INDEX($G$72:$R$83,MATCH($X75,$D$72:$D$83,0),MATCH(Y$67,$G$70:$R$70,0)), IFERROR(INDEX($G$72:$R$83,MATCH($X75,$E$72:$E$83,0),MATCH(Y$67,$G$67:$R$67,0)), IFERROR(INDEX($G$72:$R$83,MATCH($X75,$E$72:$E$83,0),MATCH(Y$67,$G$68:$R$68,0)), IFERROR(INDEX($G$72:$R$83,MATCH($X75,$E$72:$E$83,0),MATCH(Y$67,$G$69:$R$69,0)), INDEX($G$72:$R$83,MATCH($X75,$E$72:$E$83,0),MATCH(Y$67,$G$70:$R$70,0))))))))))))))))) -> 0.52 | Z75: =IFERROR(INDEX($G$72:$R$83,MATCH($X75,$B$72:$B$83,0),MATCH(Z$67,$G$67:$R$67,0)), IFERROR(INDEX($G$72:$R$83,MATCH($X75,$B$72:$B$83,0),MATCH(Z$67,$G$68:$R$68,0)), IFERROR(INDEX($G$72:$R$83,MATCH($X75,$B$72:$B$83,0),MATCH(Z$67,$G$69:$R$69,0)), IFERROR(INDEX($G$72:$R$83,MATCH($X75,$B$72:$B$83,0),MATCH(Z$67,$G$70:$R$70,0)), IFERROR(INDEX($G$72:$R$83,MATCH($X75,$C$72:$C$83,0),MATCH(Z$67,$G$67:$R$67,0)), IFERROR(INDEX($G$72:$R$83,MATCH($X75,$C$72:$C$83,0),MATCH(Z$67,$G$68:$R$68,0)), IFERROR(INDEX($G$72:$R$83,MATCH($X75,$C$72:$C$83,0),MATCH(Z$67,$G$69:$R$69,0)), IFERROR(INDEX($G$72:$R$83,MATCH($X75,$C$72:$C$83,0),MATCH(Z$67,$G$70:$R$70,0)), IFERROR(INDEX($G$72:$R$83,MATCH($X75,$D$72:$D$83,0),MATCH(Z$67,$G$67:$R$67,0)), IFERROR(INDEX($G$72:$R$83,MATCH($X75,$D$72:$D$83,0),MATCH(Z$67,$G$68:$R$68,0)), IFERROR(INDEX($G$72:$R$83,MATCH($X75,$D$72:$D$83,0),MATCH(Z$67,$G$69:$R$69,0)), IFERROR(INDEX($G$72:$R$83,MATCH($X75,$D$72:$D$83,0),MATCH(Z$67,$G$70:$R$70,0)), IFERROR(INDEX($G$72:$R$83,MATCH($X75,$E$72:$E$83,0),MATCH(Z$67,$G$67:$R$67,0)), IFERROR(INDEX($G$72:$R$83,MATCH($X75,$E$72:$E$83,0),MATCH(Z$67,$G$68:$R$68,0)), IFERROR(INDEX($G$72:$R$83,MATCH($X75,$E$72:$E$83,0),MATCH(Z$67,$G$69:$R$69,0)), INDEX($G$72:$R$83,MATCH($X75,$E$72:$E$83,0),MATCH(Z$67,$G$70:$R$70,0))))))))))))))))) -> 0.6 | AA75: =IFERROR(INDEX($G$72:$R$83,MATCH($X75,$B$72:$B$83,0),MATCH(AA$67,$G$67:$R$67,0)), IFERROR(INDEX($G$72:$R$83,MATCH($X75,$B$72:$B$83,0),MATCH(AA$67,$G$68:$R$68,0)), IFERROR(INDEX($G$72:$R$83,MATCH($X75,$B$72:$B$83,0),MATCH(AA$67,$G$69:$R$69,0)), IFERROR(INDEX($G$72:$R$83,MATCH($X75,$B$72:$B$83,0),MATCH(AA$67,$G$70:$R$70,0)), IFERROR(INDEX($G$72:$R$83,MATCH($X75,$C$72:$C$83,0),MATCH(AA$67,$G$67:$R$67,0)), IFERROR(INDEX($G$72:$R$83,MATCH($X75,$C$72:$C$83,0),MATCH(AA$67,$G$68:$R$68,0)), IFERROR(INDEX($G$72:$R$83,MATCH($X75,$C$72:$C$83,0),MATCH(AA$67,$G$69:$R$69,0)), IFERROR(INDEX($G$72:$R$83,MATCH($X75,$C$72:$C$83,0),MATCH(AA$67,$G$70:$R$70,0)), IFERROR(INDEX($G$72:$R$83,MATCH($X75,$D$72:$D$83,0),MATCH(AA$67,$G$67:$R$67,0)), IFERROR(INDEX($G$72:$R$83,MATCH($X75,$D$72:$D$83,0),MATCH(AA$67,$G$68:$R$68,0)), IFERROR(INDEX($G$72:$R$83,MATCH($X75,$D$72:$D$83,0),MATCH(AA$67,$G$69:$R$69,0)), IFERROR(INDEX($G$72:$R$83,MATCH($X75,$D$72:$D$83,0),MATCH(AA$67,$G$70:$R$70,0)), IFERROR(INDEX($G$72:$R$83,MATCH($X75,$E$72:$E$83,0),MATCH(AA$67,$G$67:$R$67,0)), IFERROR(INDEX($G$72:$R$83,MATCH($X75,$E$72:$E$83,0),MATCH(AA$67,$G$68:$R$68,0)), IFERROR(INDEX($G$72:$R$83,MATCH($X75,$E$72:$E$83,0),MATCH(AA$67,$G$69:$R$69,0)), INDEX($G$72:$R$83,MATCH($X75,$E$72:$E$83,0),MATCH(AA$67,$G$70:$R$70,0))))))))))))))))) -> 0.69 | AB75: =IFERROR(INDEX($G$72:$R$83,MATCH($X75,$B$72:$B$83,0),MATCH(AB$67,$G$67:$R$67,0)), IFERROR(INDEX($G$72:$R$83,MATCH($X75,$B$72:$B$83,0),MATCH(AB$67,$G$68:$R$68,0)), IFERROR(INDEX($G$72:$R$83,MATCH($X75,$B$72:$B$83,0),MATCH(AB$67,$G$69:$R$69,0)), IFERROR(INDEX($G$72:$R$83,MATCH($X75,$B$72:$B$83,0),MATCH(AB$67,$G$70:$R$70,0)), IFERROR(INDEX($G$72:$R$83,MATCH($X75,$C$72:$C$83,0),MATCH(AB$67,$G$67:$R$67,0)), IFERROR(INDEX($G$72:$R$83,MATCH($X75,$C$72:$C$83,0),MATCH(AB$67,$G$68:$R$68,0)), IFERROR(INDEX($G$72:$R$83,MATCH($X75,$C$72:$C$83,0),MATCH(AB$67,$G$69:$R$69,0)), IFERROR(INDEX($G$72:$R$83,MATCH($X75,$C$72:$C$83,0),MATCH(AB$67,$G$70:$R$70,0)), IFERROR(INDEX($G$72:$R$83,MATCH($X75,$D$72:$D$83,0),MATCH(AB$67,$G$67:$R$67,0)), IFERROR(INDEX($G$72:$R$83,MATCH($X75,$D$72:$D$83,0),MATCH(AB$67,$G$68:$R$68,0)), IFERROR(INDEX($G$72:$R$83,MATCH($X75,$D$72:$D$83,0),MATCH(AB$67,$G$69:$R$69,0)), IFERROR(INDEX($G$72:$R$83,MATCH($X75,$D$72:$D$83,0),MATCH(AB$67,$G$70:$R$70,0)), IFERROR(INDEX($G$72:$R$83,MATCH($X75,$E$72:$E$83,0),MATCH(AB$67,$G$67:$R$67,0)), IFERROR(INDEX($G$72:$R$83,MATCH($X75,$E$72:$E$83,0),MATCH(AB$67,$G$68:$R$68,0)), IFERROR(INDEX($G$72:$R$83,MATCH($X75,$E$72:$E$83,0),MATCH(AB$67,$G$69:$R$69,0)), INDEX($G$72:$R$83,MATCH($X75,$E$72:$E$83,0),MATCH(AB$67,$G$70:$R$70,0))))))))))))))))) -> 0.64 | AC75: =IFERROR(INDEX($G$72:$R$83,MATCH($X75,$B$72:$B$83,0),MATCH(AC$67,$G$67:$R$67,0)), IFERROR(INDEX($G$72:$R$83,MATCH($X75,$B$72:$B$83,0),MATCH(AC$67,$G$68:$R$68,0)), IFERROR(INDEX($G$72:$R$83,MATCH($X75,$B$72:$B$83,0),MATCH(AC$67,$G$69:$R$69,0)), IFERROR(INDEX($G$72:$R$83,MATCH($X75,$B$72:$B$83,0),MATCH(AC$67,$G$70:$R$70,0)), IFERROR(INDEX($G$72:$R$83,MATCH($X75,$C$72:$C$83,0),MATCH(AC$67,$G$67:$R$67,0)), IFERROR(INDEX($G$72:$R$83,MATCH($X75,$C$72:$C$83,0),MATCH(AC$67,$G$68:$R$68,0)), IFERROR(INDEX($G$72:$R$83,MATCH($X75,$C$72:$C$83,0),MATCH(AC$67,$G$69:$R$69,0)), IFERROR(INDEX($G$72:$R$83,MATCH($X75,$C$72:$C$83,0),MATCH(AC$67,$G$70:$R$70,0)), IFERROR(INDEX($G$72:$R$83,MATCH($X75,$D$72:$D$83,0),MATCH(AC$67,$G$67:$R$67,0)), IFERROR(INDEX($G$72:$R$83,MATCH($X75,$D$72:$D$83,0),MATCH(AC$67,$G$68:$R$68,0)), IFERROR(INDEX($G$72:$R$83,MATCH($X75,$D$72:$D$83,0),MATCH(AC$67,$G$69:$R$69,0)), IFERROR(INDEX($G$72:$R$83,MATCH($X75,$D$72:$D$83,0),MATCH(AC$67,$G$70:$R$70,0)), IFERROR(INDEX($G$72:$R$83,MATCH($X75,$E$72:$E$83,0),MATCH(AC$67,$G$67:$R$67,0)), IFERROR(INDEX($G$72:$R$83,MATCH($X75,$E$72:$E$83,0),MATCH(AC$67,$G$68:$R$68,0)), IFERROR(INDEX($G$72:$R$83,MATCH($X75,$E$72:$E$83,0),MATCH(AC$67,$G$69:$R$69,0)), INDEX($G$72:$R$83,MATCH($X75,$E$72:$E$83,0),MATCH(AC$67,$G$70:$R$70,0))))))))))))))))) -> 1 | AD75: =IFERROR(INDEX($G$72:$R$83,MATCH($X75,$B$72:$B$83,0),MATCH(AD$67,$G$67:$R$67,0)), IFERROR(INDEX($G$72:$R$83,MATCH($X75,$B$72:$B$83,0),MATCH(AD$67,$G$68:$R$68,0)), IFERROR(INDEX($G$72:$R$83,MATCH($X75,$B$72:$B$83,0),MATCH(AD$67,$G$69:$R$69,0)), IFERROR(INDEX($G$72:$R$83,MATCH($X75,$B$72:$B$83,0),MATCH(AD$67,$G$70:$R$70,0)), IFERROR(INDEX($G$72:$R$83,MATCH($X75,$C$72:$C$83,0),MATCH(AD$67,$G$67:$R$67,0)), IFERROR(INDEX($G$72:$R$83,MATCH($X75,$C$72:$C$83,0),MATCH(AD$67,$G$68:$R$68,0)), IFERROR(INDEX($G$72:$R$83,MATCH($X75,$C$72:$C$83,0),MATCH(AD$67,$G$69:$R$69,0)), IFERROR(INDEX($G$72:$R$83,MATCH($X75,$C$72:$C$83,0),MATCH(AD$67,$G$70:$R$70,0)), IFERROR(INDEX($G$72:$R$83,MATCH($X75,$D$72:$D$83,0),MATCH(AD$67,$G$67:$R$67,0)), IFERROR(INDEX($G$72:$R$83,MATCH($X75,$D$72:$D$83,0),MATCH(AD$67,$G$68:$R$68,0)), IFERROR(INDEX($G$72:$R$83,MATCH($X75,$D$72:$D$83,0),MATCH(AD$67,$G$69:$R$69,0)), IFERROR(INDEX($G$72:$R$83,MATCH($X75,$D$72:$D$83,0),MATCH(AD$67,$G$70:$R$70,0)), IFERROR(INDEX($G$72:$R$83,MATCH($X75,$E$72:$E$83,0),MATCH(AD$67,$G$67:$R$67,0)), IFERROR(INDEX($G$72:$R$83,MATCH($X75,$E$72:$E$83,0),MATCH(AD$67,$G$68:$R$68,0)), IFERROR(INDEX($G$72:$R$83,MATCH($X75,$E$72:$E$83,0),MATCH(AD$67,$G$69:$R$69,0)), INDEX($G$72:$R$83,MATCH($X75,$E$72:$E$83,0),MATCH(AD$67,$G$70:$R$70,0))))))))))))))))) -> 1 | AE75: =IFERROR(INDEX($G$72:$R$83,MATCH($X75,$B$72:$B$83,0),MATCH(AE$67,$G$67:$R$67,0)), IFERROR(INDEX($G$72:$R$83,MATCH($X75,$B$72:$B$83,0),MATCH(AE$67,$G$68:$R$68,0)), IFERROR(INDEX($G$72:$R$83,MATCH($X75,$B$72:$B$83,0),MATCH(AE$67,$G$69:$R$69,0)), IFERROR(INDEX($G$72:$R$83,MATCH($X75,$B$72:$B$83,0),MATCH(AE$67,$G$70:$R$70,0)), IFERROR(INDEX($G$72:$R$83,MATCH($X75,$C$72:$C$83,0),MATCH(AE$67,$G$67:$R$67,0)), IFERROR(INDEX($G$72:$R$83,MATCH($X75,$C$72:$C$83,0),MATCH(AE$67,$G$68:$R$68,0)), IFERROR(INDEX($G$72:$R$83,MATCH($X75,$C$72:$C$83,0),MATCH(AE$67,$G$69:$R$69,0)), IFERROR(INDEX($G$72:$R$83,MATCH($X75,$C$72:$C$83,0),MATCH(AE$67,$G$70:$R$70,0)), IFERROR(INDEX($G$72:$R$83,MATCH($X75,$D$72:$D$83,0),MATCH(AE$67,$G$67:$R$67,0)), IFERROR(INDEX($G$72:$R$83,MATCH($X75,$D$72:$D$83,0),MATCH(AE$67,$G$68:$R$68,0)), IFERROR(INDEX($G$72:$R$83,MATCH($X75,$D$72:$D$83,0),MATCH(AE$67,$G$69:$R$69,0)), IFERROR(INDEX($G$72:$R$83,MATCH($X75,$D$72:$D$83,0),MATCH(AE$67,$G$70:$R$70,0)), IFERROR(INDEX($G$72:$R$83,MATCH($X75,$E$72:$E$83,0),MATCH(AE$67,$G$67:$R$67,0)), IFERROR(INDEX($G$72:$R$83,MATCH($X75,$E$72:$E$83,0),MATCH(AE$67,$G$68:$R$68,0)), IFERROR(INDEX($G$72:$R$83,MATCH($X75,$E$72:$E$83,0),MATCH(AE$67,$G$69:$R$69,0)), INDEX($G$72:$R$83,MATCH($X75,$E$72:$E$83,0),MATCH(AE$67,$G$70:$R$70,0))))))))))))))))) -> 1 | AF75: =IFERROR(INDEX($G$72:$R$83,MATCH($X75,$B$72:$B$83,0),MATCH(AF$67,$G$67:$R$67,0)), IFERROR(INDEX($G$72:$R$83,MATCH($X75,$B$72:$B$83,0),MATCH(AF$67,$G$68:$R$68,0)), IFERROR(INDEX($G$72:$R$83,MATCH($X75,$B$72:$B$83,0),MATCH(AF$67,$G$69:$R$69,0)), IFERROR(INDEX($G$72:$R$83,MATCH($X75,$B$72:$B$83,0),MATCH(AF$67,$G$70:$R$70,0)), IFERROR(INDEX($G$72:$R$83,MATCH($X75,$C$72:$C$83,0),MATCH(AF$67,$G$67:$R$67,0)), IFERROR(INDEX($G$72:$R$83,MATCH($X75,$C$72:$C$83,0),MATCH(AF$67,$G$68:$R$68,0)), IFERROR(INDEX($G$72:$R$83,MATCH($X75,$C$72:$C$83,0),MATCH(AF$67,$G$69:$R$69,0)), IFERROR(INDEX($G$72:$R$83,MATCH($X75,$C$72:$C$83,0),MATCH(AF$67,$G$70:$R$70,0)), IFERROR(INDEX($G$72:$R$83,MATCH($X75,$D$72:$D$83,0),MATCH(AF$67,$G$67:$R$67,0)), IFERROR(INDEX($G$72:$R$83,MATCH($X75,$D$72:$D$83,0),MATCH(AF$67,$G$68:$R$68,0)), IFERROR(INDEX($G$72:$R$83,MATCH($X75,$D$72:$D$83,0),MATCH(AF$67,$G$69:$R$69,0)), IFERROR(INDEX($G$72:$R$83,MATCH($X75,$D$72:$D$83,0),MATCH(AF$67,$G$70:$R$70,0)), IFERROR(INDEX($G$72:$R$83,MATCH($X75,$E$72:$E$83,0),MATCH(AF$67,$G$67:$R$67,0)), IFERROR(INDEX($G$72:$R$83,MATCH($X75,$E$72:$E$83,0),MATCH(AF$67,$G$68:$R$68,0)), IFERROR(INDEX($G$72:$R$83,MATCH($X75,$E$72:$E$83,0),MATCH(AF$67,$G$69:$R$69,0)), INDEX($G$72:$R$83,MATCH($X75,$E$72:$E$83,0),MATCH(AF$67,$G$70:$R$70,0))))))))))))))))) -> 1 | ... AS75: =IFERROR(INDEX($G$72:$R$83,MATCH($X75,$B$72:$B$83,0),MATCH(AS$67,$G$67:$R$67,0)), IFERROR(INDEX($G$72:$R$83,MATCH($X75,$B$72:$B$83,0),MATCH(AS$67,$G$68:$R$68,0)), IFERROR(INDEX($G$72:$R$83,MATCH($X75,$B$72:$B$83,0),MATCH(AS$67,$G$69:$R$69,0)), IFERROR(INDEX($G$72:$R$83,MATCH($X75,$B$72:$B$83,0),MATCH(AS$67,$G$70:$R$70,0)), IFERROR(INDEX($G$72:$R$83,MATCH($X75,$C$72:$C$83,0),MATCH(AS$67,$G$67:$R$67,0)), IFERROR(INDEX($G$72:$R$83,MATCH($X75,$C$72:$C$83,0),MATCH(AS$67,$G$68:$R$68,0)), IFERROR(INDEX($G$72:$R$83,MATCH($X75,$C$72:$C$83,0),MATCH(AS$67,$G$69:$R$69,0)), IFERROR(INDEX($G$72:$R$83,MATCH($X75,$C$72:$C$83,0),MATCH(AS$67,$G$70:$R$70,0)), IFERROR(INDEX($G$72:$R$83,MATCH($X75,$D$72:$D$83,0),MATCH(AS$67,$G$67:$R$67,0)), IFERROR(INDEX($G$72:$R$83,MATCH($X75,$D$72:$D$83,0),MATCH(AS$67,$G$68:$R$68,0)), IFERROR(INDEX($G$72:$R$83,MATCH($X75,$D$72:$D$83,0),MATCH(AS$67,$G$69:$R$69,0)), IFERROR(INDEX($G$72:$R$83,MATCH($X75,$D$72:$D$83,0),MATCH(AS$67,$G$70:$R$70,0)), IFERROR(INDEX($G$72:$R$83,MATCH($X75,$E$72:$E$83,0),MATCH(AS$67,$G$67:$R$67,0)), IFERROR(INDEX($G$72:$R$83,MATCH($X75,$E$72:$E$83,0),MATCH(AS$67,$G$68:$R$68,0)), IFERROR(INDEX($G$72:$R$83,MATCH($X75,$E$72:$E$83,0),MATCH(AS$67,$G$69:$R$69,0)), INDEX($G$72:$R$83,MATCH($X75,$E$72:$E$83,0),MATCH(AS$67,$G$70:$R$70,0))))))))))))))))) -> 0
B76: US Public Corporates, HY Intermediate | C76: US Public Corporates, HY Long | F76: U.S. High Yield Bonds | G76: -0.02 | H76: 0 | I76: 0.38 | J76: 0.66 | K76: 1 | L76: 0.77 | M76: 0.19 | N76: 0.42 | O76: 0.35 | P76: 0.49 | Q76: 0.72 | R76: 0.67 | X76: US Public Corporates, HY Intermediate | Y76: =IFERROR(INDEX($G$72:$R$83,MATCH($X76,$B$72:$B$83,0),MATCH(Y$67,$G$67:$R$67,0)), IFERROR(INDEX($G$72:$R$83,MATCH($X76,$B$72:$B$83,0),MATCH(Y$67,$G$68:$R$68,0)), IFERROR(INDEX($G$72:$R$83,MATCH($X76,$B$72:$B$83,0),MATCH(Y$67,$G$69:$R$69,0)), IFERROR(INDEX($G$72:$R$83,MATCH($X76,$B$72:$B$83,0),MATCH(Y$67,$G$70:$R$70,0)), IFERROR(INDEX($G$72:$R$83,MATCH($X76,$C$72:$C$83,0),MATCH(Y$67,$G$67:$R$67,0)), IFERROR(INDEX($G$72:$R$83,MATCH($X76,$C$72:$C$83,0),MATCH(Y$67,$G$68:$R$68,0)), IFERROR(INDEX($G$72:$R$83,MATCH($X76,$C$72:$C$83,0),MATCH(Y$67,$G$69:$R$69,0)), IFERROR(INDEX($G$72:$R$83,MATCH($X76,$C$72:$C$83,0),MATCH(Y$67,$G$70:$R$70,0)), IFERROR(INDEX($G$72:$R$83,MATCH($X76,$D$72:$D$83,0),MATCH(Y$67,$G$67:$R$67,0)), IFERROR(INDEX($G$72:$R$83,MATCH($X76,$D$72:$D$83,0),MATCH(Y$67,$G$68:$R$68,0)), IFERROR(INDEX($G$72:$R$83,MATCH($X76,$D$72:$D$83,0),MATCH(Y$67,$G$69:$R$69,0)), IFERROR(INDEX($G$72:$R$83,MATCH($X76,$D$72:$D$83,0),MATCH(Y$67,$G$70:$R$70,0)), IFERROR(INDEX($G$72:$R$83,MATCH($X76,$E$72:$E$83,0),MATCH(Y$67,$G$67:$R$67,0)), IFERROR(INDEX($G$72:$R$83,MATCH($X76,$E$72:$E$83,0),MATCH(Y$67,$G$68:$R$68,0)), IFERROR(INDEX($G$72:$R$83,MATCH($X76,$E$72:$E$83,0),MATCH(Y$67,$G$69:$R$69,0)), INDEX($G$72:$R$83,MATCH($X76,$E$72:$E$83,0),MATCH(Y$67,$G$70:$R$70,0))))))))))))))))) -> -0.02 | Z76: =IFERROR(INDEX($G$72:$R$83,MATCH($X76,$B$72:$B$83,0),MATCH(Z$67,$G$67:$R$67,0)), IFERROR(INDEX($G$72:$R$83,MATCH($X76,$B$72:$B$83,0),MATCH(Z$67,$G$68:$R$68,0)), IFERROR(INDEX($G$72:$R$83,MATCH($X76,$B$72:$B$83,0),MATCH(Z$67,$G$69:$R$69,0)), IFERROR(INDEX($G$72:$R$83,MATCH($X76,$B$72:$B$83,0),MATCH(Z$67,$G$70:$R$70,0)), IFERROR(INDEX($G$72:$R$83,MATCH($X76,$C$72:$C$83,0),MATCH(Z$67,$G$67:$R$67,0)), IFERROR(INDEX($G$72:$R$83,MATCH($X76,$C$72:$C$83,0),MATCH(Z$67,$G$68:$R$68,0)), IFERROR(INDEX($G$72:$R$83,MATCH($X76,$C$72:$C$83,0),MATCH(Z$67,$G$69:$R$69,0)), IFERROR(INDEX($G$72:$R$83,MATCH($X76,$C$72:$C$83,0),MATCH(Z$67,$G$70:$R$70,0)), IFERROR(INDEX($G$72:$R$83,MATCH($X76,$D$72:$D$83,0),MATCH(Z$67,$G$67:$R$67,0)), IFERROR(INDEX($G$72:$R$83,MATCH($X76,$D$72:$D$83,0),MATCH(Z$67,$G$68:$R$68,0)), IFERROR(INDEX($G$72:$R$83,MATCH($X76,$D$72:$D$83,0),MATCH(Z$67,$G$69:$R$69,0)), IFERROR(INDEX($G$72:$R$83,MATCH($X76,$D$72:$D$83,0),MATCH(Z$67,$G$70:$R$70,0)), IFERROR(INDEX($G$72:$R$83,MATCH($X76,$E$72:$E$83,0),MATCH(Z$67,$G$67:$R$67,0)), IFERROR(INDEX($G$72:$R$83,MATCH($X76,$E$72:$E$83,0),MATCH(Z$67,$G$68:$R$68,0)), IFERROR(INDEX($G$72:$R$83,MATCH($X76,$E$72:$E$83,0),MATCH(Z$67,$G$69:$R$69,0)), INDEX($G$72:$R$83,MATCH($X76,$E$72:$E$83,0),MATCH(Z$67,$G$70:$R$70,0))))))))))))))))) -> 0 | AA76: =IFERROR(INDEX($G$72:$R$83,MATCH($X76,$B$72:$B$83,0),MATCH(AA$67,$G$67:$R$67,0)), IFERROR(INDEX($G$72:$R$83,MATCH($X76,$B$72:$B$83,0),MATCH(AA$67,$G$68:$R$68,0)), IFERROR(INDEX($G$72:$R$83,MATCH($X76,$B$72:$B$83,0),MATCH(AA$67,$G$69:$R$69,0)), IFERROR(INDEX($G$72:$R$83,MATCH($X76,$B$72:$B$83,0),MATCH(AA$67,$G$70:$R$70,0)), IFERROR(INDEX($G$72:$R$83,MATCH($X76,$C$72:$C$83,0),MATCH(AA$67,$G$67:$R$67,0)), IFERROR(INDEX($G$72:$R$83,MATCH($X76,$C$72:$C$83,0),MATCH(AA$67,$G$68:$R$68,0)), IFERROR(INDEX($G$72:$R$83,MATCH($X76,$C$72:$C$83,0),MATCH(AA$67,$G$69:$R$69,0)), IFERROR(INDEX($G$72:$R$83,MATCH($X76,$C$72:$C$83,0),MATCH(AA$67,$G$70:$R$70,0)), IFERROR(INDEX($G$72:$R$83,MATCH($X76,$D$72:$D$83,0),MATCH(AA$67,$G$67:$R$67,0)), IFERROR(INDEX($G$72:$R$83,MATCH($X76,$D$72:$D$83,0),MATCH(AA$67,$G$68:$R$68,0)), IFERROR(INDEX($G$72:$R$83,MATCH($X76,$D$72:$D$83,0),MATCH(AA$67,$G$69:$R$69,0)), IFERROR(INDEX($G$72:$R$83,MATCH($X76,$D$72:$D$83,0),MATCH(AA$67,$G$70:$R$70,0)), IFERROR(INDEX($G$72:$R$83,MATCH($X76,$E$72:$E$83,0),MATCH(AA$67,$G$67:$R$67,0)), IFERROR(INDEX($G$72:$R$83,MATCH($X76,$E$72:$E$83,0),MATCH(AA$67,$G$68:$R$68,0)), IFERROR(INDEX($G$72:$R$83,MATCH($X76,$E$72:$E$83,0),MATCH(AA$67,$G$69:$R$69,0)), INDEX($G$72:$R$83,MATCH($X76,$E$72:$E$83,0),MATCH(AA$67,$G$70:$R$70,0))))))))))))))))) -> 0.42 | AB76: =IFERROR(INDEX($G$72:$R$83,MATCH($X76,$B$72:$B$83,0),MATCH(AB$67,$G$67:$R$67,0)), IFERROR(INDEX($G$72:$R$83,MATCH($X76,$B$72:$B$83,0),MATCH(AB$67,$G$68:$R$68,0)), IFERROR(INDEX($G$72:$R$83,MATCH($X76,$B$72:$B$83,0),MATCH(AB$67,$G$69:$R$69,0)), IFERROR(INDEX($G$72:$R$83,MATCH($X76,$B$72:$B$83,0),MATCH(AB$67,$G$70:$R$70,0)), IFERROR(INDEX($G$72:$R$83,MATCH($X76,$C$72:$C$83,0),MATCH(AB$67,$G$67:$R$67,0)), IFERROR(INDEX($G$72:$R$83,MATCH($X76,$C$72:$C$83,0),MATCH(AB$67,$G$68:$R$68,0)), IFERROR(INDEX($G$72:$R$83,MATCH($X76,$C$72:$C$83,0),MATCH(AB$67,$G$69:$R$69,0)), IFERROR(INDEX($G$72:$R$83,MATCH($X76,$C$72:$C$83,0),MATCH(AB$67,$G$70:$R$70,0)), IFERROR(INDEX($G$72:$R$83,MATCH($X76,$D$72:$D$83,0),MATCH(AB$67,$G$67:$R$67,0)), IFERROR(INDEX($G$72:$R$83,MATCH($X76,$D$72:$D$83,0),MATCH(AB$67,$G$68:$R$68,0)), IFERROR(INDEX($G$72:$R$83,MATCH($X76,$D$72:$D$83,0),MATCH(AB$67,$G$69:$R$69,0)), IFERROR(INDEX($G$72:$R$83,MATCH($X76,$D$72:$D$83,0),MATCH(AB$67,$G$70:$R$70,0)), IFERROR(INDEX($G$72:$R$83,MATCH($X76,$E$72:$E$83,0),MATCH(AB$67,$G$67:$R$67,0)), IFERROR(INDEX($G$72:$R$83,MATCH($X76,$E$72:$E$83,0),MATCH(AB$67,$G$68:$R$68,0)), IFERROR(INDEX($G$72:$R$83,MATCH($X76,$E$72:$E$83,0),MATCH(AB$67,$G$69:$R$69,0)), INDEX($G$72:$R$83,MATCH($X76,$E$72:$E$83,0),MATCH(AB$67,$G$70:$R$70,0))))))))))))))))) -> 0.19 | AC76: =IFERROR(INDEX($G$72:$R$83,MATCH($X76,$B$72:$B$83,0),MATCH(AC$67,$G$67:$R$67,0)), IFERROR(INDEX($G$72:$R$83,MATCH($X76,$B$72:$B$83,0),MATCH(AC$67,$G$68:$R$68,0)), IFERROR(INDEX($G$72:$R$83,MATCH($X76,$B$72:$B$83,0),MATCH(AC$67,$G$69:$R$69,0)), IFERROR(INDEX($G$72:$R$83,MATCH($X76,$B$72:$B$83,0),MATCH(AC$67,$G$70:$R$70,0)), IFERROR(INDEX($G$72:$R$83,MATCH($X76,$C$72:$C$83,0),MATCH(AC$67,$G$67:$R$67,0)), IFERROR(INDEX($G$72:$R$83,MATCH($X76,$C$72:$C$83,0),MATCH(AC$67,$G$68:$R$68,0)), IFERROR(INDEX($G$72:$R$83,MATCH($X76,$C$72:$C$83,0),MATCH(AC$67,$G$69:$R$69,0)), IFERROR(INDEX($G$72:$R$83,MATCH($X76,$C$72:$C$83,0),MATCH(AC$67,$G$70:$R$70,0)), IFERROR(INDEX($G$72:$R$83,MATCH($X76,$D$72:$D$83,0),MATCH(AC$67,$G$67:$R$67,0)), IFERROR(INDEX($G$72:$R$83,MATCH($X76,$D$72:$D$83,0),MATCH(AC$67,$G$68:$R$68,0)), IFERROR(INDEX($G$72:$R$83,MATCH($X76,$D$72:$D$83,0),MATCH(AC$67,$G$69:$R$69,0)), IFERROR(INDEX($G$72:$R$83,MATCH($X76,$D$72:$D$83,0),MATCH(AC$67,$G$70:$R$70,0)), IFERROR(INDEX($G$72:$R$83,MATCH($X76,$E$72:$E$83,0),MATCH(AC$67,$G$67:$R$67,0)), IFERROR(INDEX($G$72:$R$83,MATCH($X76,$E$72:$E$83,0),MATCH(AC$67,$G$68:$R$68,0)), IFERROR(INDEX($G$72:$R$83,MATCH($X76,$E$72:$E$83,0),MATCH(AC$67,$G$69:$R$69,0)), INDEX($G$72:$R$83,MATCH($X76,$E$72:$E$83,0),MATCH(AC$67,$G$70:$R$70,0))))))))))))))))) -> 0.66 | AD76: =IFERROR(INDEX($G$72:$R$83,MATCH($X76,$B$72:$B$83,0),MATCH(AD$67,$G$67:$R$67,0)), IFERROR(INDEX($G$72:$R$83,MATCH($X76,$B$72:$B$83,0),MATCH(AD$67,$G$68:$R$68,0)), IFERROR(INDEX($G$72:$R$83,MATCH($X76,$B$72:$B$83,0),MATCH(AD$67,$G$69:$R$69,0)), IFERROR(INDEX($G$72:$R$83,MATCH($X76,$B$72:$B$83,0),MATCH(AD$67,$G$70:$R$70,0)), IFERROR(INDEX($G$72:$R$83,MATCH($X76,$C$72:$C$83,0),MATCH(AD$67,$G$67:$R$67,0)), IFERROR(INDEX($G$72:$R$83,MATCH($X76,$C$72:$C$83,0),MATCH(AD$67,$G$68:$R$68,0)), IFERROR(INDEX($G$72:$R$83,MATCH($X76,$C$72:$C$83,0),MATCH(AD$67,$G$69:$R$69,0)), IFERROR(INDEX($G$72:$R$83,MATCH($X76,$C$72:$C$83,0),MATCH(AD$67,$G$70:$R$70,0)), IFERROR(INDEX($G$72:$R$83,MATCH($X76,$D$72:$D$83,0),MATCH(AD$67,$G$67:$R$67,0)), IFERROR(INDEX($G$72:$R$83,MATCH($X76,$D$72:$D$83,0),MATCH(AD$67,$G$68:$R$68,0)), IFERROR(INDEX($G$72:$R$83,MATCH($X76,$D$72:$D$83,0),MATCH(AD$67,$G$69:$R$69,0)), IFERROR(INDEX($G$72:$R$83,MATCH($X76,$D$72:$D$83,0),MATCH(AD$67,$G$70:$R$70,0)), IFERROR(INDEX($G$72:$R$83,MATCH($X76,$E$72:$E$83,0),MATCH(AD$67,$G$67:$R$67,0)), IFERROR(INDEX($G$72:$R$83,MATCH($X76,$E$72:$E$83,0),MATCH(AD$67,$G$68:$R$68,0)), IFERROR(INDEX($G$72:$R$83,MATCH($X76,$E$72:$E$83,0),MATCH(AD$67,$G$69:$R$69,0)), INDEX($G$72:$R$83,MATCH($X76,$E$72:$E$83,0),MATCH(AD$67,$G$70:$R$70,0))))))))))))))))) -> 0.66 | AE76: =IFERROR(INDEX($G$72:$R$83,MATCH($X76,$B$72:$B$83,0),MATCH(AE$67,$G$67:$R$67,0)), IFERROR(INDEX($G$72:$R$83,MATCH($X76,$B$72:$B$83,0),MATCH(AE$67,$G$68:$R$68,0)), IFERROR(INDEX($G$72:$R$83,MATCH($X76,$B$72:$B$83,0),MATCH(AE$67,$G$69:$R$69,0)), IFERROR(INDEX($G$72:$R$83,MATCH($X76,$B$72:$B$83,0),MATCH(AE$67,$G$70:$R$70,0)), IFERROR(INDEX($G$72:$R$83,MATCH($X76,$C$72:$C$83,0),MATCH(AE$67,$G$67:$R$67,0)), IFERROR(INDEX($G$72:$R$83,MATCH($X76,$C$72:$C$83,0),MATCH(AE$67,$G$68:$R$68,0)), IFERROR(INDEX($G$72:$R$83,MATCH($X76,$C$72:$C$83,0),MATCH(AE$67,$G$69:$R$69,0)), IFERROR(INDEX($G$72:$R$83,MATCH($X76,$C$72:$C$83,0),MATCH(AE$67,$G$70:$R$70,0)), IFERROR(INDEX($G$72:$R$83,MATCH($X76,$D$72:$D$83,0),MATCH(AE$67,$G$67:$R$67,0)), IFERROR(INDEX($G$72:$R$83,MATCH($X76,$D$72:$D$83,0),MATCH(AE$67,$G$68:$R$68,0)), IFERROR(INDEX($G$72:$R$83,MATCH($X76,$D$72:$D$83,0),MATCH(AE$67,$G$69:$R$69,0)), IFERROR(INDEX($G$72:$R$83,MATCH($X76,$D$72:$D$83,0),MATCH(AE$67,$G$70:$R$70,0)), IFERROR(INDEX($G$72:$R$83,MATCH($X76,$E$72:$E$83,0),MATCH(AE$67,$G$67:$R$67,0)), IFERROR(INDEX($G$72:$R$83,MATCH($X76,$E$72:$E$83,0),MATCH(AE$67,$G$68:$R$68,0)), IFERROR(INDEX($G$72:$R$83,MATCH($X76,$E$72:$E$83,0),MATCH(AE$67,$G$69:$R$69,0)), INDEX($G$72:$R$83,MATCH($X76,$E$72:$E$83,0),MATCH(AE$67,$G$70:$R$70,0))))))))))))))))) -> 0.66 | AF76: =IFERROR(INDEX($G$72:$R$83,MATCH($X76,$B$72:$B$83,0),MATCH(AF$67,$G$67:$R$67,0)), IFERROR(INDEX($G$72:$R$83,MATCH($X76,$B$72:$B$83,0),MATCH(AF$67,$G$68:$R$68,0)), IFERROR(INDEX($G$72:$R$83,MATCH($X76,$B$72:$B$83,0),MATCH(AF$67,$G$69:$R$69,0)), IFERROR(INDEX($G$72:$R$83,MATCH($X76,$B$72:$B$83,0),MATCH(AF$67,$G$70:$R$70,0)), IFERROR(INDEX($G$72:$R$83,MATCH($X76,$C$72:$C$83,0),MATCH(AF$67,$G$67:$R$67,0)), IFERROR(INDEX($G$72:$R$83,MATCH($X76,$C$72:$C$83,0),MATCH(AF$67,$G$68:$R$68,0)), IFERROR(INDEX($G$72:$R$83,MATCH($X76,$C$72:$C$83,0),MATCH(AF$67,$G$69:$R$69,0)), IFERROR(INDEX($G$72:$R$83,MATCH($X76,$C$72:$C$83,0),MATCH(AF$67,$G$70:$R$70,0)), IFERROR(INDEX($G$72:$R$83,MATCH($X76,$D$72:$D$83,0),MATCH(AF$67,$G$67:$R$67,0)), IFERROR(INDEX($G$72:$R$83,MATCH($X76,$D$72:$D$83,0),MATCH(AF$67,$G$68:$R$68,0)), IFERROR(INDEX($G$72:$R$83,MATCH($X76,$D$72:$D$83,0),MATCH(AF$67,$G$69:$R$69,0)), IFERROR(INDEX($G$72:$R$83,MATCH($X76,$D$72:$D$83,0),MATCH(AF$67,$G$70:$R$70,0)), IFERROR(INDEX($G$72:$R$83,MATCH($X76,$E$72:$E$83,0),MATCH(AF$67,$G$67:$R$67,0)), IFERROR(INDEX($G$72:$R$83,MATCH($X76,$E$72:$E$83,0),MATCH(AF$67,$G$68:$R$68,0)), IFERROR(INDEX($G$72:$R$83,MATCH($X76,$E$72:$E$83,0),MATCH(AF$67,$G$69:$R$69,0)), INDEX($G$72:$R$83,MATCH($X76,$E$72:$E$83,0),MATCH(AF$67,$G$70:$R$70,0))))))))))))))))) -> 0.66 | ... AS76: =IFERROR(INDEX($G$72:$R$83,MATCH($X76,$B$72:$B$83,0),MATCH(AS$67,$G$67:$R$67,0)), IFERROR(INDEX($G$72:$R$83,MATCH($X76,$B$72:$B$83,0),MATCH(AS$67,$G$68:$R$68,0)), IFERROR(INDEX($G$72:$R$83,MATCH($X76,$B$72:$B$83,0),MATCH(AS$67,$G$69:$R$69,0)), IFERROR(INDEX($G$72:$R$83,MATCH($X76,$B$72:$B$83,0),MATCH(AS$67,$G$70:$R$70,0)), IFERROR(INDEX($G$72:$R$83,MATCH($X76,$C$72:$C$83,0),MATCH(AS$67,$G$67:$R$67,0)), IFERROR(INDEX($G$72:$R$83,MATCH($X76,$C$72:$C$83,0),MATCH(AS$67,$G$68:$R$68,0)), IFERROR(INDEX($G$72:$R$83,MATCH($X76,$C$72:$C$83,0),MATCH(AS$67,$G$69:$R$69,0)), IFERROR(INDEX($G$72:$R$83,MATCH($X76,$C$72:$C$83,0),MATCH(AS$67,$G$70:$R$70,0)), IFERROR(INDEX($G$72:$R$83,MATCH($X76,$D$72:$D$83,0),MATCH(AS$67,$G$67:$R$67,0)), IFERROR(INDEX($G$72:$R$83,MATCH($X76,$D$72:$D$83,0),MATCH(AS$67,$G$68:$R$68,0)), IFERROR(INDEX($G$72:$R$83,MATCH($X76,$D$72:$D$83,0),MATCH(AS$67,$G$69:$R$69,0)), IFERROR(INDEX($G$72:$R$83,MATCH($X76,$D$72:$D$83,0),MATCH(AS$67,$G$70:$R$70,0)), IFERROR(INDEX($G$72:$R$83,MATCH($X76,$E$72:$E$83,0),MATCH(AS$67,$G$67:$R$67,0)), IFERROR(INDEX($G$72:$R$83,MATCH($X76,$E$72:$E$83,0),MATCH(AS$67,$G$68:$R$68,0)), IFERROR(INDEX($G$72:$R$83,MATCH($X76,$E$72:$E$83,0),MATCH(AS$67,$G$69:$R$69,0)), INDEX($G$72:$R$83,MATCH($X76,$E$72:$E$83,0),MATCH(AS$67,$G$70:$R$70,0))))))))))))))))) -> 0.35
B77: Corporate HY Private (Leveraged Loans) | F77: U.S. Leveraged Loans | G77: -0.37 | H77: 0.28 | I77: 0.04 | J77: 0.36 | K77: 0.77 | L77: 1 | M77: -0.1 | N77: 0.18 | O77: 0.44 | P77: 0.43 | Q77: 0.68 | R77: 0.67 | X77: US Public Corporates, HY Long | Y77: =IFERROR(INDEX($G$72:$R$83,MATCH($X77,$B$72:$B$83,0),MATCH(Y$67,$G$67:$R$67,0)), IFERROR(INDEX($G$72:$R$83,MATCH($X77,$B$72:$B$83,0),MATCH(Y$67,$G$68:$R$68,0)), IFERROR(INDEX($G$72:$R$83,MATCH($X77,$B$72:$B$83,0),MATCH(Y$67,$G$69:$R$69,0)), IFERROR(INDEX($G$72:$R$83,MATCH($X77,$B$72:$B$83,0),MATCH(Y$67,$G$70:$R$70,0)), IFERROR(INDEX($G$72:$R$83,MATCH($X77,$C$72:$C$83,0),MATCH(Y$67,$G$67:$R$67,0)), IFERROR(INDEX($G$72:$R$83,MATCH($X77,$C$72:$C$83,0),MATCH(Y$67,$G$68:$R$68,0)), IFERROR(INDEX($G$72:$R$83,MATCH($X77,$C$72:$C$83,0),MATCH(Y$67,$G$69:$R$69,0)), IFERROR(INDEX($G$72:$R$83,MATCH($X77,$C$72:$C$83,0),MATCH(Y$67,$G$70:$R$70,0)), IFERROR(INDEX($G$72:$R$83,MATCH($X77,$D$72:$D$83,0),MATCH(Y$67,$G$67:$R$67,0)), IFERROR(INDEX($G$72:$R$83,MATCH($X77,$D$72:$D$83,0),MATCH(Y$67,$G$68:$R$68,0)), IFERROR(INDEX($G$72:$R$83,MATCH($X77,$D$72:$D$83,0),MATCH(Y$67,$G$69:$R$69,0)), IFERROR(INDEX($G$72:$R$83,MATCH($X77,$D$72:$D$83,0),MATCH(Y$67,$G$70:$R$70,0)), IFERROR(INDEX($G$72:$R$83,MATCH($X77,$E$72:$E$83,0),MATCH(Y$67,$G$67:$R$67,0)), IFERROR(INDEX($G$72:$R$83,MATCH($X77,$E$72:$E$83,0),MATCH(Y$67,$G$68:$R$68,0)), IFERROR(INDEX($G$72:$R$83,MATCH($X77,$E$72:$E$83,0),MATCH(Y$67,$G$69:$R$69,0)), INDEX($G$72:$R$83,MATCH($X77,$E$72:$E$83,0),MATCH(Y$67,$G$70:$R$70,0))))))))))))))))) -> -0.02 | Z77: =IFERROR(INDEX($G$72:$R$83,MATCH($X77,$B$72:$B$83,0),MATCH(Z$67,$G$67:$R$67,0)), IFERROR(INDEX($G$72:$R$83,MATCH($X77,$B$72:$B$83,0),MATCH(Z$67,$G$68:$R$68,0)), IFERROR(INDEX($G$72:$R$83,MATCH($X77,$B$72:$B$83,0),MATCH(Z$67,$G$69:$R$69,0)), IFERROR(INDEX($G$72:$R$83,MATCH($X77,$B$72:$B$83,0),MATCH(Z$67,$G$70:$R$70,0)), IFERROR(INDEX($G$72:$R$83,MATCH($X77,$C$72:$C$83,0),MATCH(Z$67,$G$67:$R$67,0)), IFERROR(INDEX($G$72:$R$83,MATCH($X77,$C$72:$C$83,0),MATCH(Z$67,$G$68:$R$68,0)), IFERROR(INDEX($G$72:$R$83,MATCH($X77,$C$72:$C$83,0),MATCH(Z$67,$G$69:$R$69,0)), IFERROR(INDEX($G$72:$R$83,MATCH($X77,$C$72:$C$83,0),MATCH(Z$67,$G$70:$R$70,0)), IFERROR(INDEX($G$72:$R$83,MATCH($X77,$D$72:$D$83,0),MATCH(Z$67,$G$67:$R$67,0)), IFERROR(INDEX($G$72:$R$83,MATCH($X77,$D$72:$D$83,0),MATCH(Z$67,$G$68:$R$68,0)), IFERROR(INDEX($G$72:$R$83,MATCH($X77,$D$72:$D$83,0),MATCH(Z$67,$G$69:$R$69,0)), IFERROR(INDEX($G$72:$R$83,MATCH($X77,$D$72:$D$83,0),MATCH(Z$67,$G$70:$R$70,0)), IFERROR(INDEX($G$72:$R$83,MATCH($X77,$E$72:$E$83,0),MATCH(Z$67,$G$67:$R$67,0)), IFERROR(INDEX($G$72:$R$83,MATCH($X77,$E$72:$E$83,0),MATCH(Z$67,$G$68:$R$68,0)), IFERROR(INDEX($G$72:$R$83,MATCH($X77,$E$72:$E$83,0),MATCH(Z$67,$G$69:$R$69,0)), INDEX($G$72:$R$83,MATCH($X77,$E$72:$E$83,0),MATCH(Z$67,$G$70:$R$70,0))))))))))))))))) -> 0 | AA77: =IFERROR(INDEX($G$72:$R$83,MATCH($X77,$B$72:$B$83,0),MATCH(AA$67,$G$67:$R$67,0)), IFERROR(INDEX($G$72:$R$83,MATCH($X77,$B$72:$B$83,0),MATCH(AA$67,$G$68:$R$68,0)), IFERROR(INDEX($G$72:$R$83,MATCH($X77,$B$72:$B$83,0),MATCH(AA$67,$G$69:$R$69,0)), IFERROR(INDEX($G$72:$R$83,MATCH($X77,$B$72:$B$83,0),MATCH(AA$67,$G$70:$R$70,0)), IFERROR(INDEX($G$72:$R$83,MATCH($X77,$C$72:$C$83,0),MATCH(AA$67,$G$67:$R$67,0)), IFERROR(INDEX($G$72:$R$83,MATCH($X77,$C$72:$C$83,0),MATCH(AA$67,$G$68:$R$68,0)), IFERROR(INDEX($G$72:$R$83,MATCH($X77,$C$72:$C$83,0),MATCH(AA$67,$G$69:$R$69,0)), IFERROR(INDEX($G$72:$R$83,MATCH($X77,$C$72:$C$83,0),MATCH(AA$67,$G$70:$R$70,0)), IFERROR(INDEX($G$72:$R$83,MATCH($X77,$D$72:$D$83,0),MATCH(AA$67,$G$67:$R$67,0)), IFERROR(INDEX($G$72:$R$83,MATCH($X77,$D$72:$D$83,0),MATCH(AA$67,$G$68:$R$68,0)), IFERROR(INDEX($G$72:$R$83,MATCH($X77,$D$72:$D$83,0),MATCH(AA$67,$G$69:$R$69,0)), IFERROR(INDEX($G$72:$R$83,MATCH($X77,$D$72:$D$83,0),MATCH(AA$67,$G$70:$R$70,0)), IFERROR(INDEX($G$72:$R$83,MATCH($X77,$E$72:$E$83,0),MATCH(AA$67,$G$67:$R$67,0)), IFERROR(INDEX($G$72:$R$83,MATCH($X77,$E$72:$E$83,0),MATCH(AA$67,$G$68:$R$68,0)), IFERROR(INDEX($G$72:$R$83,MATCH($X77,$E$72:$E$83,0),MATCH(AA$67,$G$69:$R$69,0)), INDEX($G$72:$R$83,MATCH($X77,$E$72:$E$83,0),MATCH(AA$67,$G$70:$R$70,0))))))))))))))))) -> 0.42 | AB77: =IFERROR(INDEX($G$72:$R$83,MATCH($X77,$B$72:$B$83,0),MATCH(AB$67,$G$67:$R$67,0)), IFERROR(INDEX($G$72:$R$83,MATCH($X77,$B$72:$B$83,0),MATCH(AB$67,$G$68:$R$68,0)), IFERROR(INDEX($G$72:$R$83,MATCH($X77,$B$72:$B$83,0),MATCH(AB$67,$G$69:$R$69,0)), IFERROR(INDEX($G$72:$R$83,MATCH($X77,$B$72:$B$83,0),MATCH(AB$67,$G$70:$R$70,0)), IFERROR(INDEX($G$72:$R$83,MATCH($X77,$C$72:$C$83,0),MATCH(AB$67,$G$67:$R$67,0)), IFERROR(INDEX($G$72:$R$83,MATCH($X77,$C$72:$C$83,0),MATCH(AB$67,$G$68:$R$68,0)), IFERROR(INDEX($G$72:$R$83,MATCH($X77,$C$72:$C$83,0),MATCH(AB$67,$G$69:$R$69,0)), IFERROR(INDEX($G$72:$R$83,MATCH($X77,$C$72:$C$83,0),MATCH(AB$67,$G$70:$R$70,0)), IFERROR(INDEX($G$72:$R$83,MATCH($X77,$D$72:$D$83,0),MATCH(AB$67,$G$67:$R$67,0)), IFERROR(INDEX($G$72:$R$83,MATCH($X77,$D$72:$D$83,0),MATCH(AB$67,$G$68:$R$68,0)), IFERROR(INDEX($G$72:$R$83,MATCH($X77,$D$72:$D$83,0),MATCH(AB$67,$G$69:$R$69,0)), IFERROR(INDEX($G$72:$R$83,MATCH($X77,$D$72:$D$83,0),MATCH(AB$67,$G$70:$R$70,0)), IFERROR(INDEX($G$72:$R$83,MATCH($X77,$E$72:$E$83,0),MATCH(AB$67,$G$67:$R$67,0)), IFERROR(INDEX($G$72:$R$83,MATCH($X77,$E$72:$E$83,0),MATCH(AB$67,$G$68:$R$68,0)), IFERROR(INDEX($G$72:$R$83,MATCH($X77,$E$72:$E$83,0),MATCH(AB$67,$G$69:$R$69,0)), INDEX($G$72:$R$83,MATCH($X77,$E$72:$E$83,0),MATCH(AB$67,$G$70:$R$70,0))))))))))))))))) -> 0.19 | AC77: =IFERROR(INDEX($G$72:$R$83,MATCH($X77,$B$72:$B$83,0),MATCH(AC$67,$G$67:$R$67,0)), IFERROR(INDEX($G$72:$R$83,MATCH($X77,$B$72:$B$83,0),MATCH(AC$67,$G$68:$R$68,0)), IFERROR(INDEX($G$72:$R$83,MATCH($X77,$B$72:$B$83,0),MATCH(AC$67,$G$69:$R$69,0)), IFERROR(INDEX($G$72:$R$83,MATCH($X77,$B$72:$B$83,0),MATCH(AC$67,$G$70:$R$70,0)), IFERROR(INDEX($G$72:$R$83,MATCH($X77,$C$72:$C$83,0),MATCH(AC$67,$G$67:$R$67,0)), IFERROR(INDEX($G$72:$R$83,MATCH($X77,$C$72:$C$83,0),MATCH(AC$67,$G$68:$R$68,0)), IFERROR(INDEX($G$72:$R$83,MATCH($X77,$C$72:$C$83,0),MATCH(AC$67,$G$69:$R$69,0)), IFERROR(INDEX($G$72:$R$83,MATCH($X77,$C$72:$C$83,0),MATCH(AC$67,$G$70:$R$70,0)), IFERROR(INDEX($G$72:$R$83,MATCH($X77,$D$72:$D$83,0),MATCH(AC$67,$G$67:$R$67,0)), IFERROR(INDEX($G$72:$R$83,MATCH($X77,$D$72:$D$83,0),MATCH(AC$67,$G$68:$R$68,0)), IFERROR(INDEX($G$72:$R$83,MATCH($X77,$D$72:$D$83,0),MATCH(AC$67,$G$69:$R$69,0)), IFERROR(INDEX($G$72:$R$83,MATCH($X77,$D$72:$D$83,0),MATCH(AC$67,$G$70:$R$70,0)), IFERROR(INDEX($G$72:$R$83,MATCH($X77,$E$72:$E$83,0),MATCH(AC$67,$G$67:$R$67,0)), IFERROR(INDEX($G$72:$R$83,MATCH($X77,$E$72:$E$83,0),MATCH(AC$67,$G$68:$R$68,0)), IFERROR(INDEX($G$72:$R$83,MATCH($X77,$E$72:$E$83,0),MATCH(AC$67,$G$69:$R$69,0)), INDEX($G$72:$R$83,MATCH($X77,$E$72:$E$83,0),MATCH(AC$67,$G$70:$R$70,0))))))))))))))))) -> 0.66 | AD77: =IFERROR(INDEX($G$72:$R$83,MATCH($X77,$B$72:$B$83,0),MATCH(AD$67,$G$67:$R$67,0)), IFERROR(INDEX($G$72:$R$83,MATCH($X77,$B$72:$B$83,0),MATCH(AD$67,$G$68:$R$68,0)), IFERROR(INDEX($G$72:$R$83,MATCH($X77,$B$72:$B$83,0),MATCH(AD$67,$G$69:$R$69,0)), IFERROR(INDEX($G$72:$R$83,MATCH($X77,$B$72:$B$83,0),MATCH(AD$67,$G$70:$R$70,0)), IFERROR(INDEX($G$72:$R$83,MATCH($X77,$C$72:$C$83,0),MATCH(AD$67,$G$67:$R$67,0)), IFERROR(INDEX($G$72:$R$83,MATCH($X77,$C$72:$C$83,0),MATCH(AD$67,$G$68:$R$68,0)), IFERROR(INDEX($G$72:$R$83,MATCH($X77,$C$72:$C$83,0),MATCH(AD$67,$G$69:$R$69,0)), IFERROR(INDEX($G$72:$R$83,MATCH($X77,$C$72:$C$83,0),MATCH(AD$67,$G$70:$R$70,0)), IFERROR(INDEX($G$72:$R$83,MATCH($X77,$D$72:$D$83,0),MATCH(AD$67,$G$67:$R$67,0)), IFERROR(INDEX($G$72:$R$83,MATCH($X77,$D$72:$D$83,0),MATCH(AD$67,$G$68:$R$68,0)), IFERROR(INDEX($G$72:$R$83,MATCH($X77,$D$72:$D$83,0),MATCH(AD$67,$G$69:$R$69,0)), IFERROR(INDEX($G$72:$R$83,MATCH($X77,$D$72:$D$83,0),MATCH(AD$67,$G$70:$R$70,0)), IFERROR(INDEX($G$72:$R$83,MATCH($X77,$E$72:$E$83,0),MATCH(AD$67,$G$67:$R$67,0)), IFERROR(INDEX($G$72:$R$83,MATCH($X77,$E$72:$E$83,0),MATCH(AD$67,$G$68:$R$68,0)), IFERROR(INDEX($G$72:$R$83,MATCH($X77,$E$72:$E$83,0),MATCH(AD$67,$G$69:$R$69,0)), INDEX($G$72:$R$83,MATCH($X77,$E$72:$E$83,0),MATCH(AD$67,$G$70:$R$70,0))))))))))))))))) -> 0.66 | AE77: =IFERROR(INDEX($G$72:$R$83,MATCH($X77,$B$72:$B$83,0),MATCH(AE$67,$G$67:$R$67,0)), IFERROR(INDEX($G$72:$R$83,MATCH($X77,$B$72:$B$83,0),MATCH(AE$67,$G$68:$R$68,0)), IFERROR(INDEX($G$72:$R$83,MATCH($X77,$B$72:$B$83,0),MATCH(AE$67,$G$69:$R$69,0)), IFERROR(INDEX($G$72:$R$83,MATCH($X77,$B$72:$B$83,0),MATCH(AE$67,$G$70:$R$70,0)), IFERROR(INDEX($G$72:$R$83,MATCH($X77,$C$72:$C$83,0),MATCH(AE$67,$G$67:$R$67,0)), IFERROR(INDEX($G$72:$R$83,MATCH($X77,$C$72:$C$83,0),MATCH(AE$67,$G$68:$R$68,0)), IFERROR(INDEX($G$72:$R$83,MATCH($X77,$C$72:$C$83,0),MATCH(AE$67,$G$69:$R$69,0)), IFERROR(INDEX($G$72:$R$83,MATCH($X77,$C$72:$C$83,0),MATCH(AE$67,$G$70:$R$70,0)), IFERROR(INDEX($G$72:$R$83,MATCH($X77,$D$72:$D$83,0),MATCH(AE$67,$G$67:$R$67,0)), IFERROR(INDEX($G$72:$R$83,MATCH($X77,$D$72:$D$83,0),MATCH(AE$67,$G$68:$R$68,0)), IFERROR(INDEX($G$72:$R$83,MATCH($X77,$D$72:$D$83,0),MATCH(AE$67,$G$69:$R$69,0)), IFERROR(INDEX($G$72:$R$83,MATCH($X77,$D$72:$D$83,0),MATCH(AE$67,$G$70:$R$70,0)), IFERROR(INDEX($G$72:$R$83,MATCH($X77,$E$72:$E$83,0),MATCH(AE$67,$G$67:$R$67,0)), IFERROR(INDEX($G$72:$R$83,MATCH($X77,$E$72:$E$83,0),MATCH(AE$67,$G$68:$R$68,0)), IFERROR(INDEX($G$72:$R$83,MATCH($X77,$E$72:$E$83,0),MATCH(AE$67,$G$69:$R$69,0)), INDEX($G$72:$R$83,MATCH($X77,$E$72:$E$83,0),MATCH(AE$67,$G$70:$R$70,0))))))))))))))))) -> 0.66 | AF77: =IFERROR(INDEX($G$72:$R$83,MATCH($X77,$B$72:$B$83,0),MATCH(AF$67,$G$67:$R$67,0)), IFERROR(INDEX($G$72:$R$83,MATCH($X77,$B$72:$B$83,0),MATCH(AF$67,$G$68:$R$68,0)), IFERROR(INDEX($G$72:$R$83,MATCH($X77,$B$72:$B$83,0),MATCH(AF$67,$G$69:$R$69,0)), IFERROR(INDEX($G$72:$R$83,MATCH($X77,$B$72:$B$83,0),MATCH(AF$67,$G$70:$R$70,0)), IFERROR(INDEX($G$72:$R$83,MATCH($X77,$C$72:$C$83,0),MATCH(AF$67,$G$67:$R$67,0)), IFERROR(INDEX($G$72:$R$83,MATCH($X77,$C$72:$C$83,0),MATCH(AF$67,$G$68:$R$68,0)), IFERROR(INDEX($G$72:$R$83,MATCH($X77,$C$72:$C$83,0),MATCH(AF$67,$G$69:$R$69,0)), IFERROR(INDEX($G$72:$R$83,MATCH($X77,$C$72:$C$83,0),MATCH(AF$67,$G$70:$R$70,0)), IFERROR(INDEX($G$72:$R$83,MATCH($X77,$D$72:$D$83,0),MATCH(AF$67,$G$67:$R$67,0)), IFERROR(INDEX($G$72:$R$83,MATCH($X77,$D$72:$D$83,0),MATCH(AF$67,$G$68:$R$68,0)), IFERROR(INDEX($G$72:$R$83,MATCH($X77,$D$72:$D$83,0),MATCH(AF$67,$G$69:$R$69,0)), IFERROR(INDEX($G$72:$R$83,MATCH($X77,$D$72:$D$83,0),MATCH(AF$67,$G$70:$R$70,0)), IFERROR(INDEX($G$72:$R$83,MATCH($X77,$E$72:$E$83,0),MATCH(AF$67,$G$67:$R$67,0)), IFERROR(INDEX($G$72:$R$83,MATCH($X77,$E$72:$E$83,0),MATCH(AF$67,$G$68:$R$68,0)), IFERROR(INDEX($G$72:$R$83,MATCH($X77,$E$72:$E$83,0),MATCH(AF$67,$G$69:$R$69,0)), INDEX($G$72:$R$83,MATCH($X77,$E$72:$E$83,0),MATCH(AF$67,$G$70:$R$70,0))))))))))))))))) -> 0.66 | ... AS77: =IFERROR(INDEX($G$72:$R$83,MATCH($X77,$B$72:$B$83,0),MATCH(AS$67,$G$67:$R$67,0)), IFERROR(INDEX($G$72:$R$83,MATCH($X77,$B$72:$B$83,0),MATCH(AS$67,$G$68:$R$68,0)), IFERROR(INDEX($G$72:$R$83,MATCH($X77,$B$72:$B$83,0),MATCH(AS$67,$G$69:$R$69,0)), IFERROR(INDEX($G$72:$R$83,MATCH($X77,$B$72:$B$83,0),MATCH(AS$67,$G$70:$R$70,0)), IFERROR(INDEX($G$72:$R$83,MATCH($X77,$C$72:$C$83,0),MATCH(AS$67,$G$67:$R$67,0)), IFERROR(INDEX($G$72:$R$83,MATCH($X77,$C$72:$C$83,0),MATCH(AS$67,$G$68:$R$68,0)), IFERROR(INDEX($G$72:$R$83,MATCH($X77,$C$72:$C$83,0),MATCH(AS$67,$G$69:$R$69,0)), IFERROR(INDEX($G$72:$R$83,MATCH($X77,$C$72:$C$83,0),MATCH(AS$67,$G$70:$R$70,0)), IFERROR(INDEX($G$72:$R$83,MATCH($X77,$D$72:$D$83,0),MATCH(AS$67,$G$67:$R$67,0)), IFERROR(INDEX($G$72:$R$83,MATCH($X77,$D$72:$D$83,0),MATCH(AS$67,$G$68:$R$68,0)), IFERROR(INDEX($G$72:$R$83,MATCH($X77,$D$72:$D$83,0),MATCH(AS$67,$G$69:$R$69,0)), IFERROR(INDEX($G$72:$R$83,MATCH($X77,$D$72:$D$83,0),MATCH(AS$67,$G$70:$R$70,0)), IFERROR(INDEX($G$72:$R$83,MATCH($X77,$E$72:$E$83,0),MATCH(AS$67,$G$67:$R$67,0)), IFERROR(INDEX($G$72:$R$83,MATCH($X77,$E$72:$E$83,0),MATCH(AS$67,$G$68:$R$68,0)), IFERROR(INDEX($G$72:$R$83,MATCH($X77,$E$72:$E$83,0),MATCH(AS$67,$G$69:$R$69,0)), INDEX($G$72:$R$83,MATCH($X77,$E$72:$E$83,0),MATCH(AS$67,$G$70:$R$70,0))))))))))))))))) -> 0.35
B78: Global ex-US Government, hedged | C78: Global ex-US Corporates, hedged | F78: World ex-U.S. Government Bonds hedged | G78: 0.72 | H78: 0.74 | I78: 0.7 | J78: 0.64 | K78: 0.19 | L78: -0.1 | M78: 1 | N78: 0.59 | O78: -0.16 | P78: 0.37 | Q78: -0.15 | R78: -0.05 | X78: Global ex-US Corporates, hedged | Y78: =IFERROR(INDEX($G$72:$R$83,MATCH($X78,$B$72:$B$83,0),MATCH(Y$67,$G$67:$R$67,0)), IFERROR(INDEX($G$72:$R$83,MATCH($X78,$B$72:$B$83,0),MATCH(Y$67,$G$68:$R$68,0)), IFERROR(INDEX($G$72:$R$83,MATCH($X78,$B$72:$B$83,0),MATCH(Y$67,$G$69:$R$69,0)), IFERROR(INDEX($G$72:$R$83,MATCH($X78,$B$72:$B$83,0),MATCH(Y$67,$G$70:$R$70,0)), IFERROR(INDEX($G$72:$R$83,MATCH($X78,$C$72:$C$83,0),MATCH(Y$67,$G$67:$R$67,0)), IFERROR(INDEX($G$72:$R$83,MATCH($X78,$C$72:$C$83,0),MATCH(Y$67,$G$68:$R$68,0)), IFERROR(INDEX($G$72:$R$83,MATCH($X78,$C$72:$C$83,0),MATCH(Y$67,$G$69:$R$69,0)), IFERROR(INDEX($G$72:$R$83,MATCH($X78,$C$72:$C$83,0),MATCH(Y$67,$G$70:$R$70,0)), IFERROR(INDEX($G$72:$R$83,MATCH($X78,$D$72:$D$83,0),MATCH(Y$67,$G$67:$R$67,0)), IFERROR(INDEX($G$72:$R$83,MATCH($X78,$D$72:$D$83,0),MATCH(Y$67,$G$68:$R$68,0)), IFERROR(INDEX($G$72:$R$83,MATCH($X78,$D$72:$D$83,0),MATCH(Y$67,$G$69:$R$69,0)), IFERROR(INDEX($G$72:$R$83,MATCH($X78,$D$72:$D$83,0),MATCH(Y$67,$G$70:$R$70,0)), IFERROR(INDEX($G$72:$R$83,MATCH($X78,$E$72:$E$83,0),MATCH(Y$67,$G$67:$R$67,0)), IFERROR(INDEX($G$72:$R$83,MATCH($X78,$E$72:$E$83,0),MATCH(Y$67,$G$68:$R$68,0)), IFERROR(INDEX($G$72:$R$83,MATCH($X78,$E$72:$E$83,0),MATCH(Y$67,$G$69:$R$69,0)), INDEX($G$72:$R$83,MATCH($X78,$E$72:$E$83,0),MATCH(Y$67,$G$70:$R$70,0))))))))))))))))) -> 0.72 | Z78: =IFERROR(INDEX($G$72:$R$83,MATCH($X78,$B$72:$B$83,0),MATCH(Z$67,$G$67:$R$67,0)), IFERROR(INDEX($G$72:$R$83,MATCH($X78,$B$72:$B$83,0),MATCH(Z$67,$G$68:$R$68,0)), IFERROR(INDEX($G$72:$R$83,MATCH($X78,$B$72:$B$83,0),MATCH(Z$67,$G$69:$R$69,0)), IFERROR(INDEX($G$72:$R$83,MATCH($X78,$B$72:$B$83,0),MATCH(Z$67,$G$70:$R$70,0)), IFERROR(INDEX($G$72:$R$83,MATCH($X78,$C$72:$C$83,0),MATCH(Z$67,$G$67:$R$67,0)), IFERROR(INDEX($G$72:$R$83,MATCH($X78,$C$72:$C$83,0),MATCH(Z$67,$G$68:$R$68,0)), IFERROR(INDEX($G$72:$R$83,MATCH($X78,$C$72:$C$83,0),MATCH(Z$67,$G$69:$R$69,0)), IFERROR(INDEX($G$72:$R$83,MATCH($X78,$C$72:$C$83,0),MATCH(Z$67,$G$70:$R$70,0)), IFERROR(INDEX($G$72:$R$83,MATCH($X78,$D$72:$D$83,0),MATCH(Z$67,$G$67:$R$67,0)), IFERROR(INDEX($G$72:$R$83,MATCH($X78,$D$72:$D$83,0),MATCH(Z$67,$G$68:$R$68,0)), IFERROR(INDEX($G$72:$R$83,MATCH($X78,$D$72:$D$83,0),MATCH(Z$67,$G$69:$R$69,0)), IFERROR(INDEX($G$72:$R$83,MATCH($X78,$D$72:$D$83,0),MATCH(Z$67,$G$70:$R$70,0)), IFERROR(INDEX($G$72:$R$83,MATCH($X78,$E$72:$E$83,0),MATCH(Z$67,$G$67:$R$67,0)), IFERROR(INDEX($G$72:$R$83,MATCH($X78,$E$72:$E$83,0),MATCH(Z$67,$G$68:$R$68,0)), IFERROR(INDEX($G$72:$R$83,MATCH($X78,$E$72:$E$83,0),MATCH(Z$67,$G$69:$R$69,0)), INDEX($G$72:$R$83,MATCH($X78,$E$72:$E$83,0),MATCH(Z$67,$G$70:$R$70,0))))))))))))))))) -> 0.74 | AA78: =IFERROR(INDEX($G$72:$R$83,MATCH($X78,$B$72:$B$83,0),MATCH(AA$67,$G$67:$R$67,0)), IFERROR(INDEX($G$72:$R$83,MATCH($X78,$B$72:$B$83,0),MATCH(AA$67,$G$68:$R$68,0)), IFERROR(INDEX($G$72:$R$83,MATCH($X78,$B$72:$B$83,0),MATCH(AA$67,$G$69:$R$69,0)), IFERROR(INDEX($G$72:$R$83,MATCH($X78,$B$72:$B$83,0),MATCH(AA$67,$G$70:$R$70,0)), IFERROR(INDEX($G$72:$R$83,MATCH($X78,$C$72:$C$83,0),MATCH(AA$67,$G$67:$R$67,0)), IFERROR(INDEX($G$72:$R$83,MATCH($X78,$C$72:$C$83,0),MATCH(AA$67,$G$68:$R$68,0)), IFERROR(INDEX($G$72:$R$83,MATCH($X78,$C$72:$C$83,0),MATCH(AA$67,$G$69:$R$69,0)), IFERROR(INDEX($G$72:$R$83,MATCH($X78,$C$72:$C$83,0),MATCH(AA$67,$G$70:$R$70,0)), IFERROR(INDEX($G$72:$R$83,MATCH($X78,$D$72:$D$83,0),MATCH(AA$67,$G$67:$R$67,0)), IFERROR(INDEX($G$72:$R$83,MATCH($X78,$D$72:$D$83,0),MATCH(AA$67,$G$68:$R$68,0)), IFERROR(INDEX($G$72:$R$83,MATCH($X78,$D$72:$D$83,0),MATCH(AA$67,$G$69:$R$69,0)), IFERROR(INDEX($G$72:$R$83,MATCH($X78,$D$72:$D$83,0),MATCH(AA$67,$G$70:$R$70,0)), IFERROR(INDEX($G$72:$R$83,MATCH($X78,$E$72:$E$83,0),MATCH(AA$67,$G$67:$R$67,0)), IFERROR(INDEX($G$72:$R$83,MATCH($X78,$E$72:$E$83,0),MATCH(AA$67,$G$68:$R$68,0)), IFERROR(INDEX($G$72:$R$83,MATCH($X78,$E$72:$E$83,0),MATCH(AA$67,$G$69:$R$69,0)), INDEX($G$72:$R$83,MATCH($X78,$E$72:$E$83,0),MATCH(AA$67,$G$70:$R$70,0))))))))))))))))) -> 0.59 | AB78: =IFERROR(INDEX($G$72:$R$83,MATCH($X78,$B$72:$B$83,0),MATCH(AB$67,$G$67:$R$67,0)), IFERROR(INDEX($G$72:$R$83,MATCH($X78,$B$72:$B$83,0),MATCH(AB$67,$G$68:$R$68,0)), IFERROR(INDEX($G$72:$R$83,MATCH($X78,$B$72:$B$83,0),MATCH(AB$67,$G$69:$R$69,0)), IFERROR(INDEX($G$72:$R$83,MATCH($X78,$B$72:$B$83,0),MATCH(AB$67,$G$70:$R$70,0)), IFERROR(INDEX($G$72:$R$83,MATCH($X78,$C$72:$C$83,0),MATCH(AB$67,$G$67:$R$67,0)), IFERROR(INDEX($G$72:$R$83,MATCH($X78,$C$72:$C$83,0),MATCH(AB$67,$G$68:$R$68,0)), IFERROR(INDEX($G$72:$R$83,MATCH($X78,$C$72:$C$83,0),MATCH(AB$67,$G$69:$R$69,0)), IFERROR(INDEX($G$72:$R$83,MATCH($X78,$C$72:$C$83,0),MATCH(AB$67,$G$70:$R$70,0)), IFERROR(INDEX($G$72:$R$83,MATCH($X78,$D$72:$D$83,0),MATCH(AB$67,$G$67:$R$67,0)), IFERROR(INDEX($G$72:$R$83,MATCH($X78,$D$72:$D$83,0),MATCH(AB$67,$G$68:$R$68,0)), IFERROR(INDEX($G$72:$R$83,MATCH($X78,$D$72:$D$83,0),MATCH(AB$67,$G$69:$R$69,0)), IFERROR(INDEX($G$72:$R$83,MATCH($X78,$D$72:$D$83,0),MATCH(AB$67,$G$70:$R$70,0)), IFERROR(INDEX($G$72:$R$83,MATCH($X78,$E$72:$E$83,0),MATCH(AB$67,$G$67:$R$67,0)), IFERROR(INDEX($G$72:$R$83,MATCH($X78,$E$72:$E$83,0),MATCH(AB$67,$G$68:$R$68,0)), IFERROR(INDEX($G$72:$R$83,MATCH($X78,$E$72:$E$83,0),MATCH(AB$67,$G$69:$R$69,0)), INDEX($G$72:$R$83,MATCH($X78,$E$72:$E$83,0),MATCH(AB$67,$G$70:$R$70,0))))))))))))))))) -> 1 | AC78: =IFERROR(INDEX($G$72:$R$83,MATCH($X78,$B$72:$B$83,0),MATCH(AC$67,$G$67:$R$67,0)), IFERROR(INDEX($G$72:$R$83,MATCH($X78,$B$72:$B$83,0),MATCH(AC$67,$G$68:$R$68,0)), IFERROR(INDEX($G$72:$R$83,MATCH($X78,$B$72:$B$83,0),MATCH(AC$67,$G$69:$R$69,0)), IFERROR(INDEX($G$72:$R$83,MATCH($X78,$B$72:$B$83,0),MATCH(AC$67,$G$70:$R$70,0)), IFERROR(INDEX($G$72:$R$83,MATCH($X78,$C$72:$C$83,0),MATCH(AC$67,$G$67:$R$67,0)), IFERROR(INDEX($G$72:$R$83,MATCH($X78,$C$72:$C$83,0),MATCH(AC$67,$G$68:$R$68,0)), IFERROR(INDEX($G$72:$R$83,MATCH($X78,$C$72:$C$83,0),MATCH(AC$67,$G$69:$R$69,0)), IFERROR(INDEX($G$72:$R$83,MATCH($X78,$C$72:$C$83,0),MATCH(AC$67,$G$70:$R$70,0)), IFERROR(INDEX($G$72:$R$83,MATCH($X78,$D$72:$D$83,0),MATCH(AC$67,$G$67:$R$67,0)), IFERROR(INDEX($G$72:$R$83,MATCH($X78,$D$72:$D$83,0),MATCH(AC$67,$G$68:$R$68,0)), IFERROR(INDEX($G$72:$R$83,MATCH($X78,$D$72:$D$83,0),MATCH(AC$67,$G$69:$R$69,0)), IFERROR(INDEX($G$72:$R$83,MATCH($X78,$D$72:$D$83,0),MATCH(AC$67,$G$70:$R$70,0)), IFERROR(INDEX($G$72:$R$83,MATCH($X78,$E$72:$E$83,0),MATCH(AC$67,$G$67:$R$67,0)), IFERROR(INDEX($G$72:$R$83,MATCH($X78,$E$72:$E$83,0),MATCH(AC$67,$G$68:$R$68,0)), IFERROR(INDEX($G$72:$R$83,MATCH($X78,$E$72:$E$83,0),MATCH(AC$67,$G$69:$R$69,0)), INDEX($G$72:$R$83,MATCH($X78,$E$72:$E$83,0),MATCH(AC$67,$G$70:$R$70,0))))))))))))))))) -> 0.64 | AD78: =IFERROR(INDEX($G$72:$R$83,MATCH($X78,$B$72:$B$83,0),MATCH(AD$67,$G$67:$R$67,0)), IFERROR(INDEX($G$72:$R$83,MATCH($X78,$B$72:$B$83,0),MATCH(AD$67,$G$68:$R$68,0)), IFERROR(INDEX($G$72:$R$83,MATCH($X78,$B$72:$B$83,0),MATCH(AD$67,$G$69:$R$69,0)), IFERROR(INDEX($G$72:$R$83,MATCH($X78,$B$72:$B$83,0),MATCH(AD$67,$G$70:$R$70,0)), IFERROR(INDEX($G$72:$R$83,MATCH($X78,$C$72:$C$83,0),MATCH(AD$67,$G$67:$R$67,0)), IFERROR(INDEX($G$72:$R$83,MATCH($X78,$C$72:$C$83,0),MATCH(AD$67,$G$68:$R$68,0)), IFERROR(INDEX($G$72:$R$83,MATCH($X78,$C$72:$C$83,0),MATCH(AD$67,$G$69:$R$69,0)), IFERROR(INDEX($G$72:$R$83,MATCH($X78,$C$72:$C$83,0),MATCH(AD$67,$G$70:$R$70,0)), IFERROR(INDEX($G$72:$R$83,MATCH($X78,$D$72:$D$83,0),MATCH(AD$67,$G$67:$R$67,0)), IFERROR(INDEX($G$72:$R$83,MATCH($X78,$D$72:$D$83,0),MATCH(AD$67,$G$68:$R$68,0)), IFERROR(INDEX($G$72:$R$83,MATCH($X78,$D$72:$D$83,0),MATCH(AD$67,$G$69:$R$69,0)), IFERROR(INDEX($G$72:$R$83,MATCH($X78,$D$72:$D$83,0),MATCH(AD$67,$G$70:$R$70,0)), IFERROR(INDEX($G$72:$R$83,MATCH($X78,$E$72:$E$83,0),MATCH(AD$67,$G$67:$R$67,0)), IFERROR(INDEX($G$72:$R$83,MATCH($X78,$E$72:$E$83,0),MATCH(AD$67,$G$68:$R$68,0)), IFERROR(INDEX($G$72:$R$83,MATCH($X78,$E$72:$E$83,0),MATCH(AD$67,$G$69:$R$69,0)), INDEX($G$72:$R$83,MATCH($X78,$E$72:$E$83,0),MATCH(AD$67,$G$70:$R$70,0))))))))))))))))) -> 0.64 | AE78: =IFERROR(INDEX($G$72:$R$83,MATCH($X78,$B$72:$B$83,0),MATCH(AE$67,$G$67:$R$67,0)), IFERROR(INDEX($G$72:$R$83,MATCH($X78,$B$72:$B$83,0),MATCH(AE$67,$G$68:$R$68,0)), IFERROR(INDEX($G$72:$R$83,MATCH($X78,$B$72:$B$83,0),MATCH(AE$67,$G$69:$R$69,0)), IFERROR(INDEX($G$72:$R$83,MATCH($X78,$B$72:$B$83,0),MATCH(AE$67,$G$70:$R$70,0)), IFERROR(INDEX($G$72:$R$83,MATCH($X78,$C$72:$C$83,0),MATCH(AE$67,$G$67:$R$67,0)), IFERROR(INDEX($G$72:$R$83,MATCH($X78,$C$72:$C$83,0),MATCH(AE$67,$G$68:$R$68,0)), IFERROR(INDEX($G$72:$R$83,MATCH($X78,$C$72:$C$83,0),MATCH(AE$67,$G$69:$R$69,0)), IFERROR(INDEX($G$72:$R$83,MATCH($X78,$C$72:$C$83,0),MATCH(AE$67,$G$70:$R$70,0)), IFERROR(INDEX($G$72:$R$83,MATCH($X78,$D$72:$D$83,0),MATCH(AE$67,$G$67:$R$67,0)), IFERROR(INDEX($G$72:$R$83,MATCH($X78,$D$72:$D$83,0),MATCH(AE$67,$G$68:$R$68,0)), IFERROR(INDEX($G$72:$R$83,MATCH($X78,$D$72:$D$83,0),MATCH(AE$67,$G$69:$R$69,0)), IFERROR(INDEX($G$72:$R$83,MATCH($X78,$D$72:$D$83,0),MATCH(AE$67,$G$70:$R$70,0)), IFERROR(INDEX($G$72:$R$83,MATCH($X78,$E$72:$E$83,0),MATCH(AE$67,$G$67:$R$67,0)), IFERROR(INDEX($G$72:$R$83,MATCH($X78,$E$72:$E$83,0),MATCH(AE$67,$G$68:$R$68,0)), IFERROR(INDEX($G$72:$R$83,MATCH($X78,$E$72:$E$83,0),MATCH(AE$67,$G$69:$R$69,0)), INDEX($G$72:$R$83,MATCH($X78,$E$72:$E$83,0),MATCH(AE$67,$G$70:$R$70,0))))))))))))))))) -> 0.64 | AF78: =IFERROR(INDEX($G$72:$R$83,MATCH($X78,$B$72:$B$83,0),MATCH(AF$67,$G$67:$R$67,0)), IFERROR(INDEX($G$72:$R$83,MATCH($X78,$B$72:$B$83,0),MATCH(AF$67,$G$68:$R$68,0)), IFERROR(INDEX($G$72:$R$83,MATCH($X78,$B$72:$B$83,0),MATCH(AF$67,$G$69:$R$69,0)), IFERROR(INDEX($G$72:$R$83,MATCH($X78,$B$72:$B$83,0),MATCH(AF$67,$G$70:$R$70,0)), IFERROR(INDEX($G$72:$R$83,MATCH($X78,$C$72:$C$83,0),MATCH(AF$67,$G$67:$R$67,0)), IFERROR(INDEX($G$72:$R$83,MATCH($X78,$C$72:$C$83,0),MATCH(AF$67,$G$68:$R$68,0)), IFERROR(INDEX($G$72:$R$83,MATCH($X78,$C$72:$C$83,0),MATCH(AF$67,$G$69:$R$69,0)), IFERROR(INDEX($G$72:$R$83,MATCH($X78,$C$72:$C$83,0),MATCH(AF$67,$G$70:$R$70,0)), IFERROR(INDEX($G$72:$R$83,MATCH($X78,$D$72:$D$83,0),MATCH(AF$67,$G$67:$R$67,0)), IFERROR(INDEX($G$72:$R$83,MATCH($X78,$D$72:$D$83,0),MATCH(AF$67,$G$68:$R$68,0)), IFERROR(INDEX($G$72:$R$83,MATCH($X78,$D$72:$D$83,0),MATCH(AF$67,$G$69:$R$69,0)), IFERROR(INDEX($G$72:$R$83,MATCH($X78,$D$72:$D$83,0),MATCH(AF$67,$G$70:$R$70,0)), IFERROR(INDEX($G$72:$R$83,MATCH($X78,$E$72:$E$83,0),MATCH(AF$67,$G$67:$R$67,0)), IFERROR(INDEX($G$72:$R$83,MATCH($X78,$E$72:$E$83,0),MATCH(AF$67,$G$68:$R$68,0)), IFERROR(INDEX($G$72:$R$83,MATCH($X78,$E$72:$E$83,0),MATCH(AF$67,$G$69:$R$69,0)), INDEX($G$72:$R$83,MATCH($X78,$E$72:$E$83,0),MATCH(AF$67,$G$70:$R$70,0))))))))))))))))) -> 0.64 | ... AS78: =IFERROR(INDEX($G$72:$R$83,MATCH($X78,$B$72:$B$83,0),MATCH(AS$67,$G$67:$R$67,0)), IFERROR(INDEX($G$72:$R$83,MATCH($X78,$B$72:$B$83,0),MATCH(AS$67,$G$68:$R$68,0)), IFERROR(INDEX($G$72:$R$83,MATCH($X78,$B$72:$B$83,0),MATCH(AS$67,$G$69:$R$69,0)), IFERROR(INDEX($G$72:$R$83,MATCH($X78,$B$72:$B$83,0),MATCH(AS$67,$G$70:$R$70,0)), IFERROR(INDEX($G$72:$R$83,MATCH($X78,$C$72:$C$83,0),MATCH(AS$67,$G$67:$R$67,0)), IFERROR(INDEX($G$72:$R$83,MATCH($X78,$C$72:$C$83,0),MATCH(AS$67,$G$68:$R$68,0)), IFERROR(INDEX($G$72:$R$83,MATCH($X78,$C$72:$C$83,0),MATCH(AS$67,$G$69:$R$69,0)), IFERROR(INDEX($G$72:$R$83,MATCH($X78,$C$72:$C$83,0),MATCH(AS$67,$G$70:$R$70,0)), IFERROR(INDEX($G$72:$R$83,MATCH($X78,$D$72:$D$83,0),MATCH(AS$67,$G$67:$R$67,0)), IFERROR(INDEX($G$72:$R$83,MATCH($X78,$D$72:$D$83,0),MATCH(AS$67,$G$68:$R$68,0)), IFERROR(INDEX($G$72:$R$83,MATCH($X78,$D$72:$D$83,0),MATCH(AS$67,$G$69:$R$69,0)), IFERROR(INDEX($G$72:$R$83,MATCH($X78,$D$72:$D$83,0),MATCH(AS$67,$G$70:$R$70,0)), IFERROR(INDEX($G$72:$R$83,MATCH($X78,$E$72:$E$83,0),MATCH(AS$67,$G$67:$R$67,0)), IFERROR(INDEX($G$72:$R$83,MATCH($X78,$E$72:$E$83,0),MATCH(AS$67,$G$68:$R$68,0)), IFERROR(INDEX($G$72:$R$83,MATCH($X78,$E$72:$E$83,0),MATCH(AS$67,$G$69:$R$69,0)), INDEX($G$72:$R$83,MATCH($X78,$E$72:$E$83,0),MATCH(AS$67,$G$70:$R$70,0))))))))))))))))) -> -0.16
B79: US Taxable Munis | F79: U.S. Muni 1-15 Yr Blend | G79: 0.52 | H79: 0.51 | I79: 0.69 | J79: 0.69 | K79: 0.42 | L79: 0.18 | M79: 0.59 | N79: 1 | O79: 0.2 | P79: 0.51 | Q79: 0.13 | R79: 0.17 | X79: Residential Mortgage-Backed Securities | Y79: =IFERROR(INDEX($G$72:$R$83,MATCH($X79,$B$72:$B$83,0),MATCH(Y$67,$G$67:$R$67,0)), IFERROR(INDEX($G$72:$R$83,MATCH($X79,$B$72:$B$83,0),MATCH(Y$67,$G$68:$R$68,0)), IFERROR(INDEX($G$72:$R$83,MATCH($X79,$B$72:$B$83,0),MATCH(Y$67,$G$69:$R$69,0)), IFERROR(INDEX($G$72:$R$83,MATCH($X79,$B$72:$B$83,0),MATCH(Y$67,$G$70:$R$70,0)), IFERROR(INDEX($G$72:$R$83,MATCH($X79,$C$72:$C$83,0),MATCH(Y$67,$G$67:$R$67,0)), IFERROR(INDEX($G$72:$R$83,MATCH($X79,$C$72:$C$83,0),MATCH(Y$67,$G$68:$R$68,0)), IFERROR(INDEX($G$72:$R$83,MATCH($X79,$C$72:$C$83,0),MATCH(Y$67,$G$69:$R$69,0)), IFERROR(INDEX($G$72:$R$83,MATCH($X79,$C$72:$C$83,0),MATCH(Y$67,$G$70:$R$70,0)), IFERROR(INDEX($G$72:$R$83,MATCH($X79,$D$72:$D$83,0),MATCH(Y$67,$G$67:$R$67,0)), IFERROR(INDEX($G$72:$R$83,MATCH($X79,$D$72:$D$83,0),MATCH(Y$67,$G$68:$R$68,0)), IFERROR(INDEX($G$72:$R$83,MATCH($X79,$D$72:$D$83,0),MATCH(Y$67,$G$69:$R$69,0)), IFERROR(INDEX($G$72:$R$83,MATCH($X79,$D$72:$D$83,0),MATCH(Y$67,$G$70:$R$70,0)), IFERROR(INDEX($G$72:$R$83,MATCH($X79,$E$72:$E$83,0),MATCH(Y$67,$G$67:$R$67,0)), IFERROR(INDEX($G$72:$R$83,MATCH($X79,$E$72:$E$83,0),MATCH(Y$67,$G$68:$R$68,0)), IFERROR(INDEX($G$72:$R$83,MATCH($X79,$E$72:$E$83,0),MATCH(Y$67,$G$69:$R$69,0)), INDEX($G$72:$R$83,MATCH($X79,$E$72:$E$83,0),MATCH(Y$67,$G$70:$R$70,0))))))))))))))))) -> 0.78 | Z79: =IFERROR(INDEX($G$72:$R$83,MATCH($X79,$B$72:$B$83,0),MATCH(Z$67,$G$67:$R$67,0)), IFERROR(INDEX($G$72:$R$83,MATCH($X79,$B$72:$B$83,0),MATCH(Z$67,$G$68:$R$68,0)), IFERROR(INDEX($G$72:$R$83,MATCH($X79,$B$72:$B$83,0),MATCH(Z$67,$G$69:$R$69,0)), IFERROR(INDEX($G$72:$R$83,MATCH($X79,$B$72:$B$83,0),MATCH(Z$67,$G$70:$R$70,0)), IFERROR(INDEX($G$72:$R$83,MATCH($X79,$C$72:$C$83,0),MATCH(Z$67,$G$67:$R$67,0)), IFERROR(INDEX($G$72:$R$83,MATCH($X79,$C$72:$C$83,0),MATCH(Z$67,$G$68:$R$68,0)), IFERROR(INDEX($G$72:$R$83,MATCH($X79,$C$72:$C$83,0),MATCH(Z$67,$G$69:$R$69,0)), IFERROR(INDEX($G$72:$R$83,MATCH($X79,$C$72:$C$83,0),MATCH(Z$67,$G$70:$R$70,0)), IFERROR(INDEX($G$72:$R$83,MATCH($X79,$D$72:$D$83,0),MATCH(Z$67,$G$67:$R$67,0)), IFERROR(INDEX($G$72:$R$83,MATCH($X79,$D$72:$D$83,0),MATCH(Z$67,$G$68:$R$68,0)), IFERROR(INDEX($G$72:$R$83,MATCH($X79,$D$72:$D$83,0),MATCH(Z$67,$G$69:$R$69,0)), IFERROR(INDEX($G$72:$R$83,MATCH($X79,$D$72:$D$83,0),MATCH(Z$67,$G$70:$R$70,0)), IFERROR(INDEX($G$72:$R$83,MATCH($X79,$E$72:$E$83,0),MATCH(Z$67,$G$67:$R$67,0)), IFERROR(INDEX($G$72:$R$83,MATCH($X79,$E$72:$E$83,0),MATCH(Z$67,$G$68:$R$68,0)), IFERROR(INDEX($G$72:$R$83,MATCH($X79,$E$72:$E$83,0),MATCH(Z$67,$G$69:$R$69,0)), INDEX($G$72:$R$83,MATCH($X79,$E$72:$E$83,0),MATCH(Z$67,$G$70:$R$70,0))))))))))))))))) -> 0.74 | AA79: =IFERROR(INDEX($G$72:$R$83,MATCH($X79,$B$72:$B$83,0),MATCH(AA$67,$G$67:$R$67,0)), IFERROR(INDEX($G$72:$R$83,MATCH($X79,$B$72:$B$83,0),MATCH(AA$67,$G$68:$R$68,0)), IFERROR(INDEX($G$72:$R$83,MATCH($X79,$B$72:$B$83,0),MATCH(AA$67,$G$69:$R$69,0)), IFERROR(INDEX($G$72:$R$83,MATCH($X79,$B$72:$B$83,0),MATCH(AA$67,$G$70:$R$70,0)), IFERROR(INDEX($G$72:$R$83,MATCH($X79,$C$72:$C$83,0),MATCH(AA$67,$G$67:$R$67,0)), IFERROR(INDEX($G$72:$R$83,MATCH($X79,$C$72:$C$83,0),MATCH(AA$67,$G$68:$R$68,0)), IFERROR(INDEX($G$72:$R$83,MATCH($X79,$C$72:$C$83,0),MATCH(AA$67,$G$69:$R$69,0)), IFERROR(INDEX($G$72:$R$83,MATCH($X79,$C$72:$C$83,0),MATCH(AA$67,$G$70:$R$70,0)), IFERROR(INDEX($G$72:$R$83,MATCH($X79,$D$72:$D$83,0),MATCH(AA$67,$G$67:$R$67,0)), IFERROR(INDEX($G$72:$R$83,MATCH($X79,$D$72:$D$83,0),MATCH(AA$67,$G$68:$R$68,0)), IFERROR(INDEX($G$72:$R$83,MATCH($X79,$D$72:$D$83,0),MATCH(AA$67,$G$69:$R$69,0)), IFERROR(INDEX($G$72:$R$83,MATCH($X79,$D$72:$D$83,0),MATCH(AA$67,$G$70:$R$70,0)), IFERROR(INDEX($G$72:$R$83,MATCH($X79,$E$72:$E$83,0),MATCH(AA$67,$G$67:$R$67,0)), IFERROR(INDEX($G$72:$R$83,MATCH($X79,$E$72:$E$83,0),MATCH(AA$67,$G$68:$R$68,0)), IFERROR(INDEX($G$72:$R$83,MATCH($X79,$E$72:$E$83,0),MATCH(AA$67,$G$69:$R$69,0)), INDEX($G$72:$R$83,MATCH($X79,$E$72:$E$83,0),MATCH(AA$67,$G$70:$R$70,0))))))))))))))))) -> 0.69 | AB79: =IFERROR(INDEX($G$72:$R$83,MATCH($X79,$B$72:$B$83,0),MATCH(AB$67,$G$67:$R$67,0)), IFERROR(INDEX($G$72:$R$83,MATCH($X79,$B$72:$B$83,0),MATCH(AB$67,$G$68:$R$68,0)), IFERROR(INDEX($G$72:$R$83,MATCH($X79,$B$72:$B$83,0),MATCH(AB$67,$G$69:$R$69,0)), IFERROR(INDEX($G$72:$R$83,MATCH($X79,$B$72:$B$83,0),MATCH(AB$67,$G$70:$R$70,0)), IFERROR(INDEX($G$72:$R$83,MATCH($X79,$C$72:$C$83,0),MATCH(AB$67,$G$67:$R$67,0)), IFERROR(INDEX($G$72:$R$83,MATCH($X79,$C$72:$C$83,0),MATCH(AB$67,$G$68:$R$68,0)), IFERROR(INDEX($G$72:$R$83,MATCH($X79,$C$72:$C$83,0),MATCH(AB$67,$G$69:$R$69,0)), IFERROR(INDEX($G$72:$R$83,MATCH($X79,$C$72:$C$83,0),MATCH(AB$67,$G$70:$R$70,0)), IFERROR(INDEX($G$72:$R$83,MATCH($X79,$D$72:$D$83,0),MATCH(AB$67,$G$67:$R$67,0)), IFERROR(INDEX($G$72:$R$83,MATCH($X79,$D$72:$D$83,0),MATCH(AB$67,$G$68:$R$68,0)), IFERROR(INDEX($G$72:$R$83,MATCH($X79,$D$72:$D$83,0),MATCH(AB$67,$G$69:$R$69,0)), IFERROR(INDEX($G$72:$R$83,MATCH($X79,$D$72:$D$83,0),MATCH(AB$67,$G$70:$R$70,0)), IFERROR(INDEX($G$72:$R$83,MATCH($X79,$E$72:$E$83,0),MATCH(AB$67,$G$67:$R$67,0)), IFERROR(INDEX($G$72:$R$83,MATCH($X79,$E$72:$E$83,0),MATCH(AB$67,$G$68:$R$68,0)), IFERROR(INDEX($G$72:$R$83,MATCH($X79,$E$72:$E$83,0),MATCH(AB$67,$G$69:$R$69,0)), INDEX($G$72:$R$83,MATCH($X79,$E$72:$E$83,0),MATCH(AB$67,$G$70:$R$70,0))))))))))))))))) -> 0.7 | AC79: =IFERROR(INDEX($G$72:$R$83,MATCH($X79,$B$72:$B$83,0),MATCH(AC$67,$G$67:$R$67,0)), IFERROR(INDEX($G$72:$R$83,MATCH($X79,$B$72:$B$83,0),MATCH(AC$67,$G$68:$R$68,0)), IFERROR(INDEX($G$72:$R$83,MATCH($X79,$B$72:$B$83,0),MATCH(AC$67,$G$69:$R$69,0)), IFERROR(INDEX($G$72:$R$83,MATCH($X79,$B$72:$B$83,0),MATCH(AC$67,$G$70:$R$70,0)), IFERROR(INDEX($G$72:$R$83,MATCH($X79,$C$72:$C$83,0),MATCH(AC$67,$G$67:$R$67,0)), IFERROR(INDEX($G$72:$R$83,MATCH($X79,$C$72:$C$83,0),MATCH(AC$67,$G$68:$R$68,0)), IFERROR(INDEX($G$72:$R$83,MATCH($X79,$C$72:$C$83,0),MATCH(AC$67,$G$69:$R$69,0)), IFERROR(INDEX($G$72:$R$83,MATCH($X79,$C$72:$C$83,0),MATCH(AC$67,$G$70:$R$70,0)), IFERROR(INDEX($G$72:$R$83,MATCH($X79,$D$72:$D$83,0),MATCH(AC$67,$G$67:$R$67,0)), IFERROR(INDEX($G$72:$R$83,MATCH($X79,$D$72:$D$83,0),MATCH(AC$67,$G$68:$R$68,0)), IFERROR(INDEX($G$72:$R$83,MATCH($X79,$D$72:$D$83,0),MATCH(AC$67,$G$69:$R$69,0)), IFERROR(INDEX($G$72:$R$83,MATCH($X79,$D$72:$D$83,0),MATCH(AC$67,$G$70:$R$70,0)), IFERROR(INDEX($G$72:$R$83,MATCH($X79,$E$72:$E$83,0),MATCH(AC$67,$G$67:$R$67,0)), IFERROR(INDEX($G$72:$R$83,MATCH($X79,$E$72:$E$83,0),MATCH(AC$67,$G$68:$R$68,0)), IFERROR(INDEX($G$72:$R$83,MATCH($X79,$E$72:$E$83,0),MATCH(AC$67,$G$69:$R$69,0)), INDEX($G$72:$R$83,MATCH($X79,$E$72:$E$83,0),MATCH(AC$67,$G$70:$R$70,0))))))))))))))))) -> 0.75 | AD79: =IFERROR(INDEX($G$72:$R$83,MATCH($X79,$B$72:$B$83,0),MATCH(AD$67,$G$67:$R$67,0)), IFERROR(INDEX($G$72:$R$83,MATCH($X79,$B$72:$B$83,0),MATCH(AD$67,$G$68:$R$68,0)), IFERROR(INDEX($G$72:$R$83,MATCH($X79,$B$72:$B$83,0),MATCH(AD$67,$G$69:$R$69,0)), IFERROR(INDEX($G$72:$R$83,MATCH($X79,$B$72:$B$83,0),MATCH(AD$67,$G$70:$R$70,0)), IFERROR(INDEX($G$72:$R$83,MATCH($X79,$C$72:$C$83,0),MATCH(AD$67,$G$67:$R$67,0)), IFERROR(INDEX($G$72:$R$83,MATCH($X79,$C$72:$C$83,0),MATCH(AD$67,$G$68:$R$68,0)), IFERROR(INDEX($G$72:$R$83,MATCH($X79,$C$72:$C$83,0),MATCH(AD$67,$G$69:$R$69,0)), IFERROR(INDEX($G$72:$R$83,MATCH($X79,$C$72:$C$83,0),MATCH(AD$67,$G$70:$R$70,0)), IFERROR(INDEX($G$72:$R$83,MATCH($X79,$D$72:$D$83,0),MATCH(AD$67,$G$67:$R$67,0)), IFERROR(INDEX($G$72:$R$83,MATCH($X79,$D$72:$D$83,0),MATCH(AD$67,$G$68:$R$68,0)), IFERROR(INDEX($G$72:$R$83,MATCH($X79,$D$72:$D$83,0),MATCH(AD$67,$G$69:$R$69,0)), IFERROR(INDEX($G$72:$R$83,MATCH($X79,$D$72:$D$83,0),MATCH(AD$67,$G$70:$R$70,0)), IFERROR(INDEX($G$72:$R$83,MATCH($X79,$E$72:$E$83,0),MATCH(AD$67,$G$67:$R$67,0)), IFERROR(INDEX($G$72:$R$83,MATCH($X79,$E$72:$E$83,0),MATCH(AD$67,$G$68:$R$68,0)), IFERROR(INDEX($G$72:$R$83,MATCH($X79,$E$72:$E$83,0),MATCH(AD$67,$G$69:$R$69,0)), INDEX($G$72:$R$83,MATCH($X79,$E$72:$E$83,0),MATCH(AD$67,$G$70:$R$70,0))))))))))))))))) -> 0.75 | AE79: =IFERROR(INDEX($G$72:$R$83,MATCH($X79,$B$72:$B$83,0),MATCH(AE$67,$G$67:$R$67,0)), IFERROR(INDEX($G$72:$R$83,MATCH($X79,$B$72:$B$83,0),MATCH(AE$67,$G$68:$R$68,0)), IFERROR(INDEX($G$72:$R$83,MATCH($X79,$B$72:$B$83,0),MATCH(AE$67,$G$69:$R$69,0)), IFERROR(INDEX($G$72:$R$83,MATCH($X79,$B$72:$B$83,0),MATCH(AE$67,$G$70:$R$70,0)), IFERROR(INDEX($G$72:$R$83,MATCH($X79,$C$72:$C$83,0),MATCH(AE$67,$G$67:$R$67,0)), IFERROR(INDEX($G$72:$R$83,MATCH($X79,$C$72:$C$83,0),MATCH(AE$67,$G$68:$R$68,0)), IFERROR(INDEX($G$72:$R$83,MATCH($X79,$C$72:$C$83,0),MATCH(AE$67,$G$69:$R$69,0)), IFERROR(INDEX($G$72:$R$83,MATCH($X79,$C$72:$C$83,0),MATCH(AE$67,$G$70:$R$70,0)), IFERROR(INDEX($G$72:$R$83,MATCH($X79,$D$72:$D$83,0),MATCH(AE$67,$G$67:$R$67,0)), IFERROR(INDEX($G$72:$R$83,MATCH($X79,$D$72:$D$83,0),MATCH(AE$67,$G$68:$R$68,0)), IFERROR(INDEX($G$72:$R$83,MATCH($X79,$D$72:$D$83,0),MATCH(AE$67,$G$69:$R$69,0)), IFERROR(INDEX($G$72:$R$83,MATCH($X79,$D$72:$D$83,0),MATCH(AE$67,$G$70:$R$70,0)), IFERROR(INDEX($G$72:$R$83,MATCH($X79,$E$72:$E$83,0),MATCH(AE$67,$G$67:$R$67,0)), IFERROR(INDEX($G$72:$R$83,MATCH($X79,$E$72:$E$83,0),MATCH(AE$67,$G$68:$R$68,0)), IFERROR(INDEX($G$72:$R$83,MATCH($X79,$E$72:$E$83,0),MATCH(AE$67,$G$69:$R$69,0)), INDEX($G$72:$R$83,MATCH($X79,$E$72:$E$83,0),MATCH(AE$67,$G$70:$R$70,0))))))))))))))))) -> 0.75 | AF79: =IFERROR(INDEX($G$72:$R$83,MATCH($X79,$B$72:$B$83,0),MATCH(AF$67,$G$67:$R$67,0)), IFERROR(INDEX($G$72:$R$83,MATCH($X79,$B$72:$B$83,0),MATCH(AF$67,$G$68:$R$68,0)), IFERROR(INDEX($G$72:$R$83,MATCH($X79,$B$72:$B$83,0),MATCH(AF$67,$G$69:$R$69,0)), IFERROR(INDEX($G$72:$R$83,MATCH($X79,$B$72:$B$83,0),MATCH(AF$67,$G$70:$R$70,0)), IFERROR(INDEX($G$72:$R$83,MATCH($X79,$C$72:$C$83,0),MATCH(AF$67,$G$67:$R$67,0)), IFERROR(INDEX($G$72:$R$83,MATCH($X79,$C$72:$C$83,0),MATCH(AF$67,$G$68:$R$68,0)), IFERROR(INDEX($G$72:$R$83,MATCH($X79,$C$72:$C$83,0),MATCH(AF$67,$G$69:$R$69,0)), IFERROR(INDEX($G$72:$R$83,MATCH($X79,$C$72:$C$83,0),MATCH(AF$67,$G$70:$R$70,0)), IFERROR(INDEX($G$72:$R$83,MATCH($X79,$D$72:$D$83,0),MATCH(AF$67,$G$67:$R$67,0)), IFERROR(INDEX($G$72:$R$83,MATCH($X79,$D$72:$D$83,0),MATCH(AF$67,$G$68:$R$68,0)), IFERROR(INDEX($G$72:$R$83,MATCH($X79,$D$72:$D$83,0),MATCH(AF$67,$G$69:$R$69,0)), IFERROR(INDEX($G$72:$R$83,MATCH($X79,$D$72:$D$83,0),MATCH(AF$67,$G$70:$R$70,0)), IFERROR(INDEX($G$72:$R$83,MATCH($X79,$E$72:$E$83,0),MATCH(AF$67,$G$67:$R$67,0)), IFERROR(INDEX($G$72:$R$83,MATCH($X79,$E$72:$E$83,0),MATCH(AF$67,$G$68:$R$68,0)), IFERROR(INDEX($G$72:$R$83,MATCH($X79,$E$72:$E$83,0),MATCH(AF$67,$G$69:$R$69,0)), INDEX($G$72:$R$83,MATCH($X79,$E$72:$E$83,0),MATCH(AF$67,$G$70:$R$70,0))))))))))))))))) -> 0.75 | ... AS79: =IFERROR(INDEX($G$72:$R$83,MATCH($X79,$B$72:$B$83,0),MATCH(AS$67,$G$67:$R$67,0)), IFERROR(INDEX($G$72:$R$83,MATCH($X79,$B$72:$B$83,0),MATCH(AS$67,$G$68:$R$68,0)), IFERROR(INDEX($G$72:$R$83,MATCH($X79,$B$72:$B$83,0),MATCH(AS$67,$G$69:$R$69,0)), IFERROR(INDEX($G$72:$R$83,MATCH($X79,$B$72:$B$83,0),MATCH(AS$67,$G$70:$R$70,0)), IFERROR(INDEX($G$72:$R$83,MATCH($X79,$C$72:$C$83,0),MATCH(AS$67,$G$67:$R$67,0)), IFERROR(INDEX($G$72:$R$83,MATCH($X79,$C$72:$C$83,0),MATCH(AS$67,$G$68:$R$68,0)), IFERROR(INDEX($G$72:$R$83,MATCH($X79,$C$72:$C$83,0),MATCH(AS$67,$G$69:$R$69,0)), IFERROR(INDEX($G$72:$R$83,MATCH($X79,$C$72:$C$83,0),MATCH(AS$67,$G$70:$R$70,0)), IFERROR(INDEX($G$72:$R$83,MATCH($X79,$D$72:$D$83,0),MATCH(AS$67,$G$67:$R$67,0)), IFERROR(INDEX($G$72:$R$83,MATCH($X79,$D$72:$D$83,0),MATCH(AS$67,$G$68:$R$68,0)), IFERROR(INDEX($G$72:$R$83,MATCH($X79,$D$72:$D$83,0),MATCH(AS$67,$G$69:$R$69,0)), IFERROR(INDEX($G$72:$R$83,MATCH($X79,$D$72:$D$83,0),MATCH(AS$67,$G$70:$R$70,0)), IFERROR(INDEX($G$72:$R$83,MATCH($X79,$E$72:$E$83,0),MATCH(AS$67,$G$67:$R$67,0)), IFERROR(INDEX($G$72:$R$83,MATCH($X79,$E$72:$E$83,0),MATCH(AS$67,$G$68:$R$68,0)), IFERROR(INDEX($G$72:$R$83,MATCH($X79,$E$72:$E$83,0),MATCH(AS$67,$G$69:$R$69,0)), INDEX($G$72:$R$83,MATCH($X79,$E$72:$E$83,0),MATCH(AS$67,$G$70:$R$70,0))))))))))))))))) -> -0.09
B80: Real Estate (via partnerships, equity) | F80: U.S. Core Real Estate | G80: -0.27 | H80: 0.19 | I80: -0.09 | J80: 0 | K80: 0.35 | L80: 0.44 | M80: -0.16 | N80: 0.2 | O80: 1 | P80: 0.31 | Q80: 0.34 | R80: 0.43 | X80: Commercial Mortgage-Backed Securities | Y80: =IFERROR(INDEX($G$72:$R$83,MATCH($X80,$B$72:$B$83,0),MATCH(Y$67,$G$67:$R$67,0)), IFERROR(INDEX($G$72:$R$83,MATCH($X80,$B$72:$B$83,0),MATCH(Y$67,$G$68:$R$68,0)), IFERROR(INDEX($G$72:$R$83,MATCH($X80,$B$72:$B$83,0),MATCH(Y$67,$G$69:$R$69,0)), IFERROR(INDEX($G$72:$R$83,MATCH($X80,$B$72:$B$83,0),MATCH(Y$67,$G$70:$R$70,0)), IFERROR(INDEX($G$72:$R$83,MATCH($X80,$C$72:$C$83,0),MATCH(Y$67,$G$67:$R$67,0)), IFERROR(INDEX($G$72:$R$83,MATCH($X80,$C$72:$C$83,0),MATCH(Y$67,$G$68:$R$68,0)), IFERROR(INDEX($G$72:$R$83,MATCH($X80,$C$72:$C$83,0),MATCH(Y$67,$G$69:$R$69,0)), IFERROR(INDEX($G$72:$R$83,MATCH($X80,$C$72:$C$83,0),MATCH(Y$67,$G$70:$R$70,0)), IFERROR(INDEX($G$72:$R$83,MATCH($X80,$D$72:$D$83,0),MATCH(Y$67,$G$67:$R$67,0)), IFERROR(INDEX($G$72:$R$83,MATCH($X80,$D$72:$D$83,0),MATCH(Y$67,$G$68:$R$68,0)), IFERROR(INDEX($G$72:$R$83,MATCH($X80,$D$72:$D$83,0),MATCH(Y$67,$G$69:$R$69,0)), IFERROR(INDEX($G$72:$R$83,MATCH($X80,$D$72:$D$83,0),MATCH(Y$67,$G$70:$R$70,0)), IFERROR(INDEX($G$72:$R$83,MATCH($X80,$E$72:$E$83,0),MATCH(Y$67,$G$67:$R$67,0)), IFERROR(INDEX($G$72:$R$83,MATCH($X80,$E$72:$E$83,0),MATCH(Y$67,$G$68:$R$68,0)), IFERROR(INDEX($G$72:$R$83,MATCH($X80,$E$72:$E$83,0),MATCH(Y$67,$G$69:$R$69,0)), INDEX($G$72:$R$83,MATCH($X80,$E$72:$E$83,0),MATCH(Y$67,$G$70:$R$70,0))))))))))))))))) -> 0.78 | Z80: =IFERROR(INDEX($G$72:$R$83,MATCH($X80,$B$72:$B$83,0),MATCH(Z$67,$G$67:$R$67,0)), IFERROR(INDEX($G$72:$R$83,MATCH($X80,$B$72:$B$83,0),MATCH(Z$67,$G$68:$R$68,0)), IFERROR(INDEX($G$72:$R$83,MATCH($X80,$B$72:$B$83,0),MATCH(Z$67,$G$69:$R$69,0)), IFERROR(INDEX($G$72:$R$83,MATCH($X80,$B$72:$B$83,0),MATCH(Z$67,$G$70:$R$70,0)), IFERROR(INDEX($G$72:$R$83,MATCH($X80,$C$72:$C$83,0),MATCH(Z$67,$G$67:$R$67,0)), IFERROR(INDEX($G$72:$R$83,MATCH($X80,$C$72:$C$83,0),MATCH(Z$67,$G$68:$R$68,0)), IFERROR(INDEX($G$72:$R$83,MATCH($X80,$C$72:$C$83,0),MATCH(Z$67,$G$69:$R$69,0)), IFERROR(INDEX($G$72:$R$83,MATCH($X80,$C$72:$C$83,0),MATCH(Z$67,$G$70:$R$70,0)), IFERROR(INDEX($G$72:$R$83,MATCH($X80,$D$72:$D$83,0),MATCH(Z$67,$G$67:$R$67,0)), IFERROR(INDEX($G$72:$R$83,MATCH($X80,$D$72:$D$83,0),MATCH(Z$67,$G$68:$R$68,0)), IFERROR(INDEX($G$72:$R$83,MATCH($X80,$D$72:$D$83,0),MATCH(Z$67,$G$69:$R$69,0)), IFERROR(INDEX($G$72:$R$83,MATCH($X80,$D$72:$D$83,0),MATCH(Z$67,$G$70:$R$70,0)), IFERROR(INDEX($G$72:$R$83,MATCH($X80,$E$72:$E$83,0),MATCH(Z$67,$G$67:$R$67,0)), IFERROR(INDEX($G$72:$R$83,MATCH($X80,$E$72:$E$83,0),MATCH(Z$67,$G$68:$R$68,0)), IFERROR(INDEX($G$72:$R$83,MATCH($X80,$E$72:$E$83,0),MATCH(Z$67,$G$69:$R$69,0)), INDEX($G$72:$R$83,MATCH($X80,$E$72:$E$83,0),MATCH(Z$67,$G$70:$R$70,0))))))))))))))))) -> 0.74 | AA80: =IFERROR(INDEX($G$72:$R$83,MATCH($X80,$B$72:$B$83,0),MATCH(AA$67,$G$67:$R$67,0)), IFERROR(INDEX($G$72:$R$83,MATCH($X80,$B$72:$B$83,0),MATCH(AA$67,$G$68:$R$68,0)), IFERROR(INDEX($G$72:$R$83,MATCH($X80,$B$72:$B$83,0),MATCH(AA$67,$G$69:$R$69,0)), IFERROR(INDEX($G$72:$R$83,MATCH($X80,$B$72:$B$83,0),MATCH(AA$67,$G$70:$R$70,0)), IFERROR(INDEX($G$72:$R$83,MATCH($X80,$C$72:$C$83,0),MATCH(AA$67,$G$67:$R$67,0)), IFERROR(INDEX($G$72:$R$83,MATCH($X80,$C$72:$C$83,0),MATCH(AA$67,$G$68:$R$68,0)), IFERROR(INDEX($G$72:$R$83,MATCH($X80,$C$72:$C$83,0),MATCH(AA$67,$G$69:$R$69,0)), IFERROR(INDEX($G$72:$R$83,MATCH($X80,$C$72:$C$83,0),MATCH(AA$67,$G$70:$R$70,0)), IFERROR(INDEX($G$72:$R$83,MATCH($X80,$D$72:$D$83,0),MATCH(AA$67,$G$67:$R$67,0)), IFERROR(INDEX($G$72:$R$83,MATCH($X80,$D$72:$D$83,0),MATCH(AA$67,$G$68:$R$68,0)), IFERROR(INDEX($G$72:$R$83,MATCH($X80,$D$72:$D$83,0),MATCH(AA$67,$G$69:$R$69,0)), IFERROR(INDEX($G$72:$R$83,MATCH($X80,$D$72:$D$83,0),MATCH(AA$67,$G$70:$R$70,0)), IFERROR(INDEX($G$72:$R$83,MATCH($X80,$E$72:$E$83,0),MATCH(AA$67,$G$67:$R$67,0)), IFERROR(INDEX($G$72:$R$83,MATCH($X80,$E$72:$E$83,0),MATCH(AA$67,$G$68:$R$68,0)), IFERROR(INDEX($G$72:$R$83,MATCH($X80,$E$72:$E$83,0),MATCH(AA$67,$G$69:$R$69,0)), INDEX($G$72:$R$83,MATCH($X80,$E$72:$E$83,0),MATCH(AA$67,$G$70:$R$70,0))))))))))))))))) -> 0.69 | AB80: =IFERROR(INDEX($G$72:$R$83,MATCH($X80,$B$72:$B$83,0),MATCH(AB$67,$G$67:$R$67,0)), IFERROR(INDEX($G$72:$R$83,MATCH($X80,$B$72:$B$83,0),MATCH(AB$67,$G$68:$R$68,0)), IFERROR(INDEX($G$72:$R$83,MATCH($X80,$B$72:$B$83,0),MATCH(AB$67,$G$69:$R$69,0)), IFERROR(INDEX($G$72:$R$83,MATCH($X80,$B$72:$B$83,0),MATCH(AB$67,$G$70:$R$70,0)), IFERROR(INDEX($G$72:$R$83,MATCH($X80,$C$72:$C$83,0),MATCH(AB$67,$G$67:$R$67,0)), IFERROR(INDEX($G$72:$R$83,MATCH($X80,$C$72:$C$83,0),MATCH(AB$67,$G$68:$R$68,0)), IFERROR(INDEX($G$72:$R$83,MATCH($X80,$C$72:$C$83,0),MATCH(AB$67,$G$69:$R$69,0)), IFERROR(INDEX($G$72:$R$83,MATCH($X80,$C$72:$C$83,0),MATCH(AB$67,$G$70:$R$70,0)), IFERROR(INDEX($G$72:$R$83,MATCH($X80,$D$72:$D$83,0),MATCH(AB$67,$G$67:$R$67,0)), IFERROR(INDEX($G$72:$R$83,MATCH($X80,$D$72:$D$83,0),MATCH(AB$67,$G$68:$R$68,0)), IFERROR(INDEX($G$72:$R$83,MATCH($X80,$D$72:$D$83,0),MATCH(AB$67,$G$69:$R$69,0)), IFERROR(INDEX($G$72:$R$83,MATCH($X80,$D$72:$D$83,0),MATCH(AB$67,$G$70:$R$70,0)), IFERROR(INDEX($G$72:$R$83,MATCH($X80,$E$72:$E$83,0),MATCH(AB$67,$G$67:$R$67,0)), IFERROR(INDEX($G$72:$R$83,MATCH($X80,$E$72:$E$83,0),MATCH(AB$67,$G$68:$R$68,0)), IFERROR(INDEX($G$72:$R$83,MATCH($X80,$E$72:$E$83,0),MATCH(AB$67,$G$69:$R$69,0)), INDEX($G$72:$R$83,MATCH($X80,$E$72:$E$83,0),MATCH(AB$67,$G$70:$R$70,0))))))))))))))))) -> 0.7 | AC80: =IFERROR(INDEX($G$72:$R$83,MATCH($X80,$B$72:$B$83,0),MATCH(AC$67,$G$67:$R$67,0)), IFERROR(INDEX($G$72:$R$83,MATCH($X80,$B$72:$B$83,0),MATCH(AC$67,$G$68:$R$68,0)), IFERROR(INDEX($G$72:$R$83,MATCH($X80,$B$72:$B$83,0),MATCH(AC$67,$G$69:$R$69,0)), IFERROR(INDEX($G$72:$R$83,MATCH($X80,$B$72:$B$83,0),MATCH(AC$67,$G$70:$R$70,0)), IFERROR(INDEX($G$72:$R$83,MATCH($X80,$C$72:$C$83,0),MATCH(AC$67,$G$67:$R$67,0)), IFERROR(INDEX($G$72:$R$83,MATCH($X80,$C$72:$C$83,0),MATCH(AC$67,$G$68:$R$68,0)), IFERROR(INDEX($G$72:$R$83,MATCH($X80,$C$72:$C$83,0),MATCH(AC$67,$G$69:$R$69,0)), IFERROR(INDEX($G$72:$R$83,MATCH($X80,$C$72:$C$83,0),MATCH(AC$67,$G$70:$R$70,0)), IFERROR(INDEX($G$72:$R$83,MATCH($X80,$D$72:$D$83,0),MATCH(AC$67,$G$67:$R$67,0)), IFERROR(INDEX($G$72:$R$83,MATCH($X80,$D$72:$D$83,0),MATCH(AC$67,$G$68:$R$68,0)), IFERROR(INDEX($G$72:$R$83,MATCH($X80,$D$72:$D$83,0),MATCH(AC$67,$G$69:$R$69,0)), IFERROR(INDEX($G$72:$R$83,MATCH($X80,$D$72:$D$83,0),MATCH(AC$67,$G$70:$R$70,0)), IFERROR(INDEX($G$72:$R$83,MATCH($X80,$E$72:$E$83,0),MATCH(AC$67,$G$67:$R$67,0)), IFERROR(INDEX($G$72:$R$83,MATCH($X80,$E$72:$E$83,0),MATCH(AC$67,$G$68:$R$68,0)), IFERROR(INDEX($G$72:$R$83,MATCH($X80,$E$72:$E$83,0),MATCH(AC$67,$G$69:$R$69,0)), INDEX($G$72:$R$83,MATCH($X80,$E$72:$E$83,0),MATCH(AC$67,$G$70:$R$70,0))))))))))))))))) -> 0.75 | AD80: =IFERROR(INDEX($G$72:$R$83,MATCH($X80,$B$72:$B$83,0),MATCH(AD$67,$G$67:$R$67,0)), IFERROR(INDEX($G$72:$R$83,MATCH($X80,$B$72:$B$83,0),MATCH(AD$67,$G$68:$R$68,0)), IFERROR(INDEX($G$72:$R$83,MATCH($X80,$B$72:$B$83,0),MATCH(AD$67,$G$69:$R$69,0)), IFERROR(INDEX($G$72:$R$83,MATCH($X80,$B$72:$B$83,0),MATCH(AD$67,$G$70:$R$70,0)), IFERROR(INDEX($G$72:$R$83,MATCH($X80,$C$72:$C$83,0),MATCH(AD$67,$G$67:$R$67,0)), IFERROR(INDEX($G$72:$R$83,MATCH($X80,$C$72:$C$83,0),MATCH(AD$67,$G$68:$R$68,0)), IFERROR(INDEX($G$72:$R$83,MATCH($X80,$C$72:$C$83,0),MATCH(AD$67,$G$69:$R$69,0)), IFERROR(INDEX($G$72:$R$83,MATCH($X80,$C$72:$C$83,0),MATCH(AD$67,$G$70:$R$70,0)), IFERROR(INDEX($G$72:$R$83,MATCH($X80,$D$72:$D$83,0),MATCH(AD$67,$G$67:$R$67,0)), IFERROR(INDEX($G$72:$R$83,MATCH($X80,$D$72:$D$83,0),MATCH(AD$67,$G$68:$R$68,0)), IFERROR(INDEX($G$72:$R$83,MATCH($X80,$D$72:$D$83,0),MATCH(AD$67,$G$69:$R$69,0)), IFERROR(INDEX($G$72:$R$83,MATCH($X80,$D$72:$D$83,0),MATCH(AD$67,$G$70:$R$70,0)), IFERROR(INDEX($G$72:$R$83,MATCH($X80,$E$72:$E$83,0),MATCH(AD$67,$G$67:$R$67,0)), IFERROR(INDEX($G$72:$R$83,MATCH($X80,$E$72:$E$83,0),MATCH(AD$67,$G$68:$R$68,0)), IFERROR(INDEX($G$72:$R$83,MATCH($X80,$E$72:$E$83,0),MATCH(AD$67,$G$69:$R$69,0)), INDEX($G$72:$R$83,MATCH($X80,$E$72:$E$83,0),MATCH(AD$67,$G$70:$R$70,0))))))))))))))))) -> 0.75 | AE80: =IFERROR(INDEX($G$72:$R$83,MATCH($X80,$B$72:$B$83,0),MATCH(AE$67,$G$67:$R$67,0)), IFERROR(INDEX($G$72:$R$83,MATCH($X80,$B$72:$B$83,0),MATCH(AE$67,$G$68:$R$68,0)), IFERROR(INDEX($G$72:$R$83,MATCH($X80,$B$72:$B$83,0),MATCH(AE$67,$G$69:$R$69,0)), IFERROR(INDEX($G$72:$R$83,MATCH($X80,$B$72:$B$83,0),MATCH(AE$67,$G$70:$R$70,0)), IFERROR(INDEX($G$72:$R$83,MATCH($X80,$C$72:$C$83,0),MATCH(AE$67,$G$67:$R$67,0)), IFERROR(INDEX($G$72:$R$83,MATCH($X80,$C$72:$C$83,0),MATCH(AE$67,$G$68:$R$68,0)), IFERROR(INDEX($G$72:$R$83,MATCH($X80,$C$72:$C$83,0),MATCH(AE$67,$G$69:$R$69,0)), IFERROR(INDEX($G$72:$R$83,MATCH($X80,$C$72:$C$83,0),MATCH(AE$67,$G$70:$R$70,0)), IFERROR(INDEX($G$72:$R$83,MATCH($X80,$D$72:$D$83,0),MATCH(AE$67,$G$67:$R$67,0)), IFERROR(INDEX($G$72:$R$83,MATCH($X80,$D$72:$D$83,0),MATCH(AE$67,$G$68:$R$68,0)), IFERROR(INDEX($G$72:$R$83,MATCH($X80,$D$72:$D$83,0),MATCH(AE$67,$G$69:$R$69,0)), IFERROR(INDEX($G$72:$R$83,MATCH($X80,$D$72:$D$83,0),MATCH(AE$67,$G$70:$R$70,0)), IFERROR(INDEX($G$72:$R$83,MATCH($X80,$E$72:$E$83,0),MATCH(AE$67,$G$67:$R$67,0)), IFERROR(INDEX($G$72:$R$83,MATCH($X80,$E$72:$E$83,0),MATCH(AE$67,$G$68:$R$68,0)), IFERROR(INDEX($G$72:$R$83,MATCH($X80,$E$72:$E$83,0),MATCH(AE$67,$G$69:$R$69,0)), INDEX($G$72:$R$83,MATCH($X80,$E$72:$E$83,0),MATCH(AE$67,$G$70:$R$70,0))))))))))))))))) -> 0.75 | AF80: =IFERROR(INDEX($G$72:$R$83,MATCH($X80,$B$72:$B$83,0),MATCH(AF$67,$G$67:$R$67,0)), IFERROR(INDEX($G$72:$R$83,MATCH($X80,$B$72:$B$83,0),MATCH(AF$67,$G$68:$R$68,0)), IFERROR(INDEX($G$72:$R$83,MATCH($X80,$B$72:$B$83,0),MATCH(AF$67,$G$69:$R$69,0)), IFERROR(INDEX($G$72:$R$83,MATCH($X80,$B$72:$B$83,0),MATCH(AF$67,$G$70:$R$70,0)), IFERROR(INDEX($G$72:$R$83,MATCH($X80,$C$72:$C$83,0),MATCH(AF$67,$G$67:$R$67,0)), IFERROR(INDEX($G$72:$R$83,MATCH($X80,$C$72:$C$83,0),MATCH(AF$67,$G$68:$R$68,0)), IFERROR(INDEX($G$72:$R$83,MATCH($X80,$C$72:$C$83,0),MATCH(AF$67,$G$69:$R$69,0)), IFERROR(INDEX($G$72:$R$83,MATCH($X80,$C$72:$C$83,0),MATCH(AF$67,$G$70:$R$70,0)), IFERROR(INDEX($G$72:$R$83,MATCH($X80,$D$72:$D$83,0),MATCH(AF$67,$G$67:$R$67,0)), IFERROR(INDEX($G$72:$R$83,MATCH($X80,$D$72:$D$83,0),MATCH(AF$67,$G$68:$R$68,0)), IFERROR(INDEX($G$72:$R$83,MATCH($X80,$D$72:$D$83,0),MATCH(AF$67,$G$69:$R$69,0)), IFERROR(INDEX($G$72:$R$83,MATCH($X80,$D$72:$D$83,0),MATCH(AF$67,$G$70:$R$70,0)), IFERROR(INDEX($G$72:$R$83,MATCH($X80,$E$72:$E$83,0),MATCH(AF$67,$G$67:$R$67,0)), IFERROR(INDEX($G$72:$R$83,MATCH($X80,$E$72:$E$83,0),MATCH(AF$67,$G$68:$R$68,0)), IFERROR(INDEX($G$72:$R$83,MATCH($X80,$E$72:$E$83,0),MATCH(AF$67,$G$69:$R$69,0)), INDEX($G$72:$R$83,MATCH($X80,$E$72:$E$83,0),MATCH(AF$67,$G$70:$R$70,0))))))))))))))))) -> 0.75 | ... AS80: =IFERROR(INDEX($G$72:$R$83,MATCH($X80,$B$72:$B$83,0),MATCH(AS$67,$G$67:$R$67,0)), IFERROR(INDEX($G$72:$R$83,MATCH($X80,$B$72:$B$83,0),MATCH(AS$67,$G$68:$R$68,0)), IFERROR(INDEX($G$72:$R$83,MATCH($X80,$B$72:$B$83,0),MATCH(AS$67,$G$69:$R$69,0)), IFERROR(INDEX($G$72:$R$83,MATCH($X80,$B$72:$B$83,0),MATCH(AS$67,$G$70:$R$70,0)), IFERROR(INDEX($G$72:$R$83,MATCH($X80,$C$72:$C$83,0),MATCH(AS$67,$G$67:$R$67,0)), IFERROR(INDEX($G$72:$R$83,MATCH($X80,$C$72:$C$83,0),MATCH(AS$67,$G$68:$R$68,0)), IFERROR(INDEX($G$72:$R$83,MATCH($X80,$C$72:$C$83,0),MATCH(AS$67,$G$69:$R$69,0)), IFERROR(INDEX($G$72:$R$83,MATCH($X80,$C$72:$C$83,0),MATCH(AS$67,$G$70:$R$70,0)), IFERROR(INDEX($G$72:$R$83,MATCH($X80,$D$72:$D$83,0),MATCH(AS$67,$G$67:$R$67,0)), IFERROR(INDEX($G$72:$R$83,MATCH($X80,$D$72:$D$83,0),MATCH(AS$67,$G$68:$R$68,0)), IFERROR(INDEX($G$72:$R$83,MATCH($X80,$D$72:$D$83,0),MATCH(AS$67,$G$69:$R$69,0)), IFERROR(INDEX($G$72:$R$83,MATCH($X80,$D$72:$D$83,0),MATCH(AS$67,$G$70:$R$70,0)), IFERROR(INDEX($G$72:$R$83,MATCH($X80,$E$72:$E$83,0),MATCH(AS$67,$G$67:$R$67,0)), IFERROR(INDEX($G$72:$R$83,MATCH($X80,$E$72:$E$83,0),MATCH(AS$67,$G$68:$R$68,0)), IFERROR(INDEX($G$72:$R$83,MATCH($X80,$E$72:$E$83,0),MATCH(AS$67,$G$69:$R$69,0)), INDEX($G$72:$R$83,MATCH($X80,$E$72:$E$83,0),MATCH(AS$67,$G$70:$R$70,0))))))))))))))))) -> -0.09
